Workbook

Sheet Read Me
A1: Tunduma Water Supply – Zone Calculator
A2: Hydraulic analysis from the Momba River intake to the Tunduma tanks, split by zone. Every result is a live Excel formula.
A4: WHEN YOU RECEIVE THE REAL LEVELS – 4 STEPS
A5: Step 1 – sheet 'Levels' | B5: type ground, floor, MINIMUM and MAXIMUM water level, inlet level and capacity of every tank / sump / river. Read the 'Check' column: it must say OK.
A6: Step 2 – sheet 'Demands' | B6: type the daily demand of each tank and the WTP losses (if they changed).
A7: Step 3 – zone sheets Z1 … Z7 | B7: only if pipes or pumps changed: DN, length, C, hours, number of pumps, efficiencies, ER duty (blue cells).
A8: Step 4 – sheet 'Summary' | B8: read the pump heads (at minimum and maximum suction level), gravity surplus, tank results and storage. Each zone sheet explains its result in section F.
A9: Optional – Python and PDFs | B9: run 'python levels_from_excel.py results/Tunduma_Zone_Calculator.xlsx' to copy the levels into tunduma_config.json, then 'python run_analysis.py' and the PDF scripts to regenerate every report with the same levels.
A11: COLOUR LEGEND
A12: Blue text, yellow fill | B12: input – edit these
A13: Black text | B13: formula – do not overwrite
A14: Green text | B14: link from another sheet
A15: Green fill, bold | B15: key result
A17: WHY MINIMUM AND MAXIMUM LEVELS MATTER
A18: Pumped zone, design case | B18: suction tank at its MINIMUM level → the pump must lift the most → TDH max (used to size pump and motor).
A19: Pumped zone, low-head case | B19: suction tank at its MAXIMUM level → least lift → TDH min (the pump must also run safely here: it gives more flow unless throttled / VFD).
A20: Gravity zone, design case | B20: supplying tank at its MINIMUM level → least energy available → must still reach every tank (surplus ≥ 0).
A21: Gravity zone, high case | B21: supplying tank at its MAXIMUM level → most energy → the valve must burn the biggest surplus; static pressure (pipe class) uses this level.
A22: Receiving tank | B22: water must arrive at the inlet level (or the maximum level if the inlet is lower / submerged) plus a small residual head.
A24: ZONES (split at every free water surface)
A25: Z1 River-Intake | B25: gravity: Momba River → intake sump (abstraction pipe)
A26: Z2 Intake-Grit | B26: pumped: low-lift pumps, intake sump → grit tank
A27: Z3 Grit-WTP | B27: pumped: high-lift pumps, grit tank → WTP inlet (raw-water main)
A28: Z4 WTP-Ikana | B28: pumped: WTP clear-water pumps → Ikana GBR (treated-water rising main)
A29: Z5 Ikana-Nkangamo | B29: gravity: Ikana GBR → Nkangamo BPS sump
A30: Z6 Nkangamo-Uhuru | B30: pumped: Nkangamo BPS → J-001N (ESR), J-002N (GSR01), J-003N (Ipito) → Uhuru Park GBR
A31: Z7 Uhuru-Chapwa | B31: gravity: Uhuru Park GBR → J-004N → Makambini GSR03 and Chapwa GSR04
A33: METHOD (Bernoulli / energy equation between two water surfaces)
A34: z1 + p1/ρg + V1²/2g + Hp = z2 + p2/ρg + V2²/2g + hL | B34: at tank surfaces p = 0 and V ≈ 0
A35: Pumped zone | B35: Hp = H_req − z1 ; TDH = Hp + station losses
A36: Gravity zone | B36: surplus = z1 − H_req (≥ 0 OK, burnt by an FCV/PRV; < 0 short of head)
A37: H_req (head needed at zone start) | B37: largest of: each destination arrival level + residual + losses on the way, and each critical point crown + min. pressure + losses up to it
A38: Friction (Hazen-Williams) | B38: hf = 10.67 L Q^1.852 / (C^1.852 D^4.8704) ; hL = hf × (1 + minor-loss factor)
A39: Pressure at a point | B39: p = HGL − pipe crown ; working = max(p, static level − crown) ; PN = smallest class ≥ working × 0.0981 bar/m
A40: Surge (Joukowsky) | B40: Δh = a V / g
A42: SOURCE OF THE STARTING VALUES
A43: Employer's Requirements | B43: flows, pipe sizes and lengths, pump duties, tank elevations and capacities.
A44: ASSUMED (to confirm) | B44: operating water levels, inlet levels, WTP inlet, C value, station losses, pipe cover – marked in 'Levels' column M and in cell notes.
A45: Check | B45: column 'Python model' on Summary = run_analysis.py with the starting inputs.

Sheet Levels
A1: Levels of every water surface – ENTER THE REAL LEVELS HERE
A2: Minimum and maximum water levels drive every zone. Blank inlet = the maximum level is used. All levels in m above datum (survey datum).
A4: ID | B4: Facility | C4: Role | D4: Ground level (m) | E4: Floor level (m) | F4: MINIMUM water level (m) | G4: MAXIMUM water level (m) | H4: Inlet level (m) | I4: Capacity (m³) | J4: Water depth (m) | K4: Plan area (m²) | L4: Arrival level used (m) | M4: Source / status | N4: Check
A5: MOMBA_RIVER | B5: Momba (Saisi) River | C5: source: minimum = dry-season low level, maximum = flood level | D5: 1363 | F5: 1361 | G5: 1364.5 | J5: =IF(OR(E5="",G5=""),"",G5-E5) | K5: =IF(OR(I5="",J5="",J5<=0),"",I5/J5) | L5: =IF(H5="",G5,MAX(H5,G5)) -> 1364.5 | M5: levels ASSUMED – confirm | N5: =IF(OR(F5="",G5=""),"ENTER MIN AND MAX",IF(G5<=F5,"MAX must be above MIN",IF(AND(E5<>"",F5<E5),"MIN below floor",IF(AND(H5<>"",H5<G5),"inlet below MAX – MAX used","OK")))) -> OK
A6: MOMBA_INTAKE | B6: Momba Intake - low lift PS | C6: intake sump: minimum = pump start/stop low level (submergence) | D6: 1365.94 | F6: 1360 | G6: 1364 | J6: =IF(OR(E6="",G6=""),"",G6-E6) | K6: =IF(OR(I6="",J6="",J6<=0),"",I6/J6) | L6: =F6 -> 1360 | M6: ER elevation/capacity; levels ASSUMED – confirm | N6: =IF(OR(F6="",G6=""),"ENTER MIN AND MAX",IF(G6<=F6,"MAX must be above MIN",IF(AND(E6<>"",F6<E6),"MIN below floor",IF(AND(H6<>"",H6<G6),"inlet below MAX – MAX used","OK")))) -> OK
A7: GRIT_TANK | B7: Grit tank - high lift PS | C7: grit tank = high-lift pump suction; receives low-lift flow | D7: 1365.94 | F7: 1366.5 | G7: 1368 | H7: 1368 | J7: =IF(OR(E7="",G7=""),"",G7-E7) | K7: =IF(OR(I7="",J7="",J7<=0),"",I7/J7) | L7: =IF(H7="",G7,MAX(H7,G7)) -> 1368 | M7: ER elevation/capacity; levels ASSUMED – confirm | N7: =IF(OR(F7="",G7=""),"ENTER MIN AND MAX",IF(G7<=F7,"MAX must be above MIN",IF(AND(E7<>"",F7<E7),"MIN below floor",IF(AND(H7<>"",H7<G7),"inlet below MAX – MAX used","OK")))) -> OK
A8: MOMBA_WTP | B8: Momba WTP (20,000 m3/day) | C8: inlet = aerator inlet; min/max/capacity = CLEAR-WATER tank (pump suction) | D8: 1372.1 | E8: 1368 | F8: 1368.5 | G8: 1373 | H8: 1378 | I8: 4000 | J8: =IF(OR(E8="",G8=""),"",G8-E8) -> 5 | K8: =IF(OR(I8="",J8="",J8<=0),"",I8/J8) -> 800 | L8: =IF(H8="",G8,H8) -> 1378 | M8: ER elevation/capacity; levels ASSUMED – confirm | N8: =IF(OR(F8="",G8=""),"ENTER MIN AND MAX",IF(G8<=F8,"MAX must be above MIN",IF(AND(E8<>"",F8<E8),"MIN below floor",IF(AND(H8<>"",H8<G8),"inlet below MAX – MAX used","OK")))) -> OK
A9: IKANA_GBR | B9: Ikana (Momba) GBR 3,000 m3 | C9: receives WTP pumping; supplies gravity main | D9: 1663 | E9: 1663 | F9: 1663.3 | G9: 1668 | I9: 3000 | J9: =IF(OR(E9="",G9=""),"",G9-E9) -> 5 | K9: =IF(OR(I9="",J9="",J9<=0),"",I9/J9) -> 600 | L9: =IF(H9="",G9,MAX(H9,G9)) -> 1668 | M9: ER elevation/capacity; levels ASSUMED – confirm | N9: =IF(OR(F9="",G9=""),"ENTER MIN AND MAX",IF(G9<=F9,"MAX must be above MIN",IF(AND(E9<>"",F9<E9),"MIN below floor",IF(AND(H9<>"",H9<G9),"inlet below MAX – MAX used","OK")))) -> OK
A10: NKANGAMO_BPS | B10: Nkangamo BPS | C10: BPS sump: receives gravity main; BPS pump suction | D10: 1555.5 | E10: 1552.5 | F10: 1553 | G10: 1557 | H10: 1557.5 | I10: 2000 | J10: =IF(OR(E10="",G10=""),"",G10-E10) -> 4.5 | K10: =IF(OR(I10="",J10="",J10<=0),"",I10/J10) -> 444.44444 | L10: =IF(H10="",G10,MAX(H10,G10)) -> 1557.5 | M10: ER elevation/capacity; levels ASSUMED – confirm | N10: =IF(OR(F10="",G10=""),"ENTER MIN AND MAX",IF(G10<=F10,"MAX must be above MIN",IF(AND(E10<>"",F10<E10),"MIN below floor",IF(AND(H10<>"",H10<G10),"inlet below MAX – MAX used","OK")))) -> OK
A11: UHURU_PARK_GBR | B11: Uhuru Park GBR 5,000 m3 (Tunduma) | C11: receives BPS main; supplies town + J-004N | D11: 1697.3 | E11: 1697.3 | F11: 1697.6 | G11: 1702.3 | I11: 5000 | J11: =IF(OR(E11="",G11=""),"",G11-E11) -> 5 | K11: =IF(OR(I11="",J11="",J11<=0),"",I11/J11) -> 1000 | L11: =IF(H11="",G11,MAX(H11,G11)) -> 1702.3 | M11: ER elevation/capacity; levels ASSUMED – confirm | N11: =IF(OR(F11="",G11=""),"ENTER MIN AND MAX",IF(G11<=F11,"MAX must be above MIN",IF(AND(E11<>"",F11<E11),"MIN below floor",IF(AND(H11<>"",H11<G11),"inlet below MAX – MAX used","OK")))) -> OK
A12: TUNDUMA_ESR | B12: Existing Tunduma ESR 120 m3 | C12: existing elevated tank (from J-001N) | D12: 1700 | E12: 1703.5 | F12: 1703.5 | G12: 1706.5 | I12: 120 | J12: =IF(OR(E12="",G12=""),"",G12-E12) -> 3 | K12: =IF(OR(I12="",J12="",J12<=0),"",I12/J12) -> 40 | L12: =IF(H12="",G12,MAX(H12,G12)) -> 1706.5 | M12: ER elevation/capacity; levels ASSUMED – confirm | N12: =IF(OR(F12="",G12=""),"ENTER MIN AND MAX",IF(G12<=F12,"MAX must be above MIN",IF(AND(E12<>"",F12<E12),"MIN below floor",IF(AND(H12<>"",H12<G12),"inlet below MAX – MAX used","OK")))) -> OK
A13: UHURU_GSR01 | B13: Existing Tunduma Uhuru GSR 01 500 m3 | C13: existing tank (from J-002N) | D13: 1698.4 | E13: 1698.4 | F13: 1698.4 | G13: 1701.4 | I13: 500 | J13: =IF(OR(E13="",G13=""),"",G13-E13) -> 3 | K13: =IF(OR(I13="",J13="",J13<=0),"",I13/J13) -> 166.66667 | L13: =IF(H13="",G13,MAX(H13,G13)) -> 1701.4 | M13: ER elevation/capacity; levels ASSUMED – confirm | N13: =IF(OR(F13="",G13=""),"ENTER MIN AND MAX",IF(G13<=F13,"MAX must be above MIN",IF(AND(E13<>"",F13<E13),"MIN below floor",IF(AND(H13<>"",H13<G13),"inlet below MAX – MAX used","OK")))) -> OK
A14: IPITO_GSR02 | B14: Existing Tunduma Ipito GSR 02 | C14: existing tank (from J-003N) | D14: 1681.2 | E14: 1681.2 | F14: 1681.2 | G14: 1684.2 | I14: 200 | J14: =IF(OR(E14="",G14=""),"",G14-E14) -> 3 | K14: =IF(OR(I14="",J14="",J14<=0),"",I14/J14) -> 66.666667 | L14: =IF(H14="",G14,MAX(H14,G14)) -> 1684.2 | M14: ER elevation/capacity; levels ASSUMED – confirm | N14: =IF(OR(F14="",G14=""),"ENTER MIN AND MAX",IF(G14<=F14,"MAX must be above MIN",IF(AND(E14<>"",F14<E14),"MIN below floor",IF(AND(H14<>"",H14<G14),"inlet below MAX – MAX used","OK")))) -> OK
A15: MAKAMBINI_GSR03 | B15: Existing Tunduma Makambini GSR 03 | C15: existing tank (from J-004N, gravity) | D15: 1655.7 | E15: 1655.7 | F15: 1655.7 | G15: 1658.7 | I15: 200 | J15: =IF(OR(E15="",G15=""),"",G15-E15) -> 3 | K15: =IF(OR(I15="",J15="",J15<=0),"",I15/J15) -> 66.666667 | L15: =IF(H15="",G15,MAX(H15,G15)) -> 1658.7 | M15: ER | N15: =IF(OR(F15="",G15=""),"ENTER MIN AND MAX",IF(G15<=F15,"MAX must be above MIN",IF(AND(E15<>"",F15<E15),"MIN below floor",IF(AND(H15<>"",H15<G15),"inlet below MAX – MAX used","OK")))) -> OK
A16: CHAPWA_GSR04 | B16: Existing Tunduma Chapwa GSR 04 | C16: existing tank (from J-004N, gravity) | D16: 1521.4 | E16: 1521.4 | F16: 1521.4 | G16: 1524.4 | I16: 200 | J16: =IF(OR(E16="",G16=""),"",G16-E16) -> 3 | K16: =IF(OR(I16="",J16="",J16<=0),"",I16/J16) -> 66.666667 | L16: =IF(H16="",G16,MAX(H16,G16)) -> 1524.4 | M16: ER | N16: =IF(OR(F16="",G16=""),"ENTER MIN AND MAX",IF(G16<=F16,"MAX must be above MIN",IF(AND(E16<>"",F16<E16),"MIN below floor",IF(AND(H16<>"",H16<G16),"inlet below MAX – MAX used","OK")))) -> OK
A18: Notes
A19: MINIMUM level = lowest operating level (pump cut-out / bottom water level, BWL). MAXIMUM level = top water level (TWL, overflow level).
A20: Floor and capacity are used for the depth/area check and the Storage sheet; they do not change the hydraulics.
A21: If the real inlet is a free fall above the tank, enter its level in 'Inlet level'; if it enters from below, leave it blank.
A22: After typing new levels, look at Summary – every zone, tank and pressure check updates.

Sheet Summary
A1: Summary of all zones
A2: Linked to the zone sheets (green). Change levels on 'Levels' and read the result here. 'Python model' = run_analysis.py with the starting inputs.
A4: Zones
A5: Zone | B5: Type | C5: Flow (l/s) | D5: Velocity first pipe (m/s) | E5: hL first pipe (m) | F5: H_req (m a.s.l.) | G5: Set by | H5: Design: TDH (m) / surplus (m) | I5: Start at MAX level: TDH (m) / surplus (m) | J5: ER duty head (m) | K5: TDH − ER (m) | L5: Shaft kW per pump | M5: Motor kW per pump | N5: Energy (kWh/d) | O5: Lowest pressure on route (m) | P5: Python model (m) | Q5: Excel − Python (m)
A6: Z1 River-Intake | B6: gravity | C6: ='Z1 River-Intake'!K12 -> 271.53253 | D6: ='Z1 River-Intake'!M12 -> 0.96034987 | E6: ='Z1 River-Intake'!P12 -> 0.17817373 | F6: ='Z1 River-Intake'!$B$25 -> 1360.1782 | G6: ='Z1 River-Intake'!$B$26 -> MOMBA_INTAKE | H6: ='Z1 River-Intake'!$B$27 -> 0.82182627 | I6: ='Z1 River-Intake'!$B$28 -> 4.3218263 | J6: – | K6: – | L6: – | M6: – | N6: – | O6: ='Z1 River-Intake'!$B$30 -> no points between tanks | P6: 0.82 | Q6: =H6-P6 -> 0.0018262659
A7: Z2 Intake-Grit | B7: pumped | C7: ='Z2 Intake-Grit'!K18 -> 271.53253 | D7: ='Z2 Intake-Grit'!M18 -> 0.96034987 | E7: ='Z2 Intake-Grit'!P18 -> 0.05345212 | F7: ='Z2 Intake-Grit'!$B$31 -> 1369.0535 | G7: ='Z2 Intake-Grit'!$B$32 -> GRIT_TANK | H7: ='Z2 Intake-Grit'!$B$34 -> 12.053452 | I7: ='Z2 Intake-Grit'!$B$35 -> 8.0534521 | J7: ='Z2 Intake-Grit'!$B$14 -> 10 | K7: ='Z2 Intake-Grit'!$B$46 -> 2.0534521 | L7: ='Z2 Intake-Grit'!$B$40 -> 42.809589 | M7: ='Z2 Intake-Grit'!$B$42 -> 55 | N7: ='Z2 Intake-Grit'!$B$43 -> 1001.9265 | O7: ='Z2 Intake-Grit'!$B$47 -> no points between tanks | P7: 12.05 | Q7: =H7-P7 -> 0.0034521202
A8: Z3 Grit-WTP | B8: pumped | C8: ='Z3 Grit-WTP'!K18 -> 271.53253 | D8: ='Z3 Grit-WTP'!M18 -> 0.96034987 | E8: ='Z3 Grit-WTP'!P18 -> 1.9216037 | F8: ='Z3 Grit-WTP'!$B$33 -> 1380.9216 | G8: ='Z3 Grit-WTP'!$B$34 -> MOMBA_WTP | H8: ='Z3 Grit-WTP'!$B$36 -> 17.421604 | I8: ='Z3 Grit-WTP'!$B$37 -> 15.921604 | J8: ='Z3 Grit-WTP'!$B$14 -> 25 | K8: ='Z3 Grit-WTP'!$B$48 -> -7.5783963 | L8: ='Z3 Grit-WTP'!$B$42 -> 61.87536 | M8: ='Z3 Grit-WTP'!$B$44 -> 75 | N8: ='Z3 Grit-WTP'!$B$45 -> 1448.1467 | O8: ='Z3 Grit-WTP'!$B$49 -> 8.3046103 | P8: 17.42 | Q8: =H8-P8 -> 0.0016037227
A9: Z4 WTP-Ikana | B9: pumped | C9: ='Z4 WTP-Ikana'!K18 -> 252.52525 | D9: ='Z4 WTP-Ikana'!M18 -> 0.89312538 | E9: ='Z4 WTP-Ikana'!P18 -> 30.63242 | F9: ='Z4 WTP-Ikana'!$B$33 -> 1699.6324 | G9: ='Z4 WTP-Ikana'!$B$34 -> IKANA_GBR | H9: ='Z4 WTP-Ikana'!$B$36 -> 334.13242 | I9: ='Z4 WTP-Ikana'!$B$37 -> 329.63242 | J9: ='Z4 WTP-Ikana'!$B$14 -> 330 | K9: ='Z4 WTP-Ikana'!$B$48 -> 4.1324197 | L9: ='Z4 WTP-Ikana'!$B$42 -> 353.73382 | M9: ='Z4 WTP-Ikana'!$B$44 -> 450 | N9: ='Z4 WTP-Ikana'!$B$45 -> 24575.191 | O9: ='Z4 WTP-Ikana'!$B$49 -> 8.8711377 | P9: 334.13 | Q9: =H9-P9 -> 0.0024197216
A10: Z5 Ikana-Nkangamo | B10: gravity | C10: ='Z5 Ikana-Nkangamo'!K12 -> 231.48148 | D10: ='Z5 Ikana-Nkangamo'!M12 -> 0.81869827 | E10: ='Z5 Ikana-Nkangamo'!P12 -> 51.615046 | F10: ='Z5 Ikana-Nkangamo'!$B$27 -> 1610.115 | G10: ='Z5 Ikana-Nkangamo'!$B$28 -> NKANGAMO_BPS | H10: ='Z5 Ikana-Nkangamo'!$B$29 -> 53.184954 | I10: ='Z5 Ikana-Nkangamo'!$B$30 -> 57.884954 | J10: – | K10: – | L10: – | M10: – | N10: – | O10: ='Z5 Ikana-Nkangamo'!$B$32 -> 65.611726 | P10: 53.18 | Q10: =H10-P10 -> 0.0049535157
A11: Z6 Nkangamo-Uhuru | B11: pumped | C11: ='Z6 Nkangamo-Uhuru'!K18 -> 252.52525 | D11: ='Z6 Nkangamo-Uhuru'!M18 -> 0.89312538 | E11: ='Z6 Nkangamo-Uhuru'!P18 -> 30.501264 | F11: ='Z6 Nkangamo-Uhuru'!$B$50 -> 1738.2284 | G11: ='Z6 Nkangamo-Uhuru'!$B$51 -> TUNDUMA_ESR | H11: ='Z6 Nkangamo-Uhuru'!$B$53 -> 188.22839 | I11: ='Z6 Nkangamo-Uhuru'!$B$54 -> 184.22839 | J11: ='Z6 Nkangamo-Uhuru'!$B$14 -> 221 | K11: ='Z6 Nkangamo-Uhuru'!$B$65 -> -32.771611 | L11: ='Z6 Nkangamo-Uhuru'!$B$59 -> 298.9058 | M11: ='Z6 Nkangamo-Uhuru'!$B$61 -> 355 | N11: ='Z6 Nkangamo-Uhuru'!$B$62 -> 13844.058 | O11: ='Z6 Nkangamo-Uhuru'!$B$66 -> 6.6727404 | P11: 188.23 | Q11: =H11-P11 -> -0.001610638
A12: Z7 Uhuru-Chapwa | B12: gravity | C12: ='Z7 Uhuru-Chapwa'!K12 -> 14.400463 | D12: ='Z7 Uhuru-Chapwa'!M12 -> 0.81489951 | E12: ='Z7 Uhuru-Chapwa'!P12 -> 10.353559 | F12: ='Z7 Uhuru-Chapwa'!$B$37 -> 1701.5073 | G12: ='Z7 Uhuru-Chapwa'!$B$38 -> point on UHURU_J004N | H12: ='Z7 Uhuru-Chapwa'!$B$39 -> -3.9073317 | I12: ='Z7 Uhuru-Chapwa'!$B$40 -> 0.79266833 | J12: – | K12: – | L12: – | M12: – | N12: – | O12: ='Z7 Uhuru-Chapwa'!$B$42 -> -1.9075966 | P12: -3.91 | Q12: =H12-P12 -> 0.0026683296
A13: Total pumping energy | N13: =SUM(N6:N12) -> 40869.323
A14: Pumped zones: H = pump head with suction at MINIMUM level (design), I = with suction at MAXIMUM level. Gravity zones: H/I = spare head with the supplying tank at MIN/MAX level (≥ 0 OK, burnt by a valve; < 0 short of head).
A16: Tanks and sumps
A17: Tank | B17: MIN level (m) | C17: MAX level (m) | D17: Arrival level (m) | E17: Fed by zone | F17: Arriving HGL (m) | G17: Excess head, design (m) | H17: Excess head, max (m) | I17: Inlet comment | J17: Capacity (m³) | K17: Storage required (m³) | L17: Storage status
A18: MOMBA_INTAKE | B18: =Levels!$F$6 -> 1360 | C18: =Levels!$G$6 -> 1364 | D18: =Levels!$L$6 -> 1360 | E18: Z1 River-Intake | F18: ='Z1 River-Intake'!I16 -> 1360.8218 | G18: ='Z1 River-Intake'!J16 -> 0.82182627 | H18: ='Z1 River-Intake'!K16 -> 4.3218263 | I18: ='Z1 River-Intake'!L16 -> OK | J18: =IF(Levels!$I$6="","",Levels!$I$6) | K18: – | L18: –
A19: GRIT_TANK | B19: =Levels!$F$7 -> 1366.5 | C19: =Levels!$G$7 -> 1368 | D19: =Levels!$L$7 -> 1368 | E19: Z2 Intake-Grit | F19: ='Z2 Intake-Grit'!I22 -> 1369 | G19: ='Z2 Intake-Grit'!J22 -> 0 | H19: ='Z2 Intake-Grit'!K22 -> 4 | I19: ='Z2 Intake-Grit'!L22 -> OK | J19: =IF(Levels!$I$7="","",Levels!$I$7) | K19: – | L19: –
A20: MOMBA_WTP | B20: =Levels!$F$8 -> 1368.5 | C20: =Levels!$G$8 -> 1373 | D20: =Levels!$L$8 -> 1378 | E20: Z3 Grit-WTP | F20: ='Z3 Grit-WTP'!I22 -> 1379 | G20: ='Z3 Grit-WTP'!J22 -> 0 | H20: ='Z3 Grit-WTP'!K22 -> 1.5 | I20: ='Z3 Grit-WTP'!L22 -> OK | J20: =IF(Levels!$I$8="","",Levels!$I$8) -> 4000 | K20: – | L20: –
A21: IKANA_GBR | B21: =Levels!$F$9 -> 1663.3 | C21: =Levels!$G$9 -> 1668 | D21: =Levels!$L$9 -> 1668 | E21: Z4 WTP-Ikana | F21: ='Z4 WTP-Ikana'!I22 -> 1669 | G21: ='Z4 WTP-Ikana'!J22 -> 0 | H21: ='Z4 WTP-Ikana'!K22 -> 4.5 | I21: ='Z4 WTP-Ikana'!L22 -> OK | J21: =IF(Levels!$I$9="","",Levels!$I$9) -> 3000 | K21: =Storage!I5 -> 1666.6667 | L21: =Storage!L5 -> OK
A22: NKANGAMO_BPS | B22: =Levels!$F$10 -> 1553 | C22: =Levels!$G$10 -> 1557 | D22: =Levels!$L$10 -> 1557.5 | E22: Z5 Ikana-Nkangamo | F22: ='Z5 Ikana-Nkangamo'!I16 -> 1611.685 | G22: ='Z5 Ikana-Nkangamo'!J16 -> 53.184954 | H22: ='Z5 Ikana-Nkangamo'!K16 -> 57.884954 | I22: ='Z5 Ikana-Nkangamo'!L16 -> fit flow control valve / PRV (burns 53.2–57.9 m) | J22: =IF(Levels!$I$10="","",Levels!$I$10) -> 2000 | K22: =Storage!I6 -> 1666.6667 | L22: =Storage!L6 -> OK
A23: TUNDUMA_ESR | B23: =Levels!$F$12 -> 1703.5 | C23: =Levels!$G$12 -> 1706.5 | D23: =Levels!$L$12 -> 1706.5 | E23: Z6 Nkangamo-Uhuru | F23: ='Z6 Nkangamo-Uhuru'!I28 -> 1707.5 | G23: ='Z6 Nkangamo-Uhuru'!J28 -> 0 | H23: ='Z6 Nkangamo-Uhuru'!K28 -> 4 | I23: ='Z6 Nkangamo-Uhuru'!L28 -> OK | J23: =IF(Levels!$I$12="","",Levels!$I$12) -> 120 | K23: =Storage!I8 -> 30.96 | L23: =Storage!L8 -> OK
A24: UHURU_GSR01 | B24: =Levels!$F$13 -> 1698.4 | C24: =Levels!$G$13 -> 1701.4 | D24: =Levels!$L$13 -> 1701.4 | E24: Z6 Nkangamo-Uhuru | F24: ='Z6 Nkangamo-Uhuru'!I29 -> 1707.2014 | G24: ='Z6 Nkangamo-Uhuru'!J29 -> 4.8013516 | H24: ='Z6 Nkangamo-Uhuru'!K29 -> 8.8013516 | I24: ='Z6 Nkangamo-Uhuru'!L29 -> fit flow control valve / PRV (burns 4.8–8.8 m) | J24: =IF(Levels!$I$13="","",Levels!$I$13) -> 500 | K24: =Storage!I9 -> 128.88 | L24: =Storage!L9 -> OK
A25: IPITO_GSR02 | B25: =Levels!$F$14 -> 1681.2 | C25: =Levels!$G$14 -> 1684.2 | D25: =Levels!$L$14 -> 1684.2 | E25: Z6 Nkangamo-Uhuru | F25: ='Z6 Nkangamo-Uhuru'!I30 -> 1698.4412 | G25: ='Z6 Nkangamo-Uhuru'!J30 -> 13.241179 | H25: ='Z6 Nkangamo-Uhuru'!K30 -> 17.241179 | I25: ='Z6 Nkangamo-Uhuru'!L30 -> fit flow control valve / PRV (burns 13.2–17.2 m) | J25: =IF(Levels!$I$14="","",Levels!$I$14) -> 200 | K25: =Storage!I10 -> 51.841667 | L25: =Storage!L10 -> OK
A26: UHURU_PARK_GBR | B26: =Levels!$F$11 -> 1697.6 | C26: =Levels!$G$11 -> 1702.3 | D26: =Levels!$L$11 -> 1702.3 | E26: Z6 Nkangamo-Uhuru | F26: ='Z6 Nkangamo-Uhuru'!I31 -> 1707.4769 | G26: ='Z6 Nkangamo-Uhuru'!J31 -> 4.1768894 | H26: ='Z6 Nkangamo-Uhuru'!K31 -> 8.1768894 | I26: ='Z6 Nkangamo-Uhuru'!L31 -> fit flow control valve / PRV (burns 4.2–8.2 m) | J26: =IF(Levels!$I$11="","",Levels!$I$11) -> 5000 | K26: =Storage!I7 -> 1454.985 | L26: =Storage!L7 -> OK
A27: MAKAMBINI_GSR03 | B27: =Levels!$F$15 -> 1655.7 | C27: =Levels!$G$15 -> 1658.7 | D27: =Levels!$L$15 -> 1658.7 | E27: Z7 Uhuru-Chapwa | F27: ='Z7 Uhuru-Chapwa'!I18 -> 1680.7175 | G27: ='Z7 Uhuru-Chapwa'!J18 -> 21.017451 | H27: ='Z7 Uhuru-Chapwa'!K18 -> 25.717451 | I27: ='Z7 Uhuru-Chapwa'!L18 -> fit flow control valve / PRV (burns 21.0–25.7 m) | J27: =IF(Levels!$I$15="","",Levels!$I$15) -> 200 | K27: =Storage!I11 -> 0 | L27: =Storage!L11 -> OK
A28: CHAPWA_GSR04 | B28: =Levels!$F$16 -> 1521.4 | C28: =Levels!$G$16 -> 1524.4 | D28: =Levels!$L$16 -> 1524.4 | E28: Z7 Uhuru-Chapwa | F28: ='Z7 Uhuru-Chapwa'!I19 -> 1650.3656 | G28: ='Z7 Uhuru-Chapwa'!J19 -> 124.96558 | H28: ='Z7 Uhuru-Chapwa'!K19 -> 129.66558 | I28: ='Z7 Uhuru-Chapwa'!L19 -> fit flow control valve / PRV (burns 125.0–129.7 m) | J28: =IF(Levels!$I$16="","",Levels!$I$16) -> 200 | K28: =Storage!I12 -> 0 | L28: =Storage!L12 -> OK
A30: Levels check (from sheet Levels)
A31: =IF(COUNTIF(Levels!$N$5:$N$16,"OK")=12,"All levels entered and consistent","CHECK sheet Levels – "&(12-COUNTIF(Levels!$N$5:$N$16,"OK"))&" row(s) need attention") -> All levels entered and consistent

Sheet Demands
A1: Demands and design flows
A2: Daily volumes (m³/d) supplied by each tank; pipe volumes follow by mass balance.
A4: Tank demands (ER schematic, design year 2035)
A5: Uhuru Park GBR – town supply | B5: 16215.62 | C5: m³/d | D5: ER schematic
A6: Existing Uhuru GSR 01 | B6: 1546.56 | C6: m³/d | D6: ER schematic
A7: Existing Tunduma ESR | B7: 371.52 | C7: m³/d | D7: ER schematic
A8: Existing Ipito GSR 02 | B8: 622.1 | C8: m³/d | D8: ER schematic
A9: Existing Makambini GSR 03 | B9: 622.1 | C9: m³/d | D9: ER schematic
A10: Existing Chapwa GSR 04 | B10: 622.1 | C10: m³/d | D10: ER schematic
A11: WTP + intake-to-WTP losses | B11: 0.07 | C11: – | D11: ER Table 8: 2 % + 5 %
A13: Daily volume in each pipe (mass balance, downstream → upstream)
A14: J-004N → Makambini | B14: =$B$9 -> 622.1 | C14: m³/d
A15: J-004N → Chapwa | B15: =$B$10 -> 622.1 | C15: m³/d
A16: Uhuru Park → J-004N | B16: =$B$14+$B$15 -> 1244.2 | C16: m³/d
A17: J-003N → Uhuru Park GBR | B17: =$B$5+$B$16 -> 17459.82 | C17: m³/d
A18: J-003N → Ipito | B18: =$B$8 -> 622.1 | C18: m³/d
A19: J-002N → GSR01 | B19: =$B$6 -> 1546.56 | C19: m³/d
A20: J-001N → ESR | B20: =$B$7 -> 371.52 | C20: m³/d
A21: J-002N → J-003N | B21: =$B$17+$B$18 -> 18081.92 | C21: m³/d
A22: J-001N → J-002N | B22: =$B$21+$B$19 -> 19628.48 | C22: m³/d
A23: Nkangamo BPS → J-001N | B23: =$B$22+$B$20 -> 20000 | C23: m³/d
A24: Ikana GBR → Nkangamo BPS | B24: =$B$23 -> 20000 | C24: m³/d
A25: WTP → Ikana GBR (net WTP output) | B25: =$B$24 -> 20000 | C25: m³/d
A26: Raw water: intake → WTP | B26: =$B$25/(1-$B$11) -> 21505.376 | C26: m³/d | D26: net ÷ (1 − losses)
A27: Low-lift → grit tank | B27: =$B$26 -> 21505.376 | C27: m³/d
A28: River → intake sump | B28: =$B$26 -> 21505.376 | C28: m³/d

Sheet Global
A1: Global constants and design criteria
A2: Used by every zone (named cells).
A4: Constants and criteria
A5: Gravitational acceleration g | B5: 9.81 | C5: m/s² | D5: physical constant
A6: Minor losses as fraction of friction | B6: 0.1 | C6: – | D6: ASSUMED 10 % (bends, valves, fittings)
A7: Losses inside each pump station | B7: 3 | C7: m | D7: ASSUMED pipework/valves/meter
A8: Residual head above a tank inlet | B8: 1 | C8: m | D8: ASSUMED safety margin
A9: Pipe crown depth below ground | B9: 1.2 | C9: m | D9: ASSUMED
A10: Minimum pressure at pipe crown along mains | B10: 2 | C10: m | D10: ASSUMED
A11: Minimum pressure at junctions / delivery | B11: 5 | C11: m | D11: ER Table 7
A12: Pressure wave speed a (steel) | B12: 1000 | C12: m/s | D12: ASSUMED, for surge
A13: Motor size margin over shaft power | B13: 1.15 | C13: – | D13: common practice
A14: Electricity tariff | B14: 0 | C14: per kWh | D14: enter the TANESCO tariff
A15: Bar per metre of water | B15: 0.0981 | C15: bar/m | D15: ρg/10⁵
A16: Default Hazen-Williams C | B16: 120 | C16: – | D16: ASSUMED, cement-lined steel (aged)
A17: Excess head above which a flow control valve is flagged | B17: 5 | C17: m | D17: judgement
A19: Pipe pressure classes (PN, bar)
A20: PN10 | B20: 10
A21: PN16 | B21: 16
A22: PN25 | B22: 25
A23: PN30 | B23: 30
A24: PN40 | B24: 40
A25: PN64 | B25: 64
A27: Standard motor sizes (kW)
B28: 0.75
B29: 1.1
B30: 1.5
B31: 2.2
B32: 3
B33: 4
B34: 5.5
B35: 7.5
B36: 11
B37: 15
B38: 18.5
B39: 22
... B77: 6300

Sheet Z1 River-Intake
A1: Zone 1 – Momba River to intake sump (gravity)
A2: The river fills the intake sump by gravity through the abstraction pipe. The river at its MINIMUM (dry-season) level must stay above the sump MINIMUM level plus the pipe loss, otherwise the low-lift pumps lose submergence.
A4: A. Inputs (levels come from sheet 'Levels')
A5: Start: MOMBA_RIVER MINIMUM water level | B5: =Levels!$F$5 -> 1361 | C5: m a.s.l. | D5: point 1 of Bernoulli, design case (least energy at the start)
A6: Start: MOMBA_RIVER MAXIMUM water level | B6: =Levels!$G$5 -> 1364.5 | C6: m a.s.l. | D6: low-head case for pumps / highest energy for gravity
A7: Operating hours per day | B7: 22 | C7: h/d | D7: carries the intake pump flow while the pumps run
A8: Static level for pressure class | B8: =$B$6 -> 1364.5 | C8: m a.s.l. | D8: MAXIMUM level of the supplying tank (water at rest)
A10: B. Pipes – flow (continuity) and friction (Hazen-Williams)
A11: Pipe | B11: From | C11: To | D11: Upstream pipe | E11: DN | F11: Internal D (mm) | G11: Length L (m) | H11: C (H-W) | I11: Daily volume (m³/d) | J11: Q (m³/s) | K11: Q (l/s) | L11: Area (m²) | M11: V (m/s) | N11: hf friction (m) | O11: hm minor (m) | P11: hL total (m) | Q11: Gradient (m/km) | R11: Loss before this pipe (m) | S11: HGL start (m) | T11: HGL end (m) | U11: Surge Δh = aV/g (m)
A12: ABSTRACTION | B12: MOMBA_RIVER | C12: MOMBA_INTAKE | D12: – | E12: 600 | F12: =E12 -> 600 | G12: 100 | H12: =C_default -> 120 | I12: =Demands!$B$28 -> 21505.376 | J12: =I12/($B$7*3600) -> 0.27153253 | K12: =J12*1000 -> 271.53253 | L12: =PI()*(F12/1000)^2/4 -> 0.28274334 | M12: =J12/L12 -> 0.96034987 | N12: =10.67*G12*J12^1.852/(H12^1.852*(F12/1000)^4.8704) -> 0.16197612 | O12: =k_minor*N12 -> 0.016197612 | P12: =N12+O12 -> 0.17817373 | Q12: =P12/G12*1000 -> 1.7817373 | R12: 0 | S12: =$B$5-R12 -> 1361 | T12: =S12-P12 -> 1360.8218 | U12: =wave*M12/g -> 97.894992
A14: C. Destinations – Bernoulli to each receiving water surface (levels from 'Levels')
A15: Destination | B15: Ends with pipe | C15: MIN level (m) | D15: MAX level (m) | E15: Arrival level (m) | F15: Residual (m) | G15: z2 = arrival + residual (m) | H15: Head needed at zone start = z2 + losses (m) | I15: Arriving HGL, design case (m) | J15: Excess head, design case (m) | K15: Excess head, start at MAX level (m) | L15: Comment
A16: MOMBA_INTAKE | B16: ABSTRACTION | C16: =Levels!$F$6 -> 1360 | D16: =Levels!$G$6 -> 1364 | E16: =Levels!$L$6 -> 1360 | F16: 0 | G16: =E16+F16 -> 1360 | H16: =G16+R12+P12 -> 1360.1782 | I16: =T12 -> 1360.8218 | J16: =I16-G16 -> 0.82182627 | K16: =J16+($B$6-$B$5) -> 4.3218263 | L16: =IF(J16<-0.005,"NOT REACHED – more head needed",IF(K16>fcv_limit,"fit flow control valve / PRV (burns "&TEXT(J16,"0.0")&"–"&TEXT(K16,"0.0")&" m)","OK")) -> OK
A18: D. Critical points along the pipes – pressure check (add your own rows)
A19: Pipe | B19: Chainage in pipe x (m) | C19: Ground level (m) | D19: Pipe crown (m) | E19: Head needed at zone start (m) | F19: HGL at point (m) | G19: Pressure (m) | H19: Static (m) | I19: Working (m) | J19: Working (bar) | K19: PN required | L19: Transient min = p − Δh (m) | M19: Note | N19: Status
D20: =IF($A20="","",C20-cover) | E20: =IF($A20="","",D20+p_min+INDEX($R$12:$R$12,MATCH($A20,$A$12:$A$12,0))+INDEX($P$12:$P$12,MATCH($A20,$A$12:$A$12,0))*B20/INDEX($G$12:$G$12,MATCH($A20,$A$12:$A$12,0))) | F20: =IF($A20="","",INDEX($S$12:$S$12,MATCH($A20,$A$12:$A$12,0))-INDEX($P$12:$P$12,MATCH($A20,$A$12:$A$12,0))*B20/INDEX($G$12:$G$12,MATCH($A20,$A$12:$A$12,0))) | G20: =IF($A20="","",F20-D20) | H20: =IF($A20="","",$B$8-D20) | I20: =IF($A20="","",MAX(G20,H20)) | J20: =IF($A20="","",I20*bar_per_m) | K20: =IF($A20="","",IFERROR("PN"&SMALL(PN_list,COUNTIF(PN_list,"<"&J20)+1),"> max PN")) | L20: =IF($A20="","",G20-INDEX($U$12:$U$12,MATCH($A20,$A$12:$A$12,0))) | M20: add a point: pipe ID, chainage, ground level | N20: =IF($A20="","",IF(G20<0,"NEGATIVE PRESSURE",IF(G20<p_min-0.005,"below minimum","OK")))
D21: =IF($A21="","",C21-cover) | E21: =IF($A21="","",D21+p_min+INDEX($R$12:$R$12,MATCH($A21,$A$12:$A$12,0))+INDEX($P$12:$P$12,MATCH($A21,$A$12:$A$12,0))*B21/INDEX($G$12:$G$12,MATCH($A21,$A$12:$A$12,0))) | F21: =IF($A21="","",INDEX($S$12:$S$12,MATCH($A21,$A$12:$A$12,0))-INDEX($P$12:$P$12,MATCH($A21,$A$12:$A$12,0))*B21/INDEX($G$12:$G$12,MATCH($A21,$A$12:$A$12,0))) | G21: =IF($A21="","",F21-D21) | H21: =IF($A21="","",$B$8-D21) | I21: =IF($A21="","",MAX(G21,H21)) | J21: =IF($A21="","",I21*bar_per_m) | K21: =IF($A21="","",IFERROR("PN"&SMALL(PN_list,COUNTIF(PN_list,"<"&J21)+1),"> max PN")) | L21: =IF($A21="","",G21-INDEX($U$12:$U$12,MATCH($A21,$A$12:$A$12,0))) | M21: add a point: pipe ID, chainage, ground level | N21: =IF($A21="","",IF(G21<0,"NEGATIVE PRESSURE",IF(G21<p_min-0.005,"below minimum","OK")))
D22: =IF($A22="","",C22-cover) | E22: =IF($A22="","",D22+p_min+INDEX($R$12:$R$12,MATCH($A22,$A$12:$A$12,0))+INDEX($P$12:$P$12,MATCH($A22,$A$12:$A$12,0))*B22/INDEX($G$12:$G$12,MATCH($A22,$A$12:$A$12,0))) | F22: =IF($A22="","",INDEX($S$12:$S$12,MATCH($A22,$A$12:$A$12,0))-INDEX($P$12:$P$12,MATCH($A22,$A$12:$A$12,0))*B22/INDEX($G$12:$G$12,MATCH($A22,$A$12:$A$12,0))) | G22: =IF($A22="","",F22-D22) | H22: =IF($A22="","",$B$8-D22) | I22: =IF($A22="","",MAX(G22,H22)) | J22: =IF($A22="","",I22*bar_per_m) | K22: =IF($A22="","",IFERROR("PN"&SMALL(PN_list,COUNTIF(PN_list,"<"&J22)+1),"> max PN")) | L22: =IF($A22="","",G22-INDEX($U$12:$U$12,MATCH($A22,$A$12:$A$12,0))) | M22: add a point: pipe ID, chainage, ground level | N22: =IF($A22="","",IF(G22<0,"NEGATIVE PRESSURE",IF(G22<p_min-0.005,"below minimum","OK")))
A24: E. Bernoulli result
A25: Head needed at zone start H_req | B25: =MAX($H$16:$H$16,$E$20:$E$22) -> 1360.1782 | C25: m a.s.l. | D25: largest of sections C, C2 (junctions) and D (points)
A26: Set by | B26: =IF(MAX($E$20:$E$22)>=MAX($H$16:$H$16),"point on "&INDEX($A$20:$A$22,MATCH(MAX($E$20:$E$22),$E$20:$E$22,0)),INDEX($A$16:$A$16,MATCH(MAX($H$16:$H$16),$H$16:$H$16,0))) -> MOMBA_INTAKE | D26: governing destination, junction or point
A27: Surplus = z1 − H_req (start at MINIMUM level) | B27: =$B$5-$B$25 -> 0.82182627 | C27: m | D27: design case: must be ≥ 0
A28: Surplus with start at MAXIMUM level | B28: =$B$6-$B$25 -> 4.3218263 | C28: m | D28: largest head the valve must burn
A29: Status | B29: =IF($B$27<-0.005,"SHORT OF HEAD at minimum level – bigger pipe, lower outlet, higher tank or pump","OK – valve burns "&TEXT($B$27,"0.0")&" to "&TEXT($B$28,"0.0")&" m") -> OK – valve burns 0.8 to 4.3 m
A30: Lowest pressure at any survey point (sheet Profile) | B30: =IF(COUNTIFS(Profile!$A$5:$A$2360,"Z1 River-Intake",Profile!$L$5:$L$2360,"yes")=0,"no points between tanks",_xlfn.MINIFS(Profile!$H$5:$H$2360,Profile!$A$5:$A$2360,"Z1 River-Intake",Profile!$L$5:$L$2360,"yes")) -> no points between tanks | C30: m | D30: if below the minimum, add that point to section D
A32: F. Step by step in words (updates with the numbers)
A33: ="1. Flow: "&TEXT(I12,"#,##0")&" m³/d in "&TEXT($B$7,"0")&" h → Q = "&TEXT(K12,"0.0")&" l/s, V = "&TEXT(M12,"0.00")&" m/s in "&A12&"." -> 1. Flow: 21,505 m³/d in 22 h → Q = 271.5 l/s, V = 0.96 m/s in ABSTRACTION.
A34: ="2. Friction (Hazen-Williams): "&A12&" loses hL = "&TEXT(P12,"0.00")&" m over "&TEXT(G12,"#,##0")&" m ("&TEXT(Q12,"0.00")&" m/km)." -> 2. Friction (Hazen-Williams): ABSTRACTION loses hL = 0.18 m over 100 m (1.78 m/km).
A35: ="3. Point 1 = MOMBA_RIVER water surface at its MINIMUM level z1 = "&TEXT($B$5,"0.00")&" m (p = 0, V ≈ 0)." -> 3. Point 1 = MOMBA_RIVER water surface at its MINIMUM level z1 = 1361.00 m (p = 0, V ≈ 0).
A36: ="4. Point 2: the hardest place to reach is "&$B$26&"; it needs the HGL at the zone start to be H_req = "&TEXT($B$25,"0.00")&" m (its level + residual + losses on the way)." -> 4. Point 2: the hardest place to reach is MOMBA_INTAKE; it needs the HGL at the zone start to be H_req = 1360.18 m (its level + residual + losses on the way).
A37: ="5. Bernoulli without pump: z1 = H_req + surplus → surplus = "&TEXT($B$5,"0.00")&" − "&TEXT($B$25,"0.00")&" = "&TEXT($B$27,"0.00")&" m." -> 5. Bernoulli without pump: z1 = H_req + surplus → surplus = 1361.00 − 1360.18 = 0.82 m.
A38: ="6. With the supplying tank full (MAXIMUM level "&TEXT($B$6,"0.00")&" m) the surplus is "&TEXT($B$28,"0.00")&" m. "&IF($B$27<-0.005,"Negative at minimum level: the zone cannot deliver – change pipe or levels.","A flow control valve burns this so the flow stays at design.") -> 6. With the supplying tank full (MAXIMUM level 1364.50 m) the surplus is 4.32 m. A flow control valve burns this so the flow stays at design.
A39: ="8. Pressure: lowest pressure along the route = "&TEXT($B$30,"0.0")&" m (minimum allowed "&TEXT(p_min,"0")&" m); pipe class from section D and sheet Profile." -> 8. Pressure: lowest pressure along the route = no points between tanks m (minimum allowed 2 m); pipe class from section D and sheet Profile.

Sheet Z2 Intake-Grit
A1: Zone 2 – Intake low-lift pumps to grit tank (pumped)
A2: Low-lift pumps lift raw water from the intake sump into the grit tank. Pump head = level the water must reach in the grit tank + losses − sump level.
A4: A. Inputs (levels come from sheet 'Levels')
A5: Start: MOMBA_INTAKE MINIMUM water level | B5: =Levels!$F$6 -> 1360 | C5: m a.s.l. | D5: point 1 of Bernoulli, design case (least energy at the start)
A6: Start: MOMBA_INTAKE MAXIMUM water level | B6: =Levels!$G$6 -> 1364 | C6: m a.s.l. | D6: low-head case for pumps / highest energy for gravity
A7: Operating hours per day | B7: 22 | C7: h/d | D7: ER: pumps 22 h/d; gravity 24 h/d
A8: Static level for pressure class | B8: =MAX(Levels!$L$7) -> 1368 | C8: m a.s.l. | D8: highest arrival level at the end of the zone (pipe full, pumps stopped)
A9: Number of duty pumps | B9: 1 | C9: no. | D9: working pumps sharing the flow
A10: Number of standby pumps | B10: 1 | C10: no. | D10: for information
A11: Pump efficiency η_p | B11: 0.75 | C11: – | D11: ASSUMED – use the pump curve
A12: Motor efficiency η_m | B12: 0.94 | C12: – | D12: ASSUMED
A13: ER duty flow per pump | B13: 978 | C13: m³/h | D13: Employer's Requirements
A14: ER duty head | B14: 10 | C14: m | D14: Employer's Requirements
A16: B. Pipes – flow (continuity) and friction (Hazen-Williams)
A17: Pipe | B17: From | C17: To | D17: Upstream pipe | E17: DN | F17: Internal D (mm) | G17: Length L (m) | H17: C (H-W) | I17: Daily volume (m³/d) | J17: Q (m³/s) | K17: Q (l/s) | L17: Area (m²) | M17: V (m/s) | N17: hf friction (m) | O17: hm minor (m) | P17: hL total (m) | Q17: Gradient (m/km) | R17: Loss before this pipe (m) | S17: HGL start (m) | T17: HGL end (m) | U17: Surge Δh = aV/g (m)
A18: LL_DELIVERY | B18: MOMBA_INTAKE | C18: GRIT_TANK | D18: – | E18: 600 | F18: =E18 -> 600 | G18: 30 | H18: =C_default -> 120 | I18: =Demands!$B$27 -> 21505.376 | J18: =I18/($B$7*3600) -> 0.27153253 | K18: =J18*1000 -> 271.53253 | L18: =PI()*(F18/1000)^2/4 -> 0.28274334 | M18: =J18/L18 -> 0.96034987 | N18: =10.67*G18*J18^1.852/(H18^1.852*(F18/1000)^4.8704) -> 0.048592837 | O18: =k_minor*N18 -> 0.0048592837 | P18: =N18+O18 -> 0.05345212 | Q18: =P18/G18*1000 -> 1.7817373 | R18: 0 | S18: =$B$31-R18 -> 1369.0535 | T18: =S18-P18 -> 1369 | U18: =wave*M18/g -> 97.894992
A20: C. Destinations – Bernoulli to each receiving water surface (levels from 'Levels')
A21: Destination | B21: Ends with pipe | C21: MIN level (m) | D21: MAX level (m) | E21: Arrival level (m) | F21: Residual (m) | G21: z2 = arrival + residual (m) | H21: Head needed at zone start = z2 + losses (m) | I21: Arriving HGL, design case (m) | J21: Excess head, design case (m) | K21: Excess head, start at MAX level (m) | L21: Comment
A22: GRIT_TANK | B22: LL_DELIVERY | C22: =Levels!$F$7 -> 1366.5 | D22: =Levels!$G$7 -> 1368 | E22: =Levels!$L$7 -> 1368 | F22: =h_res -> 1 | G22: =E22+F22 -> 1369 | H22: =G22+R18+P18 -> 1369.0535 | I22: =T18 -> 1369 | J22: =I22-G22 -> 0 | K22: =J22+($B$6-$B$5) -> 4 | L22: =IF(J22<-0.005,"NOT REACHED – more head needed",IF(K22>fcv_limit,"fit flow control valve / PRV (burns "&TEXT(J22,"0.0")&"–"&TEXT(K22,"0.0")&" m)","OK")) -> OK
A24: D. Critical points along the pipes – pressure check (add your own rows)
A25: Pipe | B25: Chainage in pipe x (m) | C25: Ground level (m) | D25: Pipe crown (m) | E25: Head needed at zone start (m) | F25: HGL at point (m) | G25: Pressure (m) | H25: Static (m) | I25: Working (m) | J25: Working (bar) | K25: PN required | L25: Transient min = p − Δh (m) | M25: Note | N25: Status
D26: =IF($A26="","",C26-cover) | E26: =IF($A26="","",D26+p_min+INDEX($R$18:$R$18,MATCH($A26,$A$18:$A$18,0))+INDEX($P$18:$P$18,MATCH($A26,$A$18:$A$18,0))*B26/INDEX($G$18:$G$18,MATCH($A26,$A$18:$A$18,0))) | F26: =IF($A26="","",INDEX($S$18:$S$18,MATCH($A26,$A$18:$A$18,0))-INDEX($P$18:$P$18,MATCH($A26,$A$18:$A$18,0))*B26/INDEX($G$18:$G$18,MATCH($A26,$A$18:$A$18,0))) | G26: =IF($A26="","",F26-D26) | H26: =IF($A26="","",$B$8-D26) | I26: =IF($A26="","",MAX(G26,H26)) | J26: =IF($A26="","",I26*bar_per_m) | K26: =IF($A26="","",IFERROR("PN"&SMALL(PN_list,COUNTIF(PN_list,"<"&J26)+1),"> max PN")) | L26: =IF($A26="","",G26-INDEX($U$18:$U$18,MATCH($A26,$A$18:$A$18,0))) | M26: add a point: pipe ID, chainage, ground level | N26: =IF($A26="","",IF(G26<0,"NEGATIVE PRESSURE",IF(G26<p_min-0.005,"below minimum","OK")))
D27: =IF($A27="","",C27-cover) | E27: =IF($A27="","",D27+p_min+INDEX($R$18:$R$18,MATCH($A27,$A$18:$A$18,0))+INDEX($P$18:$P$18,MATCH($A27,$A$18:$A$18,0))*B27/INDEX($G$18:$G$18,MATCH($A27,$A$18:$A$18,0))) | F27: =IF($A27="","",INDEX($S$18:$S$18,MATCH($A27,$A$18:$A$18,0))-INDEX($P$18:$P$18,MATCH($A27,$A$18:$A$18,0))*B27/INDEX($G$18:$G$18,MATCH($A27,$A$18:$A$18,0))) | G27: =IF($A27="","",F27-D27) | H27: =IF($A27="","",$B$8-D27) | I27: =IF($A27="","",MAX(G27,H27)) | J27: =IF($A27="","",I27*bar_per_m) | K27: =IF($A27="","",IFERROR("PN"&SMALL(PN_list,COUNTIF(PN_list,"<"&J27)+1),"> max PN")) | L27: =IF($A27="","",G27-INDEX($U$18:$U$18,MATCH($A27,$A$18:$A$18,0))) | M27: add a point: pipe ID, chainage, ground level | N27: =IF($A27="","",IF(G27<0,"NEGATIVE PRESSURE",IF(G27<p_min-0.005,"below minimum","OK")))
D28: =IF($A28="","",C28-cover) | E28: =IF($A28="","",D28+p_min+INDEX($R$18:$R$18,MATCH($A28,$A$18:$A$18,0))+INDEX($P$18:$P$18,MATCH($A28,$A$18:$A$18,0))*B28/INDEX($G$18:$G$18,MATCH($A28,$A$18:$A$18,0))) | F28: =IF($A28="","",INDEX($S$18:$S$18,MATCH($A28,$A$18:$A$18,0))-INDEX($P$18:$P$18,MATCH($A28,$A$18:$A$18,0))*B28/INDEX($G$18:$G$18,MATCH($A28,$A$18:$A$18,0))) | G28: =IF($A28="","",F28-D28) | H28: =IF($A28="","",$B$8-D28) | I28: =IF($A28="","",MAX(G28,H28)) | J28: =IF($A28="","",I28*bar_per_m) | K28: =IF($A28="","",IFERROR("PN"&SMALL(PN_list,COUNTIF(PN_list,"<"&J28)+1),"> max PN")) | L28: =IF($A28="","",G28-INDEX($U$18:$U$18,MATCH($A28,$A$18:$A$18,0))) | M28: add a point: pipe ID, chainage, ground level | N28: =IF($A28="","",IF(G28<0,"NEGATIVE PRESSURE",IF(G28<p_min-0.005,"below minimum","OK")))
A30: E. Bernoulli result
A31: Head needed at zone start H_req | B31: =MAX($H$22:$H$22,$E$26:$E$28) -> 1369.0535 | C31: m a.s.l. | D31: largest of sections C, C2 (junctions) and D (points)
A32: Set by | B32: =IF(MAX($E$26:$E$28)>=MAX($H$22:$H$22),"point on "&INDEX($A$26:$A$28,MATCH(MAX($E$26:$E$28),$E$26:$E$28,0)),INDEX($A$22:$A$22,MATCH(MAX($H$22:$H$22),$H$22:$H$22,0))) -> GRIT_TANK | D32: governing destination, junction or point
A33: Hp = H_req − z1 (suction at MINIMUM level) | B33: =$B$31-$B$5 -> 9.0534521 | C33: m | D33: z1 + 0 + 0 + Hp = H_req (p = 0, V ≈ 0 at the sump surface)
A34: TDH design (suction at MINIMUM level) | B34: =$B$33+h_station -> 12.053452 | C34: m | D34: Hp + station losses → size pump and motor with this
A35: TDH low-head (suction at MAXIMUM level) | B35: =$B$31-$B$6+h_station -> 8.0534521 | C35: m | D35: pump must also operate here (more flow unless throttled / VFD)
A36: Total pumped flow | B36: =J18 -> 0.27153253 | C36: m³/s | D36: flow in the first pipe
A37: Flow per pump | B37: =$B$36/$B$9 -> 0.27153253 | C37: m³/s
A38: Flow per pump | B38: =$B$37*3600 -> 977.51711 | C38: m³/h | D38: compare ER duty flow
A39: Hydraulic power per pump P_h = ρgQH | B39: =1000*g*$B$37*$B$34/1000 -> 32.107192 | C39: kW
A40: Shaft power per pump P_s = P_h / η_p | B40: =$B$39/$B$11 -> 42.809589 | C40: kW
A41: Motor needed = P_s × margin | B41: =$B$40*motor_margin -> 49.231027 | C41: kW
A42: Standard motor per pump | B42: =IFERROR(SMALL(Motor_list,COUNTIF(Motor_list,"<"&$B$41)+1),"> list") -> 55 | C42: kW | D42: next size up
A43: Electricity per day | B43: =$B$9*$B$40*$B$7/$B$12 -> 1001.9265 | C43: kWh/d
A44: Specific energy | B44: =$B$43/I18 -> 0.046589584 | C44: kWh/m³
A45: Electricity cost per year | B45: =$B$43*365*tariff -> 0 | C45: per year | D45: uses Global tariff
A46: TDH design minus ER duty head | B46: =$B$34-$B$14 -> 2.0534521 | C46: m | D46: negative = ER pump has spare head (throttle / VFD)
A47: Lowest pressure at any survey point (sheet Profile) | B47: =IF(COUNTIFS(Profile!$A$5:$A$2360,"Z2 Intake-Grit",Profile!$L$5:$L$2360,"yes")=0,"no points between tanks",_xlfn.MINIFS(Profile!$H$5:$H$2360,Profile!$A$5:$A$2360,"Z2 Intake-Grit",Profile!$L$5:$L$2360,"yes")) -> no points between tanks | C47: m | D47: if below the minimum, add that point to section D
A49: F. Step by step in words (updates with the numbers)
A50: ="1. Flow: "&TEXT(I18,"#,##0")&" m³/d in "&TEXT($B$7,"0")&" h → Q = "&TEXT(K18,"0.0")&" l/s, V = "&TEXT(M18,"0.00")&" m/s in "&A18&"." -> 1. Flow: 21,505 m³/d in 22 h → Q = 271.5 l/s, V = 0.96 m/s in LL_DELIVERY.
A51: ="2. Friction (Hazen-Williams): "&A18&" loses hL = "&TEXT(P18,"0.00")&" m over "&TEXT(G18,"#,##0")&" m ("&TEXT(Q18,"0.00")&" m/km)." -> 2. Friction (Hazen-Williams): LL_DELIVERY loses hL = 0.05 m over 30 m (1.78 m/km).
A52: ="3. Point 1 = MOMBA_INTAKE water surface at its MINIMUM level z1 = "&TEXT($B$5,"0.00")&" m (p = 0, V ≈ 0)." -> 3. Point 1 = MOMBA_INTAKE water surface at its MINIMUM level z1 = 1360.00 m (p = 0, V ≈ 0).
A53: ="4. Point 2: the hardest place to reach is "&$B$32&"; it needs the HGL at the zone start to be H_req = "&TEXT($B$31,"0.00")&" m (its level + residual + losses on the way)." -> 4. Point 2: the hardest place to reach is GRIT_TANK; it needs the HGL at the zone start to be H_req = 1369.05 m (its level + residual + losses on the way).
A54: ="5. Bernoulli: z1 + Hp = H_req → Hp = "&TEXT($B$31,"0.00")&" − "&TEXT($B$5,"0.00")&" = "&TEXT($B$33,"0.00")&" m; + station losses "&TEXT(h_station,"0.0")&" m → TDH = "&TEXT($B$34,"0.0")&" m." -> 5. Bernoulli: z1 + Hp = H_req → Hp = 1369.05 − 1360.00 = 9.05 m; + station losses 3.0 m → TDH = 12.1 m.
A55: ="6. With the suction tank full (MAXIMUM level "&TEXT($B$6,"0.00")&" m) TDH falls to "&TEXT($B$35,"0.0")&" m: the pump must work between "&TEXT($B$35,"0.0")&" and "&TEXT($B$34,"0.0")&" m at "&TEXT($B$38,"#,##0")&" m³/h per pump." -> 6. With the suction tank full (MAXIMUM level 1364.00 m) TDH falls to 8.1 m: the pump must work between 8.1 and 12.1 m at 978 m³/h per pump.
A56: ="7. Power: P = ρgQH/η = "&TEXT($B$40,"#,##0")&" kW per pump → motor "&TEXT($B$42,"#,##0")&" kW; ER duty head "&TEXT($B$14,"0")&" m (difference "&TEXT($B$46,"+0.0;-0.0")&" m)." -> 7. Power: P = ρgQH/η = 43 kW per pump → motor 55 kW; ER duty head 10 m (difference +2.1 m).
A57: ="8. Pressure: lowest pressure along the route = "&TEXT($B$47,"0.0")&" m (minimum allowed "&TEXT(p_min,"0")&" m); pipe class from section D and sheet Profile." -> 8. Pressure: lowest pressure along the route = no points between tanks m (minimum allowed 2 m); pipe class from section D and sheet Profile.

Sheet Z3 Grit-WTP
A1: Zone 3 – Grit tank high-lift pumps to the WTP (pumped)
A2: High-lift pumps push raw water from the grit tank through the raw-water main into the WTP inlet (cascade aerator).
A4: A. Inputs (levels come from sheet 'Levels')
A5: Start: GRIT_TANK MINIMUM water level | B5: =Levels!$F$7 -> 1366.5 | C5: m a.s.l. | D5: point 1 of Bernoulli, design case (least energy at the start)
A6: Start: GRIT_TANK MAXIMUM water level | B6: =Levels!$G$7 -> 1368 | C6: m a.s.l. | D6: low-head case for pumps / highest energy for gravity
A7: Operating hours per day | B7: 22 | C7: h/d | D7: ER: pumps 22 h/d; gravity 24 h/d
A8: Static level for pressure class | B8: =MAX(Levels!$L$8) -> 1378 | C8: m a.s.l. | D8: highest arrival level at the end of the zone (pipe full, pumps stopped)
A9: Number of duty pumps | B9: 1 | C9: no. | D9: working pumps sharing the flow
A10: Number of standby pumps | B10: 1 | C10: no. | D10: for information
A11: Pump efficiency η_p | B11: 0.75 | C11: – | D11: ASSUMED – use the pump curve
A12: Motor efficiency η_m | B12: 0.94 | C12: – | D12: ASSUMED
A13: ER duty flow per pump | B13: 978 | C13: m³/h | D13: Employer's Requirements
A14: ER duty head | B14: 25 | C14: m | D14: Employer's Requirements
A16: B. Pipes – flow (continuity) and friction (Hazen-Williams)
A17: Pipe | B17: From | C17: To | D17: Upstream pipe | E17: DN | F17: Internal D (mm) | G17: Length L (m) | H17: C (H-W) | I17: Daily volume (m³/d) | J17: Q (m³/s) | K17: Q (l/s) | L17: Area (m²) | M17: V (m/s) | N17: hf friction (m) | O17: hm minor (m) | P17: hL total (m) | Q17: Gradient (m/km) | R17: Loss before this pipe (m) | S17: HGL start (m) | T17: HGL end (m) | U17: Surge Δh = aV/g (m)
A18: RAW_MAIN | B18: GRIT_TANK | C18: MOMBA_WTP | D18: – | E18: 600 | F18: =E18 -> 600 | G18: 1078.5 | H18: =C_default -> 120 | I18: =Demands!$B$26 -> 21505.376 | J18: =I18/($B$7*3600) -> 0.27153253 | K18: =J18*1000 -> 271.53253 | L18: =PI()*(F18/1000)^2/4 -> 0.28274334 | M18: =J18/L18 -> 0.96034987 | N18: =10.67*G18*J18^1.852/(H18^1.852*(F18/1000)^4.8704) -> 1.7469125 | O18: =k_minor*N18 -> 0.17469125 | P18: =N18+O18 -> 1.9216037 | Q18: =P18/G18*1000 -> 1.7817373 | R18: 0 | S18: =$B$33-R18 -> 1380.9216 | T18: =S18-P18 -> 1379 | U18: =wave*M18/g -> 97.894992
A20: C. Destinations – Bernoulli to each receiving water surface (levels from 'Levels')
A21: Destination | B21: Ends with pipe | C21: MIN level (m) | D21: MAX level (m) | E21: Arrival level (m) | F21: Residual (m) | G21: z2 = arrival + residual (m) | H21: Head needed at zone start = z2 + losses (m) | I21: Arriving HGL, design case (m) | J21: Excess head, design case (m) | K21: Excess head, start at MAX level (m) | L21: Comment
A22: MOMBA_WTP | B22: RAW_MAIN | C22: =Levels!$F$8 -> 1368.5 | D22: =Levels!$G$8 -> 1373 | E22: =Levels!$L$8 -> 1378 | F22: =h_res -> 1 | G22: =E22+F22 -> 1379 | H22: =G22+R18+P18 -> 1380.9216 | I22: =T18 -> 1379 | J22: =I22-G22 -> 0 | K22: =J22+($B$6-$B$5) -> 1.5 | L22: =IF(J22<-0.005,"NOT REACHED – more head needed",IF(K22>fcv_limit,"fit flow control valve / PRV (burns "&TEXT(J22,"0.0")&"–"&TEXT(K22,"0.0")&" m)","OK")) -> OK
A24: D. Critical points along the pipes – pressure check (add your own rows)
A25: Pipe | B25: Chainage in pipe x (m) | C25: Ground level (m) | D25: Pipe crown (m) | E25: Head needed at zone start (m) | F25: HGL at point (m) | G25: Pressure (m) | H25: Static (m) | I25: Working (m) | J25: Working (bar) | K25: PN required | L25: Transient min = p − Δh (m) | M25: Note | N25: Status
A26: RAW_MAIN | B26: 778.5 | C26: 1372.43 | D26: =IF($A26="","",C26-cover) -> 1371.23 | E26: =IF($A26="","",D26+p_min+INDEX($R$18:$R$18,MATCH($A26,$A$18:$A$18,0))+INDEX($P$18:$P$18,MATCH($A26,$A$18:$A$18,0))*B26/INDEX($G$18:$G$18,MATCH($A26,$A$18:$A$18,0))) -> 1374.6171 | F26: =IF($A26="","",INDEX($S$18:$S$18,MATCH($A26,$A$18:$A$18,0))-INDEX($P$18:$P$18,MATCH($A26,$A$18:$A$18,0))*B26/INDEX($G$18:$G$18,MATCH($A26,$A$18:$A$18,0))) -> 1379.5345 | G26: =IF($A26="","",F26-D26) -> 8.3045212 | H26: =IF($A26="","",$B$8-D26) -> 6.77 | I26: =IF($A26="","",MAX(G26,H26)) -> 8.3045212 | J26: =IF($A26="","",I26*bar_per_m) -> 0.81467353 | K26: =IF($A26="","",IFERROR("PN"&SMALL(PN_list,COUNTIF(PN_list,"<"&J26)+1),"> max PN")) -> PN10 | L26: =IF($A26="","",G26-INDEX($U$18:$U$18,MATCH($A26,$A$18:$A$18,0))) -> -89.590471 | M26: critical high point | N26: =IF($A26="","",IF(G26<0,"NEGATIVE PRESSURE",IF(G26<p_min-0.005,"below minimum","OK"))) -> OK
A27: RAW_MAIN | B27: 129.8 | C27: 1365.87 | D27: =IF($A27="","",C27-cover) -> 1364.67 | E27: =IF($A27="","",D27+p_min+INDEX($R$18:$R$18,MATCH($A27,$A$18:$A$18,0))+INDEX($P$18:$P$18,MATCH($A27,$A$18:$A$18,0))*B27/INDEX($G$18:$G$18,MATCH($A27,$A$18:$A$18,0))) -> 1366.9013 | F27: =IF($A27="","",INDEX($S$18:$S$18,MATCH($A27,$A$18:$A$18,0))-INDEX($P$18:$P$18,MATCH($A27,$A$18:$A$18,0))*B27/INDEX($G$18:$G$18,MATCH($A27,$A$18:$A$18,0))) -> 1380.6903 | G27: =IF($A27="","",F27-D27) -> 16.020334 | H27: =IF($A27="","",$B$8-D27) -> 13.33 | I27: =IF($A27="","",MAX(G27,H27)) -> 16.020334 | J27: =IF($A27="","",I27*bar_per_m) -> 1.5715948 | K27: =IF($A27="","",IFERROR("PN"&SMALL(PN_list,COUNTIF(PN_list,"<"&J27)+1),"> max PN")) -> PN10 | L27: =IF($A27="","",G27-INDEX($U$18:$U$18,MATCH($A27,$A$18:$A$18,0))) -> -81.874658 | M27: lowest point (highest static pressure) | N27: =IF($A27="","",IF(G27<0,"NEGATIVE PRESSURE",IF(G27<p_min-0.005,"below minimum","OK"))) -> OK
D28: =IF($A28="","",C28-cover) | E28: =IF($A28="","",D28+p_min+INDEX($R$18:$R$18,MATCH($A28,$A$18:$A$18,0))+INDEX($P$18:$P$18,MATCH($A28,$A$18:$A$18,0))*B28/INDEX($G$18:$G$18,MATCH($A28,$A$18:$A$18,0))) | F28: =IF($A28="","",INDEX($S$18:$S$18,MATCH($A28,$A$18:$A$18,0))-INDEX($P$18:$P$18,MATCH($A28,$A$18:$A$18,0))*B28/INDEX($G$18:$G$18,MATCH($A28,$A$18:$A$18,0))) | G28: =IF($A28="","",F28-D28) | H28: =IF($A28="","",$B$8-D28) | I28: =IF($A28="","",MAX(G28,H28)) | J28: =IF($A28="","",I28*bar_per_m) | K28: =IF($A28="","",IFERROR("PN"&SMALL(PN_list,COUNTIF(PN_list,"<"&J28)+1),"> max PN")) | L28: =IF($A28="","",G28-INDEX($U$18:$U$18,MATCH($A28,$A$18:$A$18,0))) | M28: add a point: pipe ID, chainage, ground level | N28: =IF($A28="","",IF(G28<0,"NEGATIVE PRESSURE",IF(G28<p_min-0.005,"below minimum","OK")))
D29: =IF($A29="","",C29-cover) | E29: =IF($A29="","",D29+p_min+INDEX($R$18:$R$18,MATCH($A29,$A$18:$A$18,0))+INDEX($P$18:$P$18,MATCH($A29,$A$18:$A$18,0))*B29/INDEX($G$18:$G$18,MATCH($A29,$A$18:$A$18,0))) | F29: =IF($A29="","",INDEX($S$18:$S$18,MATCH($A29,$A$18:$A$18,0))-INDEX($P$18:$P$18,MATCH($A29,$A$18:$A$18,0))*B29/INDEX($G$18:$G$18,MATCH($A29,$A$18:$A$18,0))) | G29: =IF($A29="","",F29-D29) | H29: =IF($A29="","",$B$8-D29) | I29: =IF($A29="","",MAX(G29,H29)) | J29: =IF($A29="","",I29*bar_per_m) | K29: =IF($A29="","",IFERROR("PN"&SMALL(PN_list,COUNTIF(PN_list,"<"&J29)+1),"> max PN")) | L29: =IF($A29="","",G29-INDEX($U$18:$U$18,MATCH($A29,$A$18:$A$18,0))) | M29: add a point: pipe ID, chainage, ground level | N29: =IF($A29="","",IF(G29<0,"NEGATIVE PRESSURE",IF(G29<p_min-0.005,"below minimum","OK")))
D30: =IF($A30="","",C30-cover) | E30: =IF($A30="","",D30+p_min+INDEX($R$18:$R$18,MATCH($A30,$A$18:$A$18,0))+INDEX($P$18:$P$18,MATCH($A30,$A$18:$A$18,0))*B30/INDEX($G$18:$G$18,MATCH($A30,$A$18:$A$18,0))) | F30: =IF($A30="","",INDEX($S$18:$S$18,MATCH($A30,$A$18:$A$18,0))-INDEX($P$18:$P$18,MATCH($A30,$A$18:$A$18,0))*B30/INDEX($G$18:$G$18,MATCH($A30,$A$18:$A$18,0))) | G30: =IF($A30="","",F30-D30) | H30: =IF($A30="","",$B$8-D30) | I30: =IF($A30="","",MAX(G30,H30)) | J30: =IF($A30="","",I30*bar_per_m) | K30: =IF($A30="","",IFERROR("PN"&SMALL(PN_list,COUNTIF(PN_list,"<"&J30)+1),"> max PN")) | L30: =IF($A30="","",G30-INDEX($U$18:$U$18,MATCH($A30,$A$18:$A$18,0))) | M30: add a point: pipe ID, chainage, ground level | N30: =IF($A30="","",IF(G30<0,"NEGATIVE PRESSURE",IF(G30<p_min-0.005,"below minimum","OK")))
A32: E. Bernoulli result
A33: Head needed at zone start H_req | B33: =MAX($H$22:$H$22,$E$26:$E$30) -> 1380.9216 | C33: m a.s.l. | D33: largest of sections C, C2 (junctions) and D (points)
A34: Set by | B34: =IF(MAX($E$26:$E$30)>=MAX($H$22:$H$22),"point on "&INDEX($A$26:$A$30,MATCH(MAX($E$26:$E$30),$E$26:$E$30,0)),INDEX($A$22:$A$22,MATCH(MAX($H$22:$H$22),$H$22:$H$22,0))) -> MOMBA_WTP | D34: governing destination, junction or point
A35: Hp = H_req − z1 (suction at MINIMUM level) | B35: =$B$33-$B$5 -> 14.421604 | C35: m | D35: z1 + 0 + 0 + Hp = H_req (p = 0, V ≈ 0 at the sump surface)
A36: TDH design (suction at MINIMUM level) | B36: =$B$35+h_station -> 17.421604 | C36: m | D36: Hp + station losses → size pump and motor with this
A37: TDH low-head (suction at MAXIMUM level) | B37: =$B$33-$B$6+h_station -> 15.921604 | C37: m | D37: pump must also operate here (more flow unless throttled / VFD)
A38: Total pumped flow | B38: =J18 -> 0.27153253 | C38: m³/s | D38: flow in the first pipe
A39: Flow per pump | B39: =$B$38/$B$9 -> 0.27153253 | C39: m³/s
A40: Flow per pump | B40: =$B$39*3600 -> 977.51711 | C40: m³/h | D40: compare ER duty flow
A41: Hydraulic power per pump P_h = ρgQH | B41: =1000*g*$B$39*$B$36/1000 -> 46.40652 | C41: kW
A42: Shaft power per pump P_s = P_h / η_p | B42: =$B$41/$B$11 -> 61.87536 | C42: kW
A43: Motor needed = P_s × margin | B43: =$B$42*motor_margin -> 71.156664 | C43: kW
A44: Standard motor per pump | B44: =IFERROR(SMALL(Motor_list,COUNTIF(Motor_list,"<"&$B$43)+1),"> list") -> 75 | C44: kW | D44: next size up
A45: Electricity per day | B45: =$B$9*$B$42*$B$7/$B$12 -> 1448.1467 | C45: kWh/d
A46: Specific energy | B46: =$B$45/I18 -> 0.067338823 | C46: kWh/m³
A47: Electricity cost per year | B47: =$B$45*365*tariff -> 0 | C47: per year | D47: uses Global tariff
A48: TDH design minus ER duty head | B48: =$B$36-$B$14 -> -7.5783963 | C48: m | D48: negative = ER pump has spare head (throttle / VFD)
A49: Lowest pressure at any survey point (sheet Profile) | B49: =IF(COUNTIFS(Profile!$A$5:$A$2360,"Z3 Grit-WTP",Profile!$L$5:$L$2360,"yes")=0,"no points between tanks",_xlfn.MINIFS(Profile!$H$5:$H$2360,Profile!$A$5:$A$2360,"Z3 Grit-WTP",Profile!$L$5:$L$2360,"yes")) -> 8.3046103 | C49: m | D49: if below the minimum, add that point to section D
A51: F. Step by step in words (updates with the numbers)
A52: ="1. Flow: "&TEXT(I18,"#,##0")&" m³/d in "&TEXT($B$7,"0")&" h → Q = "&TEXT(K18,"0.0")&" l/s, V = "&TEXT(M18,"0.00")&" m/s in "&A18&"." -> 1. Flow: 21,505 m³/d in 22 h → Q = 271.5 l/s, V = 0.96 m/s in RAW_MAIN.
A53: ="2. Friction (Hazen-Williams): "&A18&" loses hL = "&TEXT(P18,"0.00")&" m over "&TEXT(G18,"#,##0")&" m ("&TEXT(Q18,"0.00")&" m/km)." -> 2. Friction (Hazen-Williams): RAW_MAIN loses hL = 1.92 m over 1,079 m (1.78 m/km).
A54: ="3. Point 1 = GRIT_TANK water surface at its MINIMUM level z1 = "&TEXT($B$5,"0.00")&" m (p = 0, V ≈ 0)." -> 3. Point 1 = GRIT_TANK water surface at its MINIMUM level z1 = 1366.50 m (p = 0, V ≈ 0).
A55: ="4. Point 2: the hardest place to reach is "&$B$34&"; it needs the HGL at the zone start to be H_req = "&TEXT($B$33,"0.00")&" m (its level + residual + losses on the way)." -> 4. Point 2: the hardest place to reach is MOMBA_WTP; it needs the HGL at the zone start to be H_req = 1380.92 m (its level + residual + losses on the way).
A56: ="5. Bernoulli: z1 + Hp = H_req → Hp = "&TEXT($B$33,"0.00")&" − "&TEXT($B$5,"0.00")&" = "&TEXT($B$35,"0.00")&" m; + station losses "&TEXT(h_station,"0.0")&" m → TDH = "&TEXT($B$36,"0.0")&" m." -> 5. Bernoulli: z1 + Hp = H_req → Hp = 1380.92 − 1366.50 = 14.42 m; + station losses 3.0 m → TDH = 17.4 m.
A57: ="6. With the suction tank full (MAXIMUM level "&TEXT($B$6,"0.00")&" m) TDH falls to "&TEXT($B$37,"0.0")&" m: the pump must work between "&TEXT($B$37,"0.0")&" and "&TEXT($B$36,"0.0")&" m at "&TEXT($B$40,"#,##0")&" m³/h per pump." -> 6. With the suction tank full (MAXIMUM level 1368.00 m) TDH falls to 15.9 m: the pump must work between 15.9 and 17.4 m at 978 m³/h per pump.
A58: ="7. Power: P = ρgQH/η = "&TEXT($B$42,"#,##0")&" kW per pump → motor "&TEXT($B$44,"#,##0")&" kW; ER duty head "&TEXT($B$14,"0")&" m (difference "&TEXT($B$48,"+0.0;-0.0")&" m)." -> 7. Power: P = ρgQH/η = 62 kW per pump → motor 75 kW; ER duty head 25 m (difference -7.6 m).
A59: ="8. Pressure: lowest pressure along the route = "&TEXT($B$49,"0.0")&" m (minimum allowed "&TEXT(p_min,"0")&" m); pipe class from section D and sheet Profile." -> 8. Pressure: lowest pressure along the route = 8.3 m (minimum allowed 2 m); pipe class from section D and sheet Profile.

Sheet Z4 WTP-Ikana
A1: Zone 4 – WTP clear-water pumps to Ikana GBR (pumped)
A2: The WTP pumps lift treated water about 300 m over ~20 km from the clear-water tank to Ikana GBR on the hill. Most of the head is lift; friction is the rest. Pressure is highest at the pumps.
A4: A. Inputs (levels come from sheet 'Levels')
A5: Start: MOMBA_WTP MINIMUM water level | B5: =Levels!$F$8 -> 1368.5 | C5: m a.s.l. | D5: point 1 of Bernoulli, design case (least energy at the start)
A6: Start: MOMBA_WTP MAXIMUM water level | B6: =Levels!$G$8 -> 1373 | C6: m a.s.l. | D6: low-head case for pumps / highest energy for gravity
A7: Operating hours per day | B7: 22 | C7: h/d | D7: ER: pumps 22 h/d; gravity 24 h/d
A8: Static level for pressure class | B8: =MAX(Levels!$L$9) -> 1668 | C8: m a.s.l. | D8: highest arrival level at the end of the zone (pipe full, pumps stopped)
A9: Number of duty pumps | B9: 3 | C9: no. | D9: working pumps sharing the flow
A10: Number of standby pumps | B10: 1 | C10: no. | D10: for information
A11: Pump efficiency η_p | B11: 0.78 | C11: – | D11: ASSUMED – use the pump curve
A12: Motor efficiency η_m | B12: 0.95 | C12: – | D12: ASSUMED
A13: ER duty flow per pump | B13: 304 | C13: m³/h | D13: Employer's Requirements
A14: ER duty head | B14: 330 | C14: m | D14: Employer's Requirements
A16: B. Pipes – flow (continuity) and friction (Hazen-Williams)
A17: Pipe | B17: From | C17: To | D17: Upstream pipe | E17: DN | F17: Internal D (mm) | G17: Length L (m) | H17: C (H-W) | I17: Daily volume (m³/d) | J17: Q (m³/s) | K17: Q (l/s) | L17: Area (m²) | M17: V (m/s) | N17: hf friction (m) | O17: hm minor (m) | P17: hL total (m) | Q17: Gradient (m/km) | R17: Loss before this pipe (m) | S17: HGL start (m) | T17: HGL end (m) | U17: Surge Δh = aV/g (m)
A18: WTP_IKANA_RM | B18: MOMBA_WTP | C18: IKANA_GBR | D18: – | E18: 600 | F18: =E18 -> 600 | G18: 19665.6 | H18: =C_default -> 120 | I18: =Demands!$B$25 -> 20000 | J18: =I18/($B$7*3600) -> 0.25252525 | K18: =J18*1000 -> 252.52525 | L18: =PI()*(F18/1000)^2/4 -> 0.28274334 | M18: =J18/L18 -> 0.89312538 | N18: =10.67*G18*J18^1.852/(H18^1.852*(F18/1000)^4.8704) -> 27.847654 | O18: =k_minor*N18 -> 2.7847654 | P18: =N18+O18 -> 30.63242 | Q18: =P18/G18*1000 -> 1.5576651 | R18: 0 | S18: =$B$33-R18 -> 1699.6324 | T18: =S18-P18 -> 1669 | U18: =wave*M18/g -> 91.042343
A20: C. Destinations – Bernoulli to each receiving water surface (levels from 'Levels')
A21: Destination | B21: Ends with pipe | C21: MIN level (m) | D21: MAX level (m) | E21: Arrival level (m) | F21: Residual (m) | G21: z2 = arrival + residual (m) | H21: Head needed at zone start = z2 + losses (m) | I21: Arriving HGL, design case (m) | J21: Excess head, design case (m) | K21: Excess head, start at MAX level (m) | L21: Comment
A22: IKANA_GBR | B22: WTP_IKANA_RM | C22: =Levels!$F$9 -> 1663.3 | D22: =Levels!$G$9 -> 1668 | E22: =Levels!$L$9 -> 1668 | F22: =h_res -> 1 | G22: =E22+F22 -> 1669 | H22: =G22+R18+P18 -> 1699.6324 | I22: =T18 -> 1669 | J22: =I22-G22 -> 0 | K22: =J22+($B$6-$B$5) -> 4.5 | L22: =IF(J22<-0.005,"NOT REACHED – more head needed",IF(K22>fcv_limit,"fit flow control valve / PRV (burns "&TEXT(J22,"0.0")&"–"&TEXT(K22,"0.0")&" m)","OK")) -> OK
A24: D. Critical points along the pipes – pressure check (add your own rows)
A25: Pipe | B25: Chainage in pipe x (m) | C25: Ground level (m) | D25: Pipe crown (m) | E25: Head needed at zone start (m) | F25: HGL at point (m) | G25: Pressure (m) | H25: Static (m) | I25: Working (m) | J25: Working (bar) | K25: PN required | L25: Transient min = p − Δh (m) | M25: Note | N25: Status
A26: WTP_IKANA_RM | B26: 19645.6 | C26: 1661.36 | D26: =IF($A26="","",C26-cover) -> 1660.16 | E26: =IF($A26="","",D26+p_min+INDEX($R$18:$R$18,MATCH($A26,$A$18:$A$18,0))+INDEX($P$18:$P$18,MATCH($A26,$A$18:$A$18,0))*B26/INDEX($G$18:$G$18,MATCH($A26,$A$18:$A$18,0))) -> 1692.7613 | F26: =IF($A26="","",INDEX($S$18:$S$18,MATCH($A26,$A$18:$A$18,0))-INDEX($P$18:$P$18,MATCH($A26,$A$18:$A$18,0))*B26/INDEX($G$18:$G$18,MATCH($A26,$A$18:$A$18,0))) -> 1669.0312 | G26: =IF($A26="","",F26-D26) -> 8.8711533 | H26: =IF($A26="","",$B$8-D26) -> 7.84 | I26: =IF($A26="","",MAX(G26,H26)) -> 8.8711533 | J26: =IF($A26="","",I26*bar_per_m) -> 0.87026014 | K26: =IF($A26="","",IFERROR("PN"&SMALL(PN_list,COUNTIF(PN_list,"<"&J26)+1),"> max PN")) -> PN10 | L26: =IF($A26="","",G26-INDEX($U$18:$U$18,MATCH($A26,$A$18:$A$18,0))) -> -82.171189 | M26: critical high point | N26: =IF($A26="","",IF(G26<0,"NEGATIVE PRESSURE",IF(G26<p_min-0.005,"below minimum","OK"))) -> OK
A27: WTP_IKANA_RM | B27: 50 | C27: 1373.21 | D27: =IF($A27="","",C27-cover) -> 1372.01 | E27: =IF($A27="","",D27+p_min+INDEX($R$18:$R$18,MATCH($A27,$A$18:$A$18,0))+INDEX($P$18:$P$18,MATCH($A27,$A$18:$A$18,0))*B27/INDEX($G$18:$G$18,MATCH($A27,$A$18:$A$18,0))) -> 1374.0879 | F27: =IF($A27="","",INDEX($S$18:$S$18,MATCH($A27,$A$18:$A$18,0))-INDEX($P$18:$P$18,MATCH($A27,$A$18:$A$18,0))*B27/INDEX($G$18:$G$18,MATCH($A27,$A$18:$A$18,0))) -> 1699.5545 | G27: =IF($A27="","",F27-D27) -> 327.54454 | H27: =IF($A27="","",$B$8-D27) -> 295.99 | I27: =IF($A27="","",MAX(G27,H27)) -> 327.54454 | J27: =IF($A27="","",I27*bar_per_m) -> 32.132119 | K27: =IF($A27="","",IFERROR("PN"&SMALL(PN_list,COUNTIF(PN_list,"<"&J27)+1),"> max PN")) -> PN40 | L27: =IF($A27="","",G27-INDEX($U$18:$U$18,MATCH($A27,$A$18:$A$18,0))) -> 236.50219 | M27: lowest point (highest static pressure) | N27: =IF($A27="","",IF(G27<0,"NEGATIVE PRESSURE",IF(G27<p_min-0.005,"below minimum","OK"))) -> OK
D28: =IF($A28="","",C28-cover) | E28: =IF($A28="","",D28+p_min+INDEX($R$18:$R$18,MATCH($A28,$A$18:$A$18,0))+INDEX($P$18:$P$18,MATCH($A28,$A$18:$A$18,0))*B28/INDEX($G$18:$G$18,MATCH($A28,$A$18:$A$18,0))) | F28: =IF($A28="","",INDEX($S$18:$S$18,MATCH($A28,$A$18:$A$18,0))-INDEX($P$18:$P$18,MATCH($A28,$A$18:$A$18,0))*B28/INDEX($G$18:$G$18,MATCH($A28,$A$18:$A$18,0))) | G28: =IF($A28="","",F28-D28) | H28: =IF($A28="","",$B$8-D28) | I28: =IF($A28="","",MAX(G28,H28)) | J28: =IF($A28="","",I28*bar_per_m) | K28: =IF($A28="","",IFERROR("PN"&SMALL(PN_list,COUNTIF(PN_list,"<"&J28)+1),"> max PN")) | L28: =IF($A28="","",G28-INDEX($U$18:$U$18,MATCH($A28,$A$18:$A$18,0))) | M28: add a point: pipe ID, chainage, ground level | N28: =IF($A28="","",IF(G28<0,"NEGATIVE PRESSURE",IF(G28<p_min-0.005,"below minimum","OK")))
D29: =IF($A29="","",C29-cover) | E29: =IF($A29="","",D29+p_min+INDEX($R$18:$R$18,MATCH($A29,$A$18:$A$18,0))+INDEX($P$18:$P$18,MATCH($A29,$A$18:$A$18,0))*B29/INDEX($G$18:$G$18,MATCH($A29,$A$18:$A$18,0))) | F29: =IF($A29="","",INDEX($S$18:$S$18,MATCH($A29,$A$18:$A$18,0))-INDEX($P$18:$P$18,MATCH($A29,$A$18:$A$18,0))*B29/INDEX($G$18:$G$18,MATCH($A29,$A$18:$A$18,0))) | G29: =IF($A29="","",F29-D29) | H29: =IF($A29="","",$B$8-D29) | I29: =IF($A29="","",MAX(G29,H29)) | J29: =IF($A29="","",I29*bar_per_m) | K29: =IF($A29="","",IFERROR("PN"&SMALL(PN_list,COUNTIF(PN_list,"<"&J29)+1),"> max PN")) | L29: =IF($A29="","",G29-INDEX($U$18:$U$18,MATCH($A29,$A$18:$A$18,0))) | M29: add a point: pipe ID, chainage, ground level | N29: =IF($A29="","",IF(G29<0,"NEGATIVE PRESSURE",IF(G29<p_min-0.005,"below minimum","OK")))
D30: =IF($A30="","",C30-cover) | E30: =IF($A30="","",D30+p_min+INDEX($R$18:$R$18,MATCH($A30,$A$18:$A$18,0))+INDEX($P$18:$P$18,MATCH($A30,$A$18:$A$18,0))*B30/INDEX($G$18:$G$18,MATCH($A30,$A$18:$A$18,0))) | F30: =IF($A30="","",INDEX($S$18:$S$18,MATCH($A30,$A$18:$A$18,0))-INDEX($P$18:$P$18,MATCH($A30,$A$18:$A$18,0))*B30/INDEX($G$18:$G$18,MATCH($A30,$A$18:$A$18,0))) | G30: =IF($A30="","",F30-D30) | H30: =IF($A30="","",$B$8-D30) | I30: =IF($A30="","",MAX(G30,H30)) | J30: =IF($A30="","",I30*bar_per_m) | K30: =IF($A30="","",IFERROR("PN"&SMALL(PN_list,COUNTIF(PN_list,"<"&J30)+1),"> max PN")) | L30: =IF($A30="","",G30-INDEX($U$18:$U$18,MATCH($A30,$A$18:$A$18,0))) | M30: add a point: pipe ID, chainage, ground level | N30: =IF($A30="","",IF(G30<0,"NEGATIVE PRESSURE",IF(G30<p_min-0.005,"below minimum","OK")))
A32: E. Bernoulli result
A33: Head needed at zone start H_req | B33: =MAX($H$22:$H$22,$E$26:$E$30) -> 1699.6324 | C33: m a.s.l. | D33: largest of sections C, C2 (junctions) and D (points)
A34: Set by | B34: =IF(MAX($E$26:$E$30)>=MAX($H$22:$H$22),"point on "&INDEX($A$26:$A$30,MATCH(MAX($E$26:$E$30),$E$26:$E$30,0)),INDEX($A$22:$A$22,MATCH(MAX($H$22:$H$22),$H$22:$H$22,0))) -> IKANA_GBR | D34: governing destination, junction or point
A35: Hp = H_req − z1 (suction at MINIMUM level) | B35: =$B$33-$B$5 -> 331.13242 | C35: m | D35: z1 + 0 + 0 + Hp = H_req (p = 0, V ≈ 0 at the sump surface)
A36: TDH design (suction at MINIMUM level) | B36: =$B$35+h_station -> 334.13242 | C36: m | D36: Hp + station losses → size pump and motor with this
A37: TDH low-head (suction at MAXIMUM level) | B37: =$B$33-$B$6+h_station -> 329.63242 | C37: m | D37: pump must also operate here (more flow unless throttled / VFD)
A38: Total pumped flow | B38: =J18 -> 0.25252525 | C38: m³/s | D38: flow in the first pipe
A39: Flow per pump | B39: =$B$38/$B$9 -> 0.084175084 | C39: m³/s
A40: Flow per pump | B40: =$B$39*3600 -> 303.0303 | C40: m³/h | D40: compare ER duty flow
A41: Hydraulic power per pump P_h = ρgQH | B41: =1000*g*$B$39*$B$36/1000 -> 275.91238 | C41: kW
A42: Shaft power per pump P_s = P_h / η_p | B42: =$B$41/$B$11 -> 353.73382 | C42: kW
A43: Motor needed = P_s × margin | B43: =$B$42*motor_margin -> 406.79389 | C43: kW
A44: Standard motor per pump | B44: =IFERROR(SMALL(Motor_list,COUNTIF(Motor_list,"<"&$B$43)+1),"> list") -> 450 | C44: kW | D44: next size up
A45: Electricity per day | B45: =$B$9*$B$42*$B$7/$B$12 -> 24575.191 | C45: kWh/d
A46: Specific energy | B46: =$B$45/I18 -> 1.2287596 | C46: kWh/m³
A47: Electricity cost per year | B47: =$B$45*365*tariff -> 0 | C47: per year | D47: uses Global tariff
A48: TDH design minus ER duty head | B48: =$B$36-$B$14 -> 4.1324197 | C48: m | D48: negative = ER pump has spare head (throttle / VFD)
A49: Lowest pressure at any survey point (sheet Profile) | B49: =IF(COUNTIFS(Profile!$A$5:$A$2360,"Z4 WTP-Ikana",Profile!$L$5:$L$2360,"yes")=0,"no points between tanks",_xlfn.MINIFS(Profile!$H$5:$H$2360,Profile!$A$5:$A$2360,"Z4 WTP-Ikana",Profile!$L$5:$L$2360,"yes")) -> 8.8711377 | C49: m | D49: if below the minimum, add that point to section D
A51: F. Step by step in words (updates with the numbers)
A52: ="1. Flow: "&TEXT(I18,"#,##0")&" m³/d in "&TEXT($B$7,"0")&" h → Q = "&TEXT(K18,"0.0")&" l/s, V = "&TEXT(M18,"0.00")&" m/s in "&A18&"." -> 1. Flow: 20,000 m³/d in 22 h → Q = 252.5 l/s, V = 0.89 m/s in WTP_IKANA_RM.
A53: ="2. Friction (Hazen-Williams): "&A18&" loses hL = "&TEXT(P18,"0.00")&" m over "&TEXT(G18,"#,##0")&" m ("&TEXT(Q18,"0.00")&" m/km)." -> 2. Friction (Hazen-Williams): WTP_IKANA_RM loses hL = 30.63 m over 19,666 m (1.56 m/km).
A54: ="3. Point 1 = MOMBA_WTP water surface at its MINIMUM level z1 = "&TEXT($B$5,"0.00")&" m (p = 0, V ≈ 0)." -> 3. Point 1 = MOMBA_WTP water surface at its MINIMUM level z1 = 1368.50 m (p = 0, V ≈ 0).
A55: ="4. Point 2: the hardest place to reach is "&$B$34&"; it needs the HGL at the zone start to be H_req = "&TEXT($B$33,"0.00")&" m (its level + residual + losses on the way)." -> 4. Point 2: the hardest place to reach is IKANA_GBR; it needs the HGL at the zone start to be H_req = 1699.63 m (its level + residual + losses on the way).
A56: ="5. Bernoulli: z1 + Hp = H_req → Hp = "&TEXT($B$33,"0.00")&" − "&TEXT($B$5,"0.00")&" = "&TEXT($B$35,"0.00")&" m; + station losses "&TEXT(h_station,"0.0")&" m → TDH = "&TEXT($B$36,"0.0")&" m." -> 5. Bernoulli: z1 + Hp = H_req → Hp = 1699.63 − 1368.50 = 331.13 m; + station losses 3.0 m → TDH = 334.1 m.
A57: ="6. With the suction tank full (MAXIMUM level "&TEXT($B$6,"0.00")&" m) TDH falls to "&TEXT($B$37,"0.0")&" m: the pump must work between "&TEXT($B$37,"0.0")&" and "&TEXT($B$36,"0.0")&" m at "&TEXT($B$40,"#,##0")&" m³/h per pump." -> 6. With the suction tank full (MAXIMUM level 1373.00 m) TDH falls to 329.6 m: the pump must work between 329.6 and 334.1 m at 303 m³/h per pump.
A58: ="7. Power: P = ρgQH/η = "&TEXT($B$42,"#,##0")&" kW per pump → motor "&TEXT($B$44,"#,##0")&" kW; ER duty head "&TEXT($B$14,"0")&" m (difference "&TEXT($B$48,"+0.0;-0.0")&" m)." -> 7. Power: P = ρgQH/η = 354 kW per pump → motor 450 kW; ER duty head 330 m (difference +4.1 m).
A59: ="8. Pressure: lowest pressure along the route = "&TEXT($B$49,"0.0")&" m (minimum allowed "&TEXT(p_min,"0")&" m); pipe class from section D and sheet Profile." -> 8. Pressure: lowest pressure along the route = 8.9 m (minimum allowed 2 m); pipe class from section D and sheet Profile.

Sheet Z5 Ikana-Nkangamo
A1: Zone 5 – Ikana GBR to Nkangamo BPS (gravity)
A2: Water runs downhill by gravity from Ikana GBR to the Nkangamo sump. With Ikana at its MINIMUM level it must still arrive (surplus ≥ 0); any surplus is burnt by the flow control valve at the sump inlet. Static pressure uses Ikana at its MAXIMUM level.
A4: A. Inputs (levels come from sheet 'Levels')
A5: Start: IKANA_GBR MINIMUM water level | B5: =Levels!$F$9 -> 1663.3 | C5: m a.s.l. | D5: point 1 of Bernoulli, design case (least energy at the start)
A6: Start: IKANA_GBR MAXIMUM water level | B6: =Levels!$G$9 -> 1668 | C6: m a.s.l. | D6: low-head case for pumps / highest energy for gravity
A7: Operating hours per day | B7: 24 | C7: h/d | D7: ER: pumps 22 h/d; gravity 24 h/d
A8: Static level for pressure class | B8: =$B$6 -> 1668 | C8: m a.s.l. | D8: MAXIMUM level of the supplying tank (water at rest)
A10: B. Pipes – flow (continuity) and friction (Hazen-Williams)
A11: Pipe | B11: From | C11: To | D11: Upstream pipe | E11: DN | F11: Internal D (mm) | G11: Length L (m) | H11: C (H-W) | I11: Daily volume (m³/d) | J11: Q (m³/s) | K11: Q (l/s) | L11: Area (m²) | M11: V (m/s) | N11: hf friction (m) | O11: hm minor (m) | P11: hL total (m) | Q11: Gradient (m/km) | R11: Loss before this pipe (m) | S11: HGL start (m) | T11: HGL end (m) | U11: Surge Δh = aV/g (m)
A12: IKANA_NKANGAMO_GM | B12: IKANA_GBR | C12: NKANGAMO_BPS | D12: – | E12: 600 | F12: =E12 -> 600 | G12: 38930.2 | H12: =C_default -> 120 | I12: =Demands!$B$24 -> 20000 | J12: =I12/($B$7*3600) -> 0.23148148 | K12: =J12*1000 -> 231.48148 | L12: =PI()*(F12/1000)^2/4 -> 0.28274334 | M12: =J12/L12 -> 0.81869827 | N12: =10.67*G12*J12^1.852/(H12^1.852*(F12/1000)^4.8704) -> 46.92277 | O12: =k_minor*N12 -> 4.692277 | P12: =N12+O12 -> 51.615046 | Q12: =P12/G12*1000 -> 1.3258356 | R12: 0 | S12: =$B$5-R12 -> 1663.3 | T12: =S12-P12 -> 1611.685 | U12: =wave*M12/g -> 83.455481
A14: C. Destinations – Bernoulli to each receiving water surface (levels from 'Levels')
A15: Destination | B15: Ends with pipe | C15: MIN level (m) | D15: MAX level (m) | E15: Arrival level (m) | F15: Residual (m) | G15: z2 = arrival + residual (m) | H15: Head needed at zone start = z2 + losses (m) | I15: Arriving HGL, design case (m) | J15: Excess head, design case (m) | K15: Excess head, start at MAX level (m) | L15: Comment
A16: NKANGAMO_BPS | B16: IKANA_NKANGAMO_GM | C16: =Levels!$F$10 -> 1553 | D16: =Levels!$G$10 -> 1557 | E16: =Levels!$L$10 -> 1557.5 | F16: =h_res -> 1 | G16: =E16+F16 -> 1558.5 | H16: =G16+R12+P12 -> 1610.115 | I16: =T12 -> 1611.685 | J16: =I16-G16 -> 53.184954 | K16: =J16+($B$6-$B$5) -> 57.884954 | L16: =IF(J16<-0.005,"NOT REACHED – more head needed",IF(K16>fcv_limit,"fit flow control valve / PRV (burns "&TEXT(J16,"0.0")&"–"&TEXT(K16,"0.0")&" m)","OK")) -> fit flow control valve / PRV (burns 53.2–57.9 m)
A18: D. Critical points along the pipes – pressure check (add your own rows)
A19: Pipe | B19: Chainage in pipe x (m) | C19: Ground level (m) | D19: Pipe crown (m) | E19: Head needed at zone start (m) | F19: HGL at point (m) | G19: Pressure (m) | H19: Static (m) | I19: Working (m) | J19: Working (bar) | K19: PN required | L19: Transient min = p − Δh (m) | M19: Note | N19: Status
A20: IKANA_NKANGAMO_GM | B20: 38668.7 | C20: 1547.62 | D20: =IF($A20="","",C20-cover) -> 1546.42 | E20: =IF($A20="","",D20+p_min+INDEX($R$12:$R$12,MATCH($A20,$A$12:$A$12,0))+INDEX($P$12:$P$12,MATCH($A20,$A$12:$A$12,0))*B20/INDEX($G$12:$G$12,MATCH($A20,$A$12:$A$12,0))) -> 1599.6883 | F20: =IF($A20="","",INDEX($S$12:$S$12,MATCH($A20,$A$12:$A$12,0))-INDEX($P$12:$P$12,MATCH($A20,$A$12:$A$12,0))*B20/INDEX($G$12:$G$12,MATCH($A20,$A$12:$A$12,0))) -> 1612.0317 | G20: =IF($A20="","",F20-D20) -> 65.61166 | H20: =IF($A20="","",$B$8-D20) -> 121.58 | I20: =IF($A20="","",MAX(G20,H20)) -> 121.58 | J20: =IF($A20="","",I20*bar_per_m) -> 11.926998 | K20: =IF($A20="","",IFERROR("PN"&SMALL(PN_list,COUNTIF(PN_list,"<"&J20)+1),"> max PN")) -> PN16 | L20: =IF($A20="","",G20-INDEX($U$12:$U$12,MATCH($A20,$A$12:$A$12,0))) -> -17.843821 | M20: critical high point | N20: =IF($A20="","",IF(G20<0,"NEGATIVE PRESSURE",IF(G20<p_min-0.005,"below minimum","OK"))) -> OK
A21: IKANA_NKANGAMO_GM | B21: 31064.3 | C21: 1450.82 | D21: =IF($A21="","",C21-cover) -> 1449.62 | E21: =IF($A21="","",D21+p_min+INDEX($R$12:$R$12,MATCH($A21,$A$12:$A$12,0))+INDEX($P$12:$P$12,MATCH($A21,$A$12:$A$12,0))*B21/INDEX($G$12:$G$12,MATCH($A21,$A$12:$A$12,0))) -> 1492.8062 | F21: =IF($A21="","",INDEX($S$12:$S$12,MATCH($A21,$A$12:$A$12,0))-INDEX($P$12:$P$12,MATCH($A21,$A$12:$A$12,0))*B21/INDEX($G$12:$G$12,MATCH($A21,$A$12:$A$12,0))) -> 1622.1138 | G21: =IF($A21="","",F21-D21) -> 172.49384 | H21: =IF($A21="","",$B$8-D21) -> 218.38 | I21: =IF($A21="","",MAX(G21,H21)) -> 218.38 | J21: =IF($A21="","",I21*bar_per_m) -> 21.423078 | K21: =IF($A21="","",IFERROR("PN"&SMALL(PN_list,COUNTIF(PN_list,"<"&J21)+1),"> max PN")) -> PN25 | L21: =IF($A21="","",G21-INDEX($U$12:$U$12,MATCH($A21,$A$12:$A$12,0))) -> 89.038363 | M21: lowest point (highest static pressure) | N21: =IF($A21="","",IF(G21<0,"NEGATIVE PRESSURE",IF(G21<p_min-0.005,"below minimum","OK"))) -> OK
D22: =IF($A22="","",C22-cover) | E22: =IF($A22="","",D22+p_min+INDEX($R$12:$R$12,MATCH($A22,$A$12:$A$12,0))+INDEX($P$12:$P$12,MATCH($A22,$A$12:$A$12,0))*B22/INDEX($G$12:$G$12,MATCH($A22,$A$12:$A$12,0))) | F22: =IF($A22="","",INDEX($S$12:$S$12,MATCH($A22,$A$12:$A$12,0))-INDEX($P$12:$P$12,MATCH($A22,$A$12:$A$12,0))*B22/INDEX($G$12:$G$12,MATCH($A22,$A$12:$A$12,0))) | G22: =IF($A22="","",F22-D22) | H22: =IF($A22="","",$B$8-D22) | I22: =IF($A22="","",MAX(G22,H22)) | J22: =IF($A22="","",I22*bar_per_m) | K22: =IF($A22="","",IFERROR("PN"&SMALL(PN_list,COUNTIF(PN_list,"<"&J22)+1),"> max PN")) | L22: =IF($A22="","",G22-INDEX($U$12:$U$12,MATCH($A22,$A$12:$A$12,0))) | M22: add a point: pipe ID, chainage, ground level | N22: =IF($A22="","",IF(G22<0,"NEGATIVE PRESSURE",IF(G22<p_min-0.005,"below minimum","OK")))
D23: =IF($A23="","",C23-cover) | E23: =IF($A23="","",D23+p_min+INDEX($R$12:$R$12,MATCH($A23,$A$12:$A$12,0))+INDEX($P$12:$P$12,MATCH($A23,$A$12:$A$12,0))*B23/INDEX($G$12:$G$12,MATCH($A23,$A$12:$A$12,0))) | F23: =IF($A23="","",INDEX($S$12:$S$12,MATCH($A23,$A$12:$A$12,0))-INDEX($P$12:$P$12,MATCH($A23,$A$12:$A$12,0))*B23/INDEX($G$12:$G$12,MATCH($A23,$A$12:$A$12,0))) | G23: =IF($A23="","",F23-D23) | H23: =IF($A23="","",$B$8-D23) | I23: =IF($A23="","",MAX(G23,H23)) | J23: =IF($A23="","",I23*bar_per_m) | K23: =IF($A23="","",IFERROR("PN"&SMALL(PN_list,COUNTIF(PN_list,"<"&J23)+1),"> max PN")) | L23: =IF($A23="","",G23-INDEX($U$12:$U$12,MATCH($A23,$A$12:$A$12,0))) | M23: add a point: pipe ID, chainage, ground level | N23: =IF($A23="","",IF(G23<0,"NEGATIVE PRESSURE",IF(G23<p_min-0.005,"below minimum","OK")))
D24: =IF($A24="","",C24-cover) | E24: =IF($A24="","",D24+p_min+INDEX($R$12:$R$12,MATCH($A24,$A$12:$A$12,0))+INDEX($P$12:$P$12,MATCH($A24,$A$12:$A$12,0))*B24/INDEX($G$12:$G$12,MATCH($A24,$A$12:$A$12,0))) | F24: =IF($A24="","",INDEX($S$12:$S$12,MATCH($A24,$A$12:$A$12,0))-INDEX($P$12:$P$12,MATCH($A24,$A$12:$A$12,0))*B24/INDEX($G$12:$G$12,MATCH($A24,$A$12:$A$12,0))) | G24: =IF($A24="","",F24-D24) | H24: =IF($A24="","",$B$8-D24) | I24: =IF($A24="","",MAX(G24,H24)) | J24: =IF($A24="","",I24*bar_per_m) | K24: =IF($A24="","",IFERROR("PN"&SMALL(PN_list,COUNTIF(PN_list,"<"&J24)+1),"> max PN")) | L24: =IF($A24="","",G24-INDEX($U$12:$U$12,MATCH($A24,$A$12:$A$12,0))) | M24: add a point: pipe ID, chainage, ground level | N24: =IF($A24="","",IF(G24<0,"NEGATIVE PRESSURE",IF(G24<p_min-0.005,"below minimum","OK")))
A26: E. Bernoulli result
A27: Head needed at zone start H_req | B27: =MAX($H$16:$H$16,$E$20:$E$24) -> 1610.115 | C27: m a.s.l. | D27: largest of sections C, C2 (junctions) and D (points)
A28: Set by | B28: =IF(MAX($E$20:$E$24)>=MAX($H$16:$H$16),"point on "&INDEX($A$20:$A$24,MATCH(MAX($E$20:$E$24),$E$20:$E$24,0)),INDEX($A$16:$A$16,MATCH(MAX($H$16:$H$16),$H$16:$H$16,0))) -> NKANGAMO_BPS | D28: governing destination, junction or point
A29: Surplus = z1 − H_req (start at MINIMUM level) | B29: =$B$5-$B$27 -> 53.184954 | C29: m | D29: design case: must be ≥ 0
A30: Surplus with start at MAXIMUM level | B30: =$B$6-$B$27 -> 57.884954 | C30: m | D30: largest head the valve must burn
A31: Status | B31: =IF($B$29<-0.005,"SHORT OF HEAD at minimum level – bigger pipe, lower outlet, higher tank or pump","OK – valve burns "&TEXT($B$29,"0.0")&" to "&TEXT($B$30,"0.0")&" m") -> OK – valve burns 53.2 to 57.9 m
A32: Lowest pressure at any survey point (sheet Profile) | B32: =IF(COUNTIFS(Profile!$A$5:$A$2360,"Z5 Ikana-Nkangamo",Profile!$L$5:$L$2360,"yes")=0,"no points between tanks",_xlfn.MINIFS(Profile!$H$5:$H$2360,Profile!$A$5:$A$2360,"Z5 Ikana-Nkangamo",Profile!$L$5:$L$2360,"yes")) -> 65.611726 | C32: m | D32: if below the minimum, add that point to section D
A34: F. Step by step in words (updates with the numbers)
A35: ="1. Flow: "&TEXT(I12,"#,##0")&" m³/d in "&TEXT($B$7,"0")&" h → Q = "&TEXT(K12,"0.0")&" l/s, V = "&TEXT(M12,"0.00")&" m/s in "&A12&"." -> 1. Flow: 20,000 m³/d in 24 h → Q = 231.5 l/s, V = 0.82 m/s in IKANA_NKANGAMO_GM.
A36: ="2. Friction (Hazen-Williams): "&A12&" loses hL = "&TEXT(P12,"0.00")&" m over "&TEXT(G12,"#,##0")&" m ("&TEXT(Q12,"0.00")&" m/km)." -> 2. Friction (Hazen-Williams): IKANA_NKANGAMO_GM loses hL = 51.62 m over 38,930 m (1.33 m/km).
A37: ="3. Point 1 = IKANA_GBR water surface at its MINIMUM level z1 = "&TEXT($B$5,"0.00")&" m (p = 0, V ≈ 0)." -> 3. Point 1 = IKANA_GBR water surface at its MINIMUM level z1 = 1663.30 m (p = 0, V ≈ 0).
A38: ="4. Point 2: the hardest place to reach is "&$B$28&"; it needs the HGL at the zone start to be H_req = "&TEXT($B$27,"0.00")&" m (its level + residual + losses on the way)." -> 4. Point 2: the hardest place to reach is NKANGAMO_BPS; it needs the HGL at the zone start to be H_req = 1610.12 m (its level + residual + losses on the way).
A39: ="5. Bernoulli without pump: z1 = H_req + surplus → surplus = "&TEXT($B$5,"0.00")&" − "&TEXT($B$27,"0.00")&" = "&TEXT($B$29,"0.00")&" m." -> 5. Bernoulli without pump: z1 = H_req + surplus → surplus = 1663.30 − 1610.12 = 53.18 m.
A40: ="6. With the supplying tank full (MAXIMUM level "&TEXT($B$6,"0.00")&" m) the surplus is "&TEXT($B$30,"0.00")&" m. "&IF($B$29<-0.005,"Negative at minimum level: the zone cannot deliver – change pipe or levels.","A flow control valve burns this so the flow stays at design.") -> 6. With the supplying tank full (MAXIMUM level 1668.00 m) the surplus is 57.88 m. A flow control valve burns this so the flow stays at design.
A41: ="8. Pressure: lowest pressure along the route = "&TEXT($B$32,"0.0")&" m (minimum allowed "&TEXT(p_min,"0")&" m); pipe class from section D and sheet Profile." -> 8. Pressure: lowest pressure along the route = 65.6 m (minimum allowed 2 m); pipe class from section D and sheet Profile.

Sheet Z6 Nkangamo-Uhuru
A1: Zone 6 – Nkangamo BPS to Uhuru Park GBR and existing tanks (pumped)
A2: One pump station feeds four tanks (ESR, GSR01, Ipito, Uhuru Park) and crosses a high point near 74 km. Bernoulli is applied to each; the one needing the most head sets the pumps, the others get flow control valves.
A4: A. Inputs (levels come from sheet 'Levels')
A5: Start: NKANGAMO_BPS MINIMUM water level | B5: =Levels!$F$10 -> 1553 | C5: m a.s.l. | D5: point 1 of Bernoulli, design case (least energy at the start)
A6: Start: NKANGAMO_BPS MAXIMUM water level | B6: =Levels!$G$10 -> 1557 | C6: m a.s.l. | D6: low-head case for pumps / highest energy for gravity
A7: Operating hours per day | B7: 22 | C7: h/d | D7: ER: pumps 22 h/d; gravity 24 h/d
A8: Static level for pressure class | B8: =MAX(Levels!$L$12,Levels!$L$13,Levels!$L$14,Levels!$L$11) -> 1706.5 | C8: m a.s.l. | D8: highest arrival level at the end of the zone (pipe full, pumps stopped)
A9: Number of duty pumps | B9: 2 | C9: no. | D9: working pumps sharing the flow
A10: Number of standby pumps | B10: 1 | C10: no. | D10: for information
A11: Pump efficiency η_p | B11: 0.78 | C11: – | D11: ASSUMED – use the pump curve
A12: Motor efficiency η_m | B12: 0.95 | C12: – | D12: ASSUMED
A13: ER duty flow per pump | B13: 455 | C13: m³/h | D13: Employer's Requirements
A14: ER duty head | B14: 221 | C14: m | D14: Employer's Requirements
A16: B. Pipes – flow (continuity) and friction (Hazen-Williams)
A17: Pipe | B17: From | C17: To | D17: Upstream pipe | E17: DN | F17: Internal D (mm) | G17: Length L (m) | H17: C (H-W) | I17: Daily volume (m³/d) | J17: Q (m³/s) | K17: Q (l/s) | L17: Area (m²) | M17: V (m/s) | N17: hf friction (m) | O17: hm minor (m) | P17: hL total (m) | Q17: Gradient (m/km) | R17: Loss before this pipe (m) | S17: HGL start (m) | T17: HGL end (m) | U17: Surge Δh = aV/g (m)
A18: BPS_RM_1 | B18: NKANGAMO_BPS | C18: J-001N | D18: – | E18: 600 | F18: =E18 -> 600 | G18: 19581.4 | H18: =C_default -> 120 | I18: =Demands!$B$23 -> 20000 | J18: =I18/($B$7*3600) -> 0.25252525 | K18: =J18*1000 -> 252.52525 | L18: =PI()*(F18/1000)^2/4 -> 0.28274334 | M18: =J18/L18 -> 0.89312538 | N18: =10.67*G18*J18^1.852/(H18^1.852*(F18/1000)^4.8704) -> 27.728422 | O18: =k_minor*N18 -> 2.7728422 | P18: =N18+O18 -> 30.501264 | Q18: =P18/G18*1000 -> 1.5576651 | R18: 0 | S18: =$B$50-R18 -> 1738.2284 | T18: =S18-P18 -> 1707.7271 | U18: =wave*M18/g -> 91.042343
A19: BPS_RM_2 | B19: J-001N | C19: J-002N | D19: BPS_RM_1 | E19: 600 | F19: =E19 -> 600 | G19: 40 | H19: =C_default -> 120 | I19: =Demands!$B$22 -> 19628.48 | J19: =I19/($B$7*3600) -> 0.24783434 | K19: =J19*1000 -> 247.83434 | L19: =PI()*(F19/1000)^2/4 -> 0.28274334 | M19: =J19/L19 -> 0.87653469 | N19: =10.67*G19*J19^1.852/(H19^1.852*(F19/1000)^4.8704) -> 0.05470915 | O19: =k_minor*N19 -> 0.005470915 | P19: =N19+O19 -> 0.060180065 | Q19: =P19/G19*1000 -> 1.5045016 | R19: =R18+P18 -> 30.501264 | S19: =$B$50-R19 -> 1707.7271 | T19: =S19-P19 -> 1707.6669 | U19: =wave*M19/g -> 89.35114
A20: BPS_RM_3 | B20: J-002N | C20: J-003N | D20: BPS_RM_2 | E20: 600 | F20: =E20 -> 600 | G20: 100.2 | H20: =C_default -> 120 | I20: =Demands!$B$21 -> 18081.92 | J20: =I20/($B$7*3600) -> 0.22830707 | K20: =J20*1000 -> 228.30707 | L20: =PI()*(F20/1000)^2/4 -> 0.28274334 | M20: =J20/L20 -> 0.80747109 | N20: =10.67*G20*J20^1.852/(H20^1.852*(F20/1000)^4.8704) -> 0.11772223 | O20: =k_minor*N20 -> 0.011772223 | P20: =N20+O20 -> 0.12949445 | Q20: =P20/G20*1000 -> 1.2923598 | R20: =R19+P19 -> 30.561444 | S20: =$B$50-R20 -> 1707.6669 | T20: =S20-P20 -> 1707.5375 | U20: =wave*M20/g -> 82.311018
A21: UHURU_INLET | B21: J-003N | C21: UHURU_PARK_GBR | D21: BPS_RM_3 | E21: 600 | F21: =E21 -> 600 | G21: 50 | H21: =C_default -> 120 | I21: =Demands!$B$17 -> 17459.82 | J21: =I21/($B$7*3600) -> 0.22045227 | K21: =J21*1000 -> 220.45227 | L21: =PI()*(F21/1000)^2/4 -> 0.28274334 | M21: =J21/L21 -> 0.77969042 | N21: =10.67*G21*J21^1.852/(H21^1.852*(F21/1000)^4.8704) -> 0.055055601 | O21: =k_minor*N21 -> 0.0055055601 | P21: =N21+O21 -> 0.060561161 | Q21: =P21/G21*1000 -> 1.2112232 | R21: =R20+P20 -> 30.690939 | S21: =$B$50-R21 -> 1707.5375 | T21: =S21-P21 -> 1707.4769 | U21: =wave*M21/g -> 79.479146
A22: ESR_BRANCH | B22: J-001N | C22: TUNDUMA_ESR | D22: BPS_RM_1 | E22: 100 | F22: =E22 -> 100 | G22: 38 | H22: =C_default -> 120 | I22: =Demands!$B$20 -> 371.52 | J22: =I22/($B$7*3600) -> 0.0046909091 | K22: =J22*1000 -> 4.6909091 | L22: =PI()*(F22/1000)^2/4 -> 0.0078539816 | M22: =J22/L22 -> 0.5972651 | N22: =10.67*G22*J22^1.852/(H22^1.852*(F22/1000)^4.8704) -> 0.20647731 | O22: =k_minor*N22 -> 0.020647731 | P22: =N22+O22 -> 0.22712505 | Q22: =P22/G22*1000 -> 5.9769749 | R22: =R18+P18 -> 30.501264 | S22: =$B$50-R22 -> 1707.7271 | T22: =S22-P22 -> 1707.5 | U22: =wave*M22/g -> 60.883292
A23: GSR01_BRANCH | B23: J-002N | C23: UHURU_GSR01 | D23: BPS_RM_2 | E23: 150 | F23: =E23 -> 150 | G23: 40 | H23: =C_default -> 120 | I23: =Demands!$B$19 -> 1546.56 | J23: =I23/($B$7*3600) -> 0.019527273 | K23: =J23*1000 -> 19.527273 | L23: =PI()*(F23/1000)^2/4 -> 0.017671459 | M23: =J23/L23 -> 1.1050176 | N23: =10.67*G23*J23^1.852/(H23^1.852*(F23/1000)^4.8704) -> 0.4232667 | O23: =k_minor*N23 -> 0.04232667 | P23: =N23+O23 -> 0.46559337 | Q23: =P23/G23*1000 -> 11.639834 | R23: =R19+P19 -> 30.561444 | S23: =$B$50-R23 -> 1707.6669 | T23: =S23-P23 -> 1707.2014 | U23: =wave*M23/g -> 112.64196
A24: IPITO_BRANCH | B24: J-003N | C24: IPITO_GSR02 | D24: BPS_RM_3 | E24: 150 | F24: =E24 -> 150 | G24: 4220.8 | H24: =C_default -> 120 | I24: =Demands!$B$18 -> 622.1 | J24: =I24/($B$7*3600) -> 0.007854798 | K24: =J24*1000 -> 7.854798 | L24: =PI()*(F24/1000)^2/4 -> 0.017671459 | M24: =J24/L24 -> 0.44449064 | N24: =10.67*G24*J24^1.852/(H24^1.852*(F24/1000)^4.8704) -> 8.2693374 | O24: =k_minor*N24 -> 0.82693374 | P24: =N24+O24 -> 9.0962712 | Q24: =P24/G24*1000 -> 2.1551059 | R24: =R20+P20 -> 30.690939 | S24: =$B$50-R24 -> 1707.5375 | T24: =S24-P24 -> 1698.4412 | U24: =wave*M24/g -> 45.309953
A26: C. Destinations – Bernoulli to each receiving water surface (levels from 'Levels')
A27: Destination | B27: Ends with pipe | C27: MIN level (m) | D27: MAX level (m) | E27: Arrival level (m) | F27: Residual (m) | G27: z2 = arrival + residual (m) | H27: Head needed at zone start = z2 + losses (m) | I27: Arriving HGL, design case (m) | J27: Excess head, design case (m) | K27: Excess head, start at MAX level (m) | L27: Comment
A28: TUNDUMA_ESR | B28: ESR_BRANCH | C28: =Levels!$F$12 -> 1703.5 | D28: =Levels!$G$12 -> 1706.5 | E28: =Levels!$L$12 -> 1706.5 | F28: =h_res -> 1 | G28: =E28+F28 -> 1707.5 | H28: =G28+R22+P22 -> 1738.2284 | I28: =T22 -> 1707.5 | J28: =I28-G28 -> 0 | K28: =J28+($B$6-$B$5) -> 4 | L28: =IF(J28<-0.005,"NOT REACHED – more head needed",IF(K28>fcv_limit,"fit flow control valve / PRV (burns "&TEXT(J28,"0.0")&"–"&TEXT(K28,"0.0")&" m)","OK")) -> OK
A29: UHURU_GSR01 | B29: GSR01_BRANCH | C29: =Levels!$F$13 -> 1698.4 | D29: =Levels!$G$13 -> 1701.4 | E29: =Levels!$L$13 -> 1701.4 | F29: =h_res -> 1 | G29: =E29+F29 -> 1702.4 | H29: =G29+R23+P23 -> 1733.427 | I29: =T23 -> 1707.2014 | J29: =I29-G29 -> 4.8013516 | K29: =J29+($B$6-$B$5) -> 8.8013516 | L29: =IF(J29<-0.005,"NOT REACHED – more head needed",IF(K29>fcv_limit,"fit flow control valve / PRV (burns "&TEXT(J29,"0.0")&"–"&TEXT(K29,"0.0")&" m)","OK")) -> fit flow control valve / PRV (burns 4.8–8.8 m)
A30: IPITO_GSR02 | B30: IPITO_BRANCH | C30: =Levels!$F$14 -> 1681.2 | D30: =Levels!$G$14 -> 1684.2 | E30: =Levels!$L$14 -> 1684.2 | F30: =h_res -> 1 | G30: =E30+F30 -> 1685.2 | H30: =G30+R24+P24 -> 1724.9872 | I30: =T24 -> 1698.4412 | J30: =I30-G30 -> 13.241179 | K30: =J30+($B$6-$B$5) -> 17.241179 | L30: =IF(J30<-0.005,"NOT REACHED – more head needed",IF(K30>fcv_limit,"fit flow control valve / PRV (burns "&TEXT(J30,"0.0")&"–"&TEXT(K30,"0.0")&" m)","OK")) -> fit flow control valve / PRV (burns 13.2–17.2 m)
A31: UHURU_PARK_GBR | B31: UHURU_INLET | C31: =Levels!$F$11 -> 1697.6 | D31: =Levels!$G$11 -> 1702.3 | E31: =Levels!$L$11 -> 1702.3 | F31: =h_res -> 1 | G31: =E31+F31 -> 1703.3 | H31: =G31+R21+P21 -> 1734.0515 | I31: =T21 -> 1707.4769 | J31: =I31-G31 -> 4.1768894 | K31: =J31+($B$6-$B$5) -> 8.1768894 | L31: =IF(J31<-0.005,"NOT REACHED – more head needed",IF(K31>fcv_limit,"fit flow control valve / PRV (burns "&TEXT(J31,"0.0")&"–"&TEXT(K31,"0.0")&" m)","OK")) -> fit flow control valve / PRV (burns 4.2–8.2 m)
A33: C2. Junctions – minimum pressure at offtakes (ER Table 7)
A34: Junction | B34: End of pipe | C34: Ground level (m) | D34: Minimum pressure (m) | E34: Head needed at zone start = ground + p_min + losses (m) | F34: HGL at junction (m) | G34: Pressure (m) | H34: Status
A35: J-001N | B35: BPS_RM_1 | C35: 1698.34 | D35: =p_min_j -> 5 | E35: =C35+D35+R18+P18 -> 1733.8413 | F35: =T18 -> 1707.7271 | G35: =F35-C35 -> 9.387125 | H35: =IF(G35<D35-0.005,"below minimum","OK") -> OK
A36: J-002N | B36: BPS_RM_2 | C36: 1699.25 | D36: =p_min_j -> 5 | E36: =C36+D36+R19+P19 -> 1734.8114 | F36: =T19 -> 1707.6669 | G36: =F36-C36 -> 8.416945 | H36: =IF(G36<D36-0.005,"below minimum","OK") -> OK
A37: J-003N | B37: BPS_RM_3 | C37: 1699.34 | D37: =p_min_j -> 5 | E37: =C37+D37+R20+P20 -> 1735.0309 | F37: =T20 -> 1707.5375 | G37: =F37-C37 -> 8.1974505 | H37: =IF(G37<D37-0.005,"below minimum","OK") -> OK
A39: D. Critical points along the pipes – pressure check (add your own rows)
A40: Pipe | B40: Chainage in pipe x (m) | C40: Ground level (m) | D40: Pipe crown (m) | E40: Head needed at zone start (m) | F40: HGL at point (m) | G40: Pressure (m) | H40: Static (m) | I40: Working (m) | J40: Working (bar) | K40: PN required | L40: Transient min = p − Δh (m) | M40: Note | N40: Status
A41: BPS_RM_1 | B41: 14583.1 | C41: 1710.04 | D41: =IF($A41="","",C41-cover) -> 1708.84 | E41: =IF($A41="","",D41+p_min+INDEX($R$18:$R$24,MATCH($A41,$A$18:$A$24,0))+INDEX($P$18:$P$24,MATCH($A41,$A$18:$A$24,0))*B41/INDEX($G$18:$G$24,MATCH($A41,$A$18:$A$24,0))) -> 1733.5556 | F41: =IF($A41="","",INDEX($S$18:$S$24,MATCH($A41,$A$18:$A$24,0))-INDEX($P$18:$P$24,MATCH($A41,$A$18:$A$24,0))*B41/INDEX($G$18:$G$24,MATCH($A41,$A$18:$A$24,0))) -> 1715.5128 | G41: =IF($A41="","",F41-D41) -> 6.6728028 | H41: =IF($A41="","",$B$8-D41) -> -2.34 | I41: =IF($A41="","",MAX(G41,H41)) -> 6.6728028 | J41: =IF($A41="","",I41*bar_per_m) -> 0.65460195 | K41: =IF($A41="","",IFERROR("PN"&SMALL(PN_list,COUNTIF(PN_list,"<"&J41)+1),"> max PN")) -> PN10 | L41: =IF($A41="","",G41-INDEX($U$18:$U$24,MATCH($A41,$A$18:$A$24,0))) -> -84.36954 | M41: critical high point | N41: =IF($A41="","",IF(G41<0,"NEGATIVE PRESSURE",IF(G41<p_min-0.005,"below minimum","OK"))) -> OK
A42: BPS_RM_1 | B42: 5635.7 | C42: 1561.57 | D42: =IF($A42="","",C42-cover) -> 1560.37 | E42: =IF($A42="","",D42+p_min+INDEX($R$18:$R$24,MATCH($A42,$A$18:$A$24,0))+INDEX($P$18:$P$24,MATCH($A42,$A$18:$A$24,0))*B42/INDEX($G$18:$G$24,MATCH($A42,$A$18:$A$24,0))) -> 1571.1485 | F42: =IF($A42="","",INDEX($S$18:$S$24,MATCH($A42,$A$18:$A$24,0))-INDEX($P$18:$P$24,MATCH($A42,$A$18:$A$24,0))*B42/INDEX($G$18:$G$24,MATCH($A42,$A$18:$A$24,0))) -> 1729.4499 | G42: =IF($A42="","",F42-D42) -> 169.07986 | H42: =IF($A42="","",$B$8-D42) -> 146.13 | I42: =IF($A42="","",MAX(G42,H42)) -> 169.07986 | J42: =IF($A42="","",I42*bar_per_m) -> 16.586734 | K42: =IF($A42="","",IFERROR("PN"&SMALL(PN_list,COUNTIF(PN_list,"<"&J42)+1),"> max PN")) -> PN25 | L42: =IF($A42="","",G42-INDEX($U$18:$U$24,MATCH($A42,$A$18:$A$24,0))) -> 78.037513 | M42: lowest point (highest static pressure) | N42: =IF($A42="","",IF(G42<0,"NEGATIVE PRESSURE",IF(G42<p_min-0.005,"below minimum","OK"))) -> OK
A43: IPITO_BRANCH | B43: 145 | C43: 1699.45 | D43: =IF($A43="","",C43-cover) -> 1698.25 | E43: =IF($A43="","",D43+p_min+INDEX($R$18:$R$24,MATCH($A43,$A$18:$A$24,0))+INDEX($P$18:$P$24,MATCH($A43,$A$18:$A$24,0))*B43/INDEX($G$18:$G$24,MATCH($A43,$A$18:$A$24,0))) -> 1731.2534 | F43: =IF($A43="","",INDEX($S$18:$S$24,MATCH($A43,$A$18:$A$24,0))-INDEX($P$18:$P$24,MATCH($A43,$A$18:$A$24,0))*B43/INDEX($G$18:$G$24,MATCH($A43,$A$18:$A$24,0))) -> 1707.225 | G43: =IF($A43="","",F43-D43) -> 8.9749602 | H43: =IF($A43="","",$B$8-D43) -> 8.25 | I43: =IF($A43="","",MAX(G43,H43)) -> 8.9749602 | J43: =IF($A43="","",I43*bar_per_m) -> 0.88044359 | K43: =IF($A43="","",IFERROR("PN"&SMALL(PN_list,COUNTIF(PN_list,"<"&J43)+1),"> max PN")) -> PN10 | L43: =IF($A43="","",G43-INDEX($U$18:$U$24,MATCH($A43,$A$18:$A$24,0))) -> -36.334993 | M43: critical high point | N43: =IF($A43="","",IF(G43<0,"NEGATIVE PRESSURE",IF(G43<p_min-0.005,"below minimum","OK"))) -> OK
A44: IPITO_BRANCH | B44: 3317.8 | C44: 1603.64 | D44: =IF($A44="","",C44-cover) -> 1602.44 | E44: =IF($A44="","",D44+p_min+INDEX($R$18:$R$24,MATCH($A44,$A$18:$A$24,0))+INDEX($P$18:$P$24,MATCH($A44,$A$18:$A$24,0))*B44/INDEX($G$18:$G$24,MATCH($A44,$A$18:$A$24,0))) -> 1642.2811 | F44: =IF($A44="","",INDEX($S$18:$S$24,MATCH($A44,$A$18:$A$24,0))-INDEX($P$18:$P$24,MATCH($A44,$A$18:$A$24,0))*B44/INDEX($G$18:$G$24,MATCH($A44,$A$18:$A$24,0))) -> 1700.3872 | G44: =IF($A44="","",F44-D44) -> 97.94724 | H44: =IF($A44="","",$B$8-D44) -> 104.06 | I44: =IF($A44="","",MAX(G44,H44)) -> 104.06 | J44: =IF($A44="","",I44*bar_per_m) -> 10.208286 | K44: =IF($A44="","",IFERROR("PN"&SMALL(PN_list,COUNTIF(PN_list,"<"&J44)+1),"> max PN")) -> PN16 | L44: =IF($A44="","",G44-INDEX($U$18:$U$24,MATCH($A44,$A$18:$A$24,0))) -> 52.637287 | M44: lowest point (highest static pressure) | N44: =IF($A44="","",IF(G44<0,"NEGATIVE PRESSURE",IF(G44<p_min-0.005,"below minimum","OK"))) -> OK
D45: =IF($A45="","",C45-cover) | E45: =IF($A45="","",D45+p_min+INDEX($R$18:$R$24,MATCH($A45,$A$18:$A$24,0))+INDEX($P$18:$P$24,MATCH($A45,$A$18:$A$24,0))*B45/INDEX($G$18:$G$24,MATCH($A45,$A$18:$A$24,0))) | F45: =IF($A45="","",INDEX($S$18:$S$24,MATCH($A45,$A$18:$A$24,0))-INDEX($P$18:$P$24,MATCH($A45,$A$18:$A$24,0))*B45/INDEX($G$18:$G$24,MATCH($A45,$A$18:$A$24,0))) | G45: =IF($A45="","",F45-D45) | H45: =IF($A45="","",$B$8-D45) | I45: =IF($A45="","",MAX(G45,H45)) | J45: =IF($A45="","",I45*bar_per_m) | K45: =IF($A45="","",IFERROR("PN"&SMALL(PN_list,COUNTIF(PN_list,"<"&J45)+1),"> max PN")) | L45: =IF($A45="","",G45-INDEX($U$18:$U$24,MATCH($A45,$A$18:$A$24,0))) | M45: add a point: pipe ID, chainage, ground level | N45: =IF($A45="","",IF(G45<0,"NEGATIVE PRESSURE",IF(G45<p_min-0.005,"below minimum","OK")))
D46: =IF($A46="","",C46-cover) | E46: =IF($A46="","",D46+p_min+INDEX($R$18:$R$24,MATCH($A46,$A$18:$A$24,0))+INDEX($P$18:$P$24,MATCH($A46,$A$18:$A$24,0))*B46/INDEX($G$18:$G$24,MATCH($A46,$A$18:$A$24,0))) | F46: =IF($A46="","",INDEX($S$18:$S$24,MATCH($A46,$A$18:$A$24,0))-INDEX($P$18:$P$24,MATCH($A46,$A$18:$A$24,0))*B46/INDEX($G$18:$G$24,MATCH($A46,$A$18:$A$24,0))) | G46: =IF($A46="","",F46-D46) | H46: =IF($A46="","",$B$8-D46) | I46: =IF($A46="","",MAX(G46,H46)) | J46: =IF($A46="","",I46*bar_per_m) | K46: =IF($A46="","",IFERROR("PN"&SMALL(PN_list,COUNTIF(PN_list,"<"&J46)+1),"> max PN")) | L46: =IF($A46="","",G46-INDEX($U$18:$U$24,MATCH($A46,$A$18:$A$24,0))) | M46: add a point: pipe ID, chainage, ground level | N46: =IF($A46="","",IF(G46<0,"NEGATIVE PRESSURE",IF(G46<p_min-0.005,"below minimum","OK")))
D47: =IF($A47="","",C47-cover) | E47: =IF($A47="","",D47+p_min+INDEX($R$18:$R$24,MATCH($A47,$A$18:$A$24,0))+INDEX($P$18:$P$24,MATCH($A47,$A$18:$A$24,0))*B47/INDEX($G$18:$G$24,MATCH($A47,$A$18:$A$24,0))) | F47: =IF($A47="","",INDEX($S$18:$S$24,MATCH($A47,$A$18:$A$24,0))-INDEX($P$18:$P$24,MATCH($A47,$A$18:$A$24,0))*B47/INDEX($G$18:$G$24,MATCH($A47,$A$18:$A$24,0))) | G47: =IF($A47="","",F47-D47) | H47: =IF($A47="","",$B$8-D47) | I47: =IF($A47="","",MAX(G47,H47)) | J47: =IF($A47="","",I47*bar_per_m) | K47: =IF($A47="","",IFERROR("PN"&SMALL(PN_list,COUNTIF(PN_list,"<"&J47)+1),"> max PN")) | L47: =IF($A47="","",G47-INDEX($U$18:$U$24,MATCH($A47,$A$18:$A$24,0))) | M47: add a point: pipe ID, chainage, ground level | N47: =IF($A47="","",IF(G47<0,"NEGATIVE PRESSURE",IF(G47<p_min-0.005,"below minimum","OK")))
A49: E. Bernoulli result
A50: Head needed at zone start H_req | B50: =MAX($H$28:$H$31,$E$41:$E$47,$E$35:$E$37) -> 1738.2284 | C50: m a.s.l. | D50: largest of sections C, C2 (junctions) and D (points)
A51: Set by | B51: =IF(AND(MAX($E$35:$E$37)>MAX($H$28:$H$31),MAX($E$35:$E$37)>MAX($E$41:$E$47)),"junction "&INDEX($A$35:$A$37,MATCH(MAX($E$35:$E$37),$E$35:$E$37,0))&" (minimum pressure)",IF(MAX($E$41:$E$47)>=MAX($H$28:$H$31),"point on "&INDEX($A$41:$A$47,MATCH(MAX($E$41:$E$47),$E$41:$E$47,0)),INDEX($A$28:$A$31,MATCH(MAX($H$28:$H$31),$H$28:$H$31,0)))) -> TUNDUMA_ESR | D51: governing destination, junction or point
A52: Hp = H_req − z1 (suction at MINIMUM level) | B52: =$B$50-$B$5 -> 185.22839 | C52: m | D52: z1 + 0 + 0 + Hp = H_req (p = 0, V ≈ 0 at the sump surface)
A53: TDH design (suction at MINIMUM level) | B53: =$B$52+h_station -> 188.22839 | C53: m | D53: Hp + station losses → size pump and motor with this
A54: TDH low-head (suction at MAXIMUM level) | B54: =$B$50-$B$6+h_station -> 184.22839 | C54: m | D54: pump must also operate here (more flow unless throttled / VFD)
A55: Total pumped flow | B55: =J18 -> 0.25252525 | C55: m³/s | D55: flow in the first pipe
A56: Flow per pump | B56: =$B$55/$B$9 -> 0.12626263 | C56: m³/s
A57: Flow per pump | B57: =$B$56*3600 -> 454.54545 | C57: m³/h | D57: compare ER duty flow
A58: Hydraulic power per pump P_h = ρgQH | B58: =1000*g*$B$56*$B$53/1000 -> 233.14653 | C58: kW
A59: Shaft power per pump P_s = P_h / η_p | B59: =$B$58/$B$11 -> 298.9058 | C59: kW
A60: Motor needed = P_s × margin | B60: =$B$59*motor_margin -> 343.74168 | C60: kW
A61: Standard motor per pump | B61: =IFERROR(SMALL(Motor_list,COUNTIF(Motor_list,"<"&$B$60)+1),"> list") -> 355 | C61: kW | D61: next size up
A62: Electricity per day | B62: =$B$9*$B$59*$B$7/$B$12 -> 13844.058 | C62: kWh/d
A63: Specific energy | B63: =$B$62/I18 -> 0.69220292 | C63: kWh/m³
A64: Electricity cost per year | B64: =$B$62*365*tariff -> 0 | C64: per year | D64: uses Global tariff
A65: TDH design minus ER duty head | B65: =$B$53-$B$14 -> -32.771611 | C65: m | D65: negative = ER pump has spare head (throttle / VFD)
A66: Lowest pressure at any survey point (sheet Profile) | B66: =IF(COUNTIFS(Profile!$A$5:$A$2360,"Z6 Nkangamo-Uhuru",Profile!$L$5:$L$2360,"yes")=0,"no points between tanks",_xlfn.MINIFS(Profile!$H$5:$H$2360,Profile!$A$5:$A$2360,"Z6 Nkangamo-Uhuru",Profile!$L$5:$L$2360,"yes")) -> 6.6727404 | C66: m | D66: if below the minimum, add that point to section D
A68: F. Step by step in words (updates with the numbers)
A69: ="1. Flow: "&TEXT(I18,"#,##0")&" m³/d in "&TEXT($B$7,"0")&" h → Q = "&TEXT(K18,"0.0")&" l/s, V = "&TEXT(M18,"0.00")&" m/s in "&A18&"." -> 1. Flow: 20,000 m³/d in 22 h → Q = 252.5 l/s, V = 0.89 m/s in BPS_RM_1.
A70: ="2. Friction (Hazen-Williams): "&A18&" loses hL = "&TEXT(P18,"0.00")&" m over "&TEXT(G18,"#,##0")&" m ("&TEXT(Q18,"0.00")&" m/km)." -> 2. Friction (Hazen-Williams): BPS_RM_1 loses hL = 30.50 m over 19,581 m (1.56 m/km).
A71: ="3. Point 1 = NKANGAMO_BPS water surface at its MINIMUM level z1 = "&TEXT($B$5,"0.00")&" m (p = 0, V ≈ 0)." -> 3. Point 1 = NKANGAMO_BPS water surface at its MINIMUM level z1 = 1553.00 m (p = 0, V ≈ 0).
A72: ="4. Point 2: the hardest place to reach is "&$B$51&"; it needs the HGL at the zone start to be H_req = "&TEXT($B$50,"0.00")&" m (its level + residual + losses on the way)." -> 4. Point 2: the hardest place to reach is TUNDUMA_ESR; it needs the HGL at the zone start to be H_req = 1738.23 m (its level + residual + losses on the way).
A73: ="5. Bernoulli: z1 + Hp = H_req → Hp = "&TEXT($B$50,"0.00")&" − "&TEXT($B$5,"0.00")&" = "&TEXT($B$52,"0.00")&" m; + station losses "&TEXT(h_station,"0.0")&" m → TDH = "&TEXT($B$53,"0.0")&" m." -> 5. Bernoulli: z1 + Hp = H_req → Hp = 1738.23 − 1553.00 = 185.23 m; + station losses 3.0 m → TDH = 188.2 m.
A74: ="6. With the suction tank full (MAXIMUM level "&TEXT($B$6,"0.00")&" m) TDH falls to "&TEXT($B$54,"0.0")&" m: the pump must work between "&TEXT($B$54,"0.0")&" and "&TEXT($B$53,"0.0")&" m at "&TEXT($B$57,"#,##0")&" m³/h per pump." -> 6. With the suction tank full (MAXIMUM level 1557.00 m) TDH falls to 184.2 m: the pump must work between 184.2 and 188.2 m at 455 m³/h per pump.
A75: ="7. Power: P = ρgQH/η = "&TEXT($B$59,"#,##0")&" kW per pump → motor "&TEXT($B$61,"#,##0")&" kW; ER duty head "&TEXT($B$14,"0")&" m (difference "&TEXT($B$65,"+0.0;-0.0")&" m)." -> 7. Power: P = ρgQH/η = 299 kW per pump → motor 355 kW; ER duty head 221 m (difference -32.8 m).
A76: ="8. Pressure: lowest pressure along the route = "&TEXT($B$66,"0.0")&" m (minimum allowed "&TEXT(p_min,"0")&" m); pipe class from section D and sheet Profile." -> 8. Pressure: lowest pressure along the route = 6.7 m (minimum allowed 2 m); pipe class from section D and sheet Profile.

Sheet Z7 Uhuru-Chapwa
A1: Zone 7 – Uhuru Park GBR to Makambini and Chapwa (gravity)
A2: Uhuru Park GBR feeds Makambini and Chapwa by gravity through J-004N. Chapwa is far below, so it arrives with large excess head (valve + higher PN). Check the points near the GBR: the ground there is close to the tank level.
A4: A. Inputs (levels come from sheet 'Levels')
A5: Start: UHURU_PARK_GBR MINIMUM water level | B5: =Levels!$F$11 -> 1697.6 | C5: m a.s.l. | D5: point 1 of Bernoulli, design case (least energy at the start)
A6: Start: UHURU_PARK_GBR MAXIMUM water level | B6: =Levels!$G$11 -> 1702.3 | C6: m a.s.l. | D6: low-head case for pumps / highest energy for gravity
A7: Operating hours per day | B7: 24 | C7: h/d | D7: ER: pumps 22 h/d; gravity 24 h/d
A8: Static level for pressure class | B8: =$B$6 -> 1702.3 | C8: m a.s.l. | D8: MAXIMUM level of the supplying tank (water at rest)
A10: B. Pipes – flow (continuity) and friction (Hazen-Williams)
A11: Pipe | B11: From | C11: To | D11: Upstream pipe | E11: DN | F11: Internal D (mm) | G11: Length L (m) | H11: C (H-W) | I11: Daily volume (m³/d) | J11: Q (m³/s) | K11: Q (l/s) | L11: Area (m²) | M11: V (m/s) | N11: hf friction (m) | O11: hm minor (m) | P11: hL total (m) | Q11: Gradient (m/km) | R11: Loss before this pipe (m) | S11: HGL start (m) | T11: HGL end (m) | U11: Surge Δh = aV/g (m)
A12: UHURU_J004N | B12: UHURU_PARK_GBR | C12: J-004N | D12: – | E12: 150 | F12: =E12 -> 150 | G12: 1563.5 | H12: =C_default -> 120 | I12: =Demands!$B$16 -> 1244.2 | J12: =I12/($B$7*3600) -> 0.014400463 | K12: =J12*1000 -> 14.400463 | L12: =PI()*(F12/1000)^2/4 -> 0.017671459 | M12: =J12/L12 -> 0.81489951 | N12: =10.67*G12*J12^1.852/(H12^1.852*(F12/1000)^4.8704) -> 9.412326 | O12: =k_minor*N12 -> 0.9412326 | P12: =N12+O12 -> 10.353559 | Q12: =P12/G12*1000 -> 6.6220394 | R12: 0 | S12: =$B$5-R12 -> 1697.6 | T12: =S12-P12 -> 1687.2464 | U12: =wave*M12/g -> 83.068247
A13: MAKAMBINI_BRANCH | B13: J-004N | C13: MAKAMBINI_GSR03 | D13: UHURU_J004N | E13: 100 | F13: =E13 -> 100 | G13: 494 | H13: =C_default -> 120 | I13: =Demands!$B$14 -> 622.1 | J13: =I13/($B$7*3600) -> 0.0072002315 | K13: =J13*1000 -> 7.2002315 | L13: =PI()*(F13/1000)^2/4 -> 0.0078539816 | M13: =J13/L13 -> 0.91676195 | N13: =10.67*G13*J13^1.852/(H13^1.852*(F13/1000)^4.8704) -> 5.9354458 | O13: =k_minor*N13 -> 0.59354458 | P13: =N13+O13 -> 6.5289904 | Q13: =P13/G13*1000 -> 13.21658 | R13: =R12+P12 -> 10.353559 | S13: =$B$5-R13 -> 1687.2464 | T13: =S13-P13 -> 1680.7175 | U13: =wave*M13/g -> 93.451778
A14: CHAPWA_BRANCH | B14: J-004N | C14: CHAPWA_GSR04 | D14: UHURU_J004N | E14: 100 | F14: =E14 -> 100 | G14: 2790.5 | H14: =C_default -> 120 | I14: =Demands!$B$15 -> 622.1 | J14: =I14/($B$7*3600) -> 0.0072002315 | K14: =J14*1000 -> 7.2002315 | L14: =PI()*(F14/1000)^2/4 -> 0.0078539816 | M14: =J14/L14 -> 0.91676195 | N14: =10.67*G14*J14^1.852/(H14^1.852*(F14/1000)^4.8704) -> 33.52806 | O14: =k_minor*N14 -> 3.352806 | P14: =N14+O14 -> 36.880866 | Q14: =P14/G14*1000 -> 13.21658 | R14: =R12+P12 -> 10.353559 | S14: =$B$5-R14 -> 1687.2464 | T14: =S14-P14 -> 1650.3656 | U14: =wave*M14/g -> 93.451778
A16: C. Destinations – Bernoulli to each receiving water surface (levels from 'Levels')
A17: Destination | B17: Ends with pipe | C17: MIN level (m) | D17: MAX level (m) | E17: Arrival level (m) | F17: Residual (m) | G17: z2 = arrival + residual (m) | H17: Head needed at zone start = z2 + losses (m) | I17: Arriving HGL, design case (m) | J17: Excess head, design case (m) | K17: Excess head, start at MAX level (m) | L17: Comment
A18: MAKAMBINI_GSR03 | B18: MAKAMBINI_BRANCH | C18: =Levels!$F$15 -> 1655.7 | D18: =Levels!$G$15 -> 1658.7 | E18: =Levels!$L$15 -> 1658.7 | F18: =h_res -> 1 | G18: =E18+F18 -> 1659.7 | H18: =G18+R13+P13 -> 1676.5825 | I18: =T13 -> 1680.7175 | J18: =I18-G18 -> 21.017451 | K18: =J18+($B$6-$B$5) -> 25.717451 | L18: =IF(J18<-0.005,"NOT REACHED – more head needed",IF(K18>fcv_limit,"fit flow control valve / PRV (burns "&TEXT(J18,"0.0")&"–"&TEXT(K18,"0.0")&" m)","OK")) -> fit flow control valve / PRV (burns 21.0–25.7 m)
A19: CHAPWA_GSR04 | B19: CHAPWA_BRANCH | C19: =Levels!$F$16 -> 1521.4 | D19: =Levels!$G$16 -> 1524.4 | E19: =Levels!$L$16 -> 1524.4 | F19: =h_res -> 1 | G19: =E19+F19 -> 1525.4 | H19: =G19+R14+P14 -> 1572.6344 | I19: =T14 -> 1650.3656 | J19: =I19-G19 -> 124.96558 | K19: =J19+($B$6-$B$5) -> 129.66558 | L19: =IF(J19<-0.005,"NOT REACHED – more head needed",IF(K19>fcv_limit,"fit flow control valve / PRV (burns "&TEXT(J19,"0.0")&"–"&TEXT(K19,"0.0")&" m)","OK")) -> fit flow control valve / PRV (burns 125.0–129.7 m)
A21: C2. Junctions – minimum pressure at offtakes (ER Table 7)
A22: Junction | B22: End of pipe | C22: Ground level (m) | D22: Minimum pressure (m) | E22: Head needed at zone start = ground + p_min + losses (m) | F22: HGL at junction (m) | G22: Pressure (m) | H22: Status
A23: J-004N | B23: UHURU_J004N | C23: 1630.08 | D23: =p_min_j -> 5 | E23: =C23+D23+R12+P12 -> 1645.4336 | F23: =T12 -> 1687.2464 | G23: =F23-C23 -> 57.166441 | H23: =IF(G23<D23-0.005,"below minimum","OK") -> OK
A25: D. Critical points along the pipes – pressure check (add your own rows)
A26: Pipe | B26: Chainage in pipe x (m) | C26: Ground level (m) | D26: Pipe crown (m) | E26: Head needed at zone start (m) | F26: HGL at point (m) | G26: Pressure (m) | H26: Static (m) | I26: Working (m) | J26: Working (bar) | K26: PN required | L26: Transient min = p − Δh (m) | M26: Note | N26: Status
A27: UHURU_J004N | B27: 179.3 | C27: 1699.52 | D27: =IF($A27="","",C27-cover) -> 1698.32 | E27: =IF($A27="","",D27+p_min+INDEX($R$12:$R$14,MATCH($A27,$A$12:$A$14,0))+INDEX($P$12:$P$14,MATCH($A27,$A$12:$A$14,0))*B27/INDEX($G$12:$G$14,MATCH($A27,$A$12:$A$14,0))) -> 1701.5073 | F27: =IF($A27="","",INDEX($S$12:$S$14,MATCH($A27,$A$12:$A$14,0))-INDEX($P$12:$P$14,MATCH($A27,$A$12:$A$14,0))*B27/INDEX($G$12:$G$14,MATCH($A27,$A$12:$A$14,0))) -> 1696.4127 | G27: =IF($A27="","",F27-D27) -> -1.9073317 | H27: =IF($A27="","",$B$8-D27) -> 3.98 | I27: =IF($A27="","",MAX(G27,H27)) -> 3.98 | J27: =IF($A27="","",I27*bar_per_m) -> 0.390438 | K27: =IF($A27="","",IFERROR("PN"&SMALL(PN_list,COUNTIF(PN_list,"<"&J27)+1),"> max PN")) -> PN10 | L27: =IF($A27="","",G27-INDEX($U$12:$U$14,MATCH($A27,$A$12:$A$14,0))) -> -84.975579 | M27: critical high point | N27: =IF($A27="","",IF(G27<0,"NEGATIVE PRESSURE",IF(G27<p_min-0.005,"below minimum","OK"))) -> NEGATIVE PRESSURE
A28: UHURU_J004N | B28: 1514.5 | C28: 1633.93 | D28: =IF($A28="","",C28-cover) -> 1632.73 | E28: =IF($A28="","",D28+p_min+INDEX($R$12:$R$14,MATCH($A28,$A$12:$A$14,0))+INDEX($P$12:$P$14,MATCH($A28,$A$12:$A$14,0))*B28/INDEX($G$12:$G$14,MATCH($A28,$A$12:$A$14,0))) -> 1644.7591 | F28: =IF($A28="","",INDEX($S$12:$S$14,MATCH($A28,$A$12:$A$14,0))-INDEX($P$12:$P$14,MATCH($A28,$A$12:$A$14,0))*B28/INDEX($G$12:$G$14,MATCH($A28,$A$12:$A$14,0))) -> 1687.5709 | G28: =IF($A28="","",F28-D28) -> 54.840921 | H28: =IF($A28="","",$B$8-D28) -> 69.57 | I28: =IF($A28="","",MAX(G28,H28)) -> 69.57 | J28: =IF($A28="","",I28*bar_per_m) -> 6.824817 | K28: =IF($A28="","",IFERROR("PN"&SMALL(PN_list,COUNTIF(PN_list,"<"&J28)+1),"> max PN")) -> PN10 | L28: =IF($A28="","",G28-INDEX($U$12:$U$14,MATCH($A28,$A$12:$A$14,0))) -> -28.227326 | M28: lowest point (highest static pressure) | N28: =IF($A28="","",IF(G28<0,"NEGATIVE PRESSURE",IF(G28<p_min-0.005,"below minimum","OK"))) -> OK
A29: CHAPWA_BRANCH | B29: 0 | C29: 1630.08 | D29: =IF($A29="","",C29-cover) -> 1628.88 | E29: =IF($A29="","",D29+p_min+INDEX($R$12:$R$14,MATCH($A29,$A$12:$A$14,0))+INDEX($P$12:$P$14,MATCH($A29,$A$12:$A$14,0))*B29/INDEX($G$12:$G$14,MATCH($A29,$A$12:$A$14,0))) -> 1641.2336 | F29: =IF($A29="","",INDEX($S$12:$S$14,MATCH($A29,$A$12:$A$14,0))-INDEX($P$12:$P$14,MATCH($A29,$A$12:$A$14,0))*B29/INDEX($G$12:$G$14,MATCH($A29,$A$12:$A$14,0))) -> 1687.2464 | G29: =IF($A29="","",F29-D29) -> 58.366441 | H29: =IF($A29="","",$B$8-D29) -> 73.42 | I29: =IF($A29="","",MAX(G29,H29)) -> 73.42 | J29: =IF($A29="","",I29*bar_per_m) -> 7.202502 | K29: =IF($A29="","",IFERROR("PN"&SMALL(PN_list,COUNTIF(PN_list,"<"&J29)+1),"> max PN")) -> PN10 | L29: =IF($A29="","",G29-INDEX($U$12:$U$14,MATCH($A29,$A$12:$A$14,0))) -> -35.085337 | M29: governing point (model) | N29: =IF($A29="","",IF(G29<0,"NEGATIVE PRESSURE",IF(G29<p_min-0.005,"below minimum","OK"))) -> OK
A30: CHAPWA_BRANCH | B30: 50 | C30: 1628.93 | D30: =IF($A30="","",C30-cover) -> 1627.73 | E30: =IF($A30="","",D30+p_min+INDEX($R$12:$R$14,MATCH($A30,$A$12:$A$14,0))+INDEX($P$12:$P$14,MATCH($A30,$A$12:$A$14,0))*B30/INDEX($G$12:$G$14,MATCH($A30,$A$12:$A$14,0))) -> 1640.7444 | F30: =IF($A30="","",INDEX($S$12:$S$14,MATCH($A30,$A$12:$A$14,0))-INDEX($P$12:$P$14,MATCH($A30,$A$12:$A$14,0))*B30/INDEX($G$12:$G$14,MATCH($A30,$A$12:$A$14,0))) -> 1686.5856 | G30: =IF($A30="","",F30-D30) -> 58.855612 | H30: =IF($A30="","",$B$8-D30) -> 74.57 | I30: =IF($A30="","",MAX(G30,H30)) -> 74.57 | J30: =IF($A30="","",I30*bar_per_m) -> 7.315317 | K30: =IF($A30="","",IFERROR("PN"&SMALL(PN_list,COUNTIF(PN_list,"<"&J30)+1),"> max PN")) -> PN10 | L30: =IF($A30="","",G30-INDEX($U$12:$U$14,MATCH($A30,$A$12:$A$14,0))) -> -34.596166 | M30: critical high point | N30: =IF($A30="","",IF(G30<0,"NEGATIVE PRESSURE",IF(G30<p_min-0.005,"below minimum","OK"))) -> OK
A31: CHAPWA_BRANCH | B31: 2781.8 | C31: 1523.93 | D31: =IF($A31="","",C31-cover) -> 1522.73 | E31: =IF($A31="","",D31+p_min+INDEX($R$12:$R$14,MATCH($A31,$A$12:$A$14,0))+INDEX($P$12:$P$14,MATCH($A31,$A$12:$A$14,0))*B31/INDEX($G$12:$G$14,MATCH($A31,$A$12:$A$14,0))) -> 1571.8494 | F31: =IF($A31="","",INDEX($S$12:$S$14,MATCH($A31,$A$12:$A$14,0))-INDEX($P$12:$P$14,MATCH($A31,$A$12:$A$14,0))*B31/INDEX($G$12:$G$14,MATCH($A31,$A$12:$A$14,0))) -> 1650.4806 | G31: =IF($A31="","",F31-D31) -> 127.75056 | H31: =IF($A31="","",$B$8-D31) -> 179.57 | I31: =IF($A31="","",MAX(G31,H31)) -> 179.57 | J31: =IF($A31="","",I31*bar_per_m) -> 17.615817 | K31: =IF($A31="","",IFERROR("PN"&SMALL(PN_list,COUNTIF(PN_list,"<"&J31)+1),"> max PN")) -> PN25 | L31: =IF($A31="","",G31-INDEX($U$12:$U$14,MATCH($A31,$A$12:$A$14,0))) -> 34.298782 | M31: lowest point (highest static pressure) | N31: =IF($A31="","",IF(G31<0,"NEGATIVE PRESSURE",IF(G31<p_min-0.005,"below minimum","OK"))) -> OK
D32: =IF($A32="","",C32-cover) | E32: =IF($A32="","",D32+p_min+INDEX($R$12:$R$14,MATCH($A32,$A$12:$A$14,0))+INDEX($P$12:$P$14,MATCH($A32,$A$12:$A$14,0))*B32/INDEX($G$12:$G$14,MATCH($A32,$A$12:$A$14,0))) | F32: =IF($A32="","",INDEX($S$12:$S$14,MATCH($A32,$A$12:$A$14,0))-INDEX($P$12:$P$14,MATCH($A32,$A$12:$A$14,0))*B32/INDEX($G$12:$G$14,MATCH($A32,$A$12:$A$14,0))) | G32: =IF($A32="","",F32-D32) | H32: =IF($A32="","",$B$8-D32) | I32: =IF($A32="","",MAX(G32,H32)) | J32: =IF($A32="","",I32*bar_per_m) | K32: =IF($A32="","",IFERROR("PN"&SMALL(PN_list,COUNTIF(PN_list,"<"&J32)+1),"> max PN")) | L32: =IF($A32="","",G32-INDEX($U$12:$U$14,MATCH($A32,$A$12:$A$14,0))) | M32: add a point: pipe ID, chainage, ground level | N32: =IF($A32="","",IF(G32<0,"NEGATIVE PRESSURE",IF(G32<p_min-0.005,"below minimum","OK")))
D33: =IF($A33="","",C33-cover) | E33: =IF($A33="","",D33+p_min+INDEX($R$12:$R$14,MATCH($A33,$A$12:$A$14,0))+INDEX($P$12:$P$14,MATCH($A33,$A$12:$A$14,0))*B33/INDEX($G$12:$G$14,MATCH($A33,$A$12:$A$14,0))) | F33: =IF($A33="","",INDEX($S$12:$S$14,MATCH($A33,$A$12:$A$14,0))-INDEX($P$12:$P$14,MATCH($A33,$A$12:$A$14,0))*B33/INDEX($G$12:$G$14,MATCH($A33,$A$12:$A$14,0))) | G33: =IF($A33="","",F33-D33) | H33: =IF($A33="","",$B$8-D33) | I33: =IF($A33="","",MAX(G33,H33)) | J33: =IF($A33="","",I33*bar_per_m) | K33: =IF($A33="","",IFERROR("PN"&SMALL(PN_list,COUNTIF(PN_list,"<"&J33)+1),"> max PN")) | L33: =IF($A33="","",G33-INDEX($U$12:$U$14,MATCH($A33,$A$12:$A$14,0))) | M33: add a point: pipe ID, chainage, ground level | N33: =IF($A33="","",IF(G33<0,"NEGATIVE PRESSURE",IF(G33<p_min-0.005,"below minimum","OK")))
D34: =IF($A34="","",C34-cover) | E34: =IF($A34="","",D34+p_min+INDEX($R$12:$R$14,MATCH($A34,$A$12:$A$14,0))+INDEX($P$12:$P$14,MATCH($A34,$A$12:$A$14,0))*B34/INDEX($G$12:$G$14,MATCH($A34,$A$12:$A$14,0))) | F34: =IF($A34="","",INDEX($S$12:$S$14,MATCH($A34,$A$12:$A$14,0))-INDEX($P$12:$P$14,MATCH($A34,$A$12:$A$14,0))*B34/INDEX($G$12:$G$14,MATCH($A34,$A$12:$A$14,0))) | G34: =IF($A34="","",F34-D34) | H34: =IF($A34="","",$B$8-D34) | I34: =IF($A34="","",MAX(G34,H34)) | J34: =IF($A34="","",I34*bar_per_m) | K34: =IF($A34="","",IFERROR("PN"&SMALL(PN_list,COUNTIF(PN_list,"<"&J34)+1),"> max PN")) | L34: =IF($A34="","",G34-INDEX($U$12:$U$14,MATCH($A34,$A$12:$A$14,0))) | M34: add a point: pipe ID, chainage, ground level | N34: =IF($A34="","",IF(G34<0,"NEGATIVE PRESSURE",IF(G34<p_min-0.005,"below minimum","OK")))
A36: E. Bernoulli result
A37: Head needed at zone start H_req | B37: =MAX($H$18:$H$19,$E$27:$E$34,$E$23:$E$23) -> 1701.5073 | C37: m a.s.l. | D37: largest of sections C, C2 (junctions) and D (points)
A38: Set by | B38: =IF(AND(MAX($E$23:$E$23)>MAX($H$18:$H$19),MAX($E$23:$E$23)>MAX($E$27:$E$34)),"junction "&INDEX($A$23:$A$23,MATCH(MAX($E$23:$E$23),$E$23:$E$23,0))&" (minimum pressure)",IF(MAX($E$27:$E$34)>=MAX($H$18:$H$19),"point on "&INDEX($A$27:$A$34,MATCH(MAX($E$27:$E$34),$E$27:$E$34,0)),INDEX($A$18:$A$19,MATCH(MAX($H$18:$H$19),$H$18:$H$19,0)))) -> point on UHURU_J004N | D38: governing destination, junction or point
A39: Surplus = z1 − H_req (start at MINIMUM level) | B39: =$B$5-$B$37 -> -3.9073317 | C39: m | D39: design case: must be ≥ 0
A40: Surplus with start at MAXIMUM level | B40: =$B$6-$B$37 -> 0.79266833 | C40: m | D40: largest head the valve must burn
A41: Status | B41: =IF($B$39<-0.005,"SHORT OF HEAD at minimum level – bigger pipe, lower outlet, higher tank or pump","OK – valve burns "&TEXT($B$39,"0.0")&" to "&TEXT($B$40,"0.0")&" m") -> SHORT OF HEAD at minimum level – bigger pipe, lower outlet, higher tank or pump
A42: Lowest pressure at any survey point (sheet Profile) | B42: =IF(COUNTIFS(Profile!$A$5:$A$2360,"Z7 Uhuru-Chapwa",Profile!$L$5:$L$2360,"yes")=0,"no points between tanks",_xlfn.MINIFS(Profile!$H$5:$H$2360,Profile!$A$5:$A$2360,"Z7 Uhuru-Chapwa",Profile!$L$5:$L$2360,"yes")) -> -1.9075966 | C42: m | D42: if below the minimum, add that point to section D
A44: F. Step by step in words (updates with the numbers)
A45: ="1. Flow: "&TEXT(I12,"#,##0")&" m³/d in "&TEXT($B$7,"0")&" h → Q = "&TEXT(K12,"0.0")&" l/s, V = "&TEXT(M12,"0.00")&" m/s in "&A12&"." -> 1. Flow: 1,244 m³/d in 24 h → Q = 14.4 l/s, V = 0.81 m/s in UHURU_J004N.
A46: ="2. Friction (Hazen-Williams): "&A12&" loses hL = "&TEXT(P12,"0.00")&" m over "&TEXT(G12,"#,##0")&" m ("&TEXT(Q12,"0.00")&" m/km)." -> 2. Friction (Hazen-Williams): UHURU_J004N loses hL = 10.35 m over 1,564 m (6.62 m/km).
A47: ="3. Point 1 = UHURU_PARK_GBR water surface at its MINIMUM level z1 = "&TEXT($B$5,"0.00")&" m (p = 0, V ≈ 0)." -> 3. Point 1 = UHURU_PARK_GBR water surface at its MINIMUM level z1 = 1697.60 m (p = 0, V ≈ 0).
A48: ="4. Point 2: the hardest place to reach is "&$B$38&"; it needs the HGL at the zone start to be H_req = "&TEXT($B$37,"0.00")&" m (its level + residual + losses on the way)." -> 4. Point 2: the hardest place to reach is point on UHURU_J004N; it needs the HGL at the zone start to be H_req = 1701.51 m (its level + residual + losses on the way).
A49: ="5. Bernoulli without pump: z1 = H_req + surplus → surplus = "&TEXT($B$5,"0.00")&" − "&TEXT($B$37,"0.00")&" = "&TEXT($B$39,"0.00")&" m." -> 5. Bernoulli without pump: z1 = H_req + surplus → surplus = 1697.60 − 1701.51 = -3.91 m.
A50: ="6. With the supplying tank full (MAXIMUM level "&TEXT($B$6,"0.00")&" m) the surplus is "&TEXT($B$40,"0.00")&" m. "&IF($B$39<-0.005,"Negative at minimum level: the zone cannot deliver – change pipe or levels.","A flow control valve burns this so the flow stays at design.") -> 6. With the supplying tank full (MAXIMUM level 1702.30 m) the surplus is 0.79 m. Negative at minimum level: the zone cannot deliver – change pipe or levels.
A51: ="8. Pressure: lowest pressure along the route = "&TEXT($B$42,"0.0")&" m (minimum allowed "&TEXT(p_min,"0")&" m); pipe class from section D and sheet Profile." -> 8. Pressure: lowest pressure along the route = -1.9 m (minimum allowed 2 m); pipe class from section D and sheet Profile.

Sheet Storage
A1: Storage – balancing for pump rest hours
A2: V_bal = inflow × (1 − hours/24); emergency = inflow × hours/24. Volumes and levels from 'Levels'.
A4: Tank | B4: MIN level (m) | C4: MAX level (m) | D4: Daily inflow (m³/d) | E4: Inflow hours (h/d) | F4: Balancing volume (m³) | G4: Emergency hours | H4: Emergency volume (m³) | I4: Required (m³) | J4: Capacity (m³) | K4: Storage (h of flow) | L4: Status
A5: IKANA_GBR | B5: =Levels!$F$9 -> 1663.3 | C5: =Levels!$G$9 -> 1668 | D5: ='Z4 WTP-Ikana'!I18 -> 20000 | E5: ='Z4 WTP-Ikana'!I18/('Z4 WTP-Ikana'!J18*3600) -> 22 | F5: =D5*(1-E5/24) -> 1666.6667 | G5: 0 | H5: =D5*G5/24 -> 0 | I5: =F5+H5 -> 1666.6667 | J5: =IF(Levels!$I$9="","",Levels!$I$9) -> 3000 | K5: =IF(J5="","",J5/(D5/24)) -> 3.6 | L5: =IF(J5="","enter capacity",IF(J5>=I5,"OK","TOO SMALL")) -> OK
A6: NKANGAMO_BPS | B6: =Levels!$F$10 -> 1553 | C6: =Levels!$G$10 -> 1557 | D6: ='Z5 Ikana-Nkangamo'!I12 -> 20000 | E6: ='Z6 Nkangamo-Uhuru'!$B$7 -> 22 | F6: =D6*(1-E6/24) -> 1666.6667 | G6: 0 | H6: =D6*G6/24 -> 0 | I6: =F6+H6 -> 1666.6667 | J6: =IF(Levels!$I$10="","",Levels!$I$10) -> 2000 | K6: =IF(J6="","",J6/(D6/24)) -> 2.4 | L6: =IF(J6="","enter capacity",IF(J6>=I6,"OK","TOO SMALL")) -> OK
A7: UHURU_PARK_GBR | B7: =Levels!$F$11 -> 1697.6 | C7: =Levels!$G$11 -> 1702.3 | D7: ='Z6 Nkangamo-Uhuru'!I21 -> 17459.82 | E7: ='Z6 Nkangamo-Uhuru'!I21/('Z6 Nkangamo-Uhuru'!J21*3600) -> 22 | F7: =D7*(1-E7/24) -> 1454.985 | G7: 0 | H7: =D7*G7/24 -> 0 | I7: =F7+H7 -> 1454.985 | J7: =IF(Levels!$I$11="","",Levels!$I$11) -> 5000 | K7: =IF(J7="","",J7/(D7/24)) -> 6.8729231 | L7: =IF(J7="","enter capacity",IF(J7>=I7,"OK","TOO SMALL")) -> OK
A8: TUNDUMA_ESR | B8: =Levels!$F$12 -> 1703.5 | C8: =Levels!$G$12 -> 1706.5 | D8: ='Z6 Nkangamo-Uhuru'!I22 -> 371.52 | E8: ='Z6 Nkangamo-Uhuru'!I22/('Z6 Nkangamo-Uhuru'!J22*3600) -> 22 | F8: =D8*(1-E8/24) -> 30.96 | G8: 0 | H8: =D8*G8/24 -> 0 | I8: =F8+H8 -> 30.96 | J8: =IF(Levels!$I$12="","",Levels!$I$12) -> 120 | K8: =IF(J8="","",J8/(D8/24)) -> 7.751938 | L8: =IF(J8="","enter capacity",IF(J8>=I8,"OK","TOO SMALL")) -> OK
A9: UHURU_GSR01 | B9: =Levels!$F$13 -> 1698.4 | C9: =Levels!$G$13 -> 1701.4 | D9: ='Z6 Nkangamo-Uhuru'!I23 -> 1546.56 | E9: ='Z6 Nkangamo-Uhuru'!I23/('Z6 Nkangamo-Uhuru'!J23*3600) -> 22 | F9: =D9*(1-E9/24) -> 128.88 | G9: 0 | H9: =D9*G9/24 -> 0 | I9: =F9+H9 -> 128.88 | J9: =IF(Levels!$I$13="","",Levels!$I$13) -> 500 | K9: =IF(J9="","",J9/(D9/24)) -> 7.7591558 | L9: =IF(J9="","enter capacity",IF(J9>=I9,"OK","TOO SMALL")) -> OK
A10: IPITO_GSR02 | B10: =Levels!$F$14 -> 1681.2 | C10: =Levels!$G$14 -> 1684.2 | D10: ='Z6 Nkangamo-Uhuru'!I24 -> 622.1 | E10: ='Z6 Nkangamo-Uhuru'!I24/('Z6 Nkangamo-Uhuru'!J24*3600) -> 22 | F10: =D10*(1-E10/24) -> 51.841667 | G10: 0 | H10: =D10*G10/24 -> 0 | I10: =F10+H10 -> 51.841667 | J10: =IF(Levels!$I$14="","",Levels!$I$14) -> 200 | K10: =IF(J10="","",J10/(D10/24)) -> 7.7158013 | L10: =IF(J10="","enter capacity",IF(J10>=I10,"OK","TOO SMALL")) -> OK
A11: MAKAMBINI_GSR03 | B11: =Levels!$F$15 -> 1655.7 | C11: =Levels!$G$15 -> 1658.7 | D11: ='Z7 Uhuru-Chapwa'!I13 -> 622.1 | E11: ='Z7 Uhuru-Chapwa'!I13/('Z7 Uhuru-Chapwa'!J13*3600) -> 24 | F11: =D11*(1-E11/24) -> 0 | G11: 0 | H11: =D11*G11/24 -> 0 | I11: =F11+H11 -> 0 | J11: =IF(Levels!$I$15="","",Levels!$I$15) -> 200 | K11: =IF(J11="","",J11/(D11/24)) -> 7.7158013 | L11: =IF(J11="","enter capacity",IF(J11>=I11,"OK","TOO SMALL")) -> OK
A12: CHAPWA_GSR04 | B12: =Levels!$F$16 -> 1521.4 | C12: =Levels!$G$16 -> 1524.4 | D12: ='Z7 Uhuru-Chapwa'!I14 -> 622.1 | E12: ='Z7 Uhuru-Chapwa'!I14/('Z7 Uhuru-Chapwa'!J14*3600) -> 24 | F12: =D12*(1-E12/24) -> 0 | G12: 0 | H12: =D12*G12/24 -> 0 | I12: =F12+H12 -> 0 | J12: =IF(Levels!$I$16="","",Levels!$I$16) -> 200 | K12: =IF(J12="","",J12/(D12/24)) -> 7.7158013 | L12: =IF(J12="","enter capacity",IF(J12>=I12,"OK","TOO SMALL")) -> OK

Sheet Profile
A1: Pressure at every surveyed point
A2: HGL from the zone sheets; ground from the topographic survey. Column L = 'no' for pipe ends at a water surface (not checked).
A4: Zone | B4: Pipe | C4: Chainage in pipe (m) | D4: Ground (m) | E4: Pipe crown (m) | F4: HGL (m) | G4: Static (m) | H4: Pressure (m) | I4: Working (m) | J4: PN required | K4: Status | L4: Check?
A5: Z1 River-Intake | B5: ABSTRACTION | C5: 0 | D5: 1360.2 | E5: =D5-cover -> 1359 | F5: ='Z1 River-Intake'!S12-'Z1 River-Intake'!P12*C5/'Z1 River-Intake'!G12 -> 1361 | G5: ='Z1 River-Intake'!$B$8-E5 -> 5.5 | H5: =F5-E5 -> 2 | I5: =MAX(H5,G5) -> 5.5 | J5: =IFERROR("PN"&SMALL(PN_list,COUNTIF(PN_list,"<"&I5*bar_per_m)+1),"> max PN") -> PN10 | K5: =IF(L5="no","end at tank",IF(H5<0,"NEGATIVE",IF(H5<p_min-0.005,"low","OK"))) -> end at tank | L5: no
A6: Z1 River-Intake | B6: ABSTRACTION | C6: 100 | D6: 1360 | E6: =D6-cover -> 1358.8 | F6: ='Z1 River-Intake'!S12-'Z1 River-Intake'!P12*C6/'Z1 River-Intake'!G12 -> 1360.8218 | G6: ='Z1 River-Intake'!$B$8-E6 -> 5.7 | H6: =F6-E6 -> 2.0218263 | I6: =MAX(H6,G6) -> 5.7 | J6: =IFERROR("PN"&SMALL(PN_list,COUNTIF(PN_list,"<"&I6*bar_per_m)+1),"> max PN") -> PN10 | K6: =IF(L6="no","end at tank",IF(H6<0,"NEGATIVE",IF(H6<p_min-0.005,"low","OK"))) -> end at tank | L6: no
A7: Z2 Intake-Grit | B7: LL_DELIVERY | C7: 0 | D7: 1365.94 | E7: =D7-cover -> 1364.74 | F7: ='Z2 Intake-Grit'!S18-'Z2 Intake-Grit'!P18*C7/'Z2 Intake-Grit'!G18 -> 1369.0535 | G7: ='Z2 Intake-Grit'!$B$8-E7 -> 3.26 | H7: =F7-E7 -> 4.3134521 | I7: =MAX(H7,G7) -> 4.3134521 | J7: =IFERROR("PN"&SMALL(PN_list,COUNTIF(PN_list,"<"&I7*bar_per_m)+1),"> max PN") -> PN10 | K7: =IF(L7="no","end at tank",IF(H7<0,"NEGATIVE",IF(H7<p_min-0.005,"low","OK"))) -> end at tank | L7: no
A8: Z2 Intake-Grit | B8: LL_DELIVERY | C8: 30 | D8: 1365.94 | E8: =D8-cover -> 1364.74 | F8: ='Z2 Intake-Grit'!S18-'Z2 Intake-Grit'!P18*C8/'Z2 Intake-Grit'!G18 -> 1369 | G8: ='Z2 Intake-Grit'!$B$8-E8 -> 3.26 | H8: =F8-E8 -> 4.26 | I8: =MAX(H8,G8) -> 4.26 | J8: =IFERROR("PN"&SMALL(PN_list,COUNTIF(PN_list,"<"&I8*bar_per_m)+1),"> max PN") -> PN10 | K8: =IF(L8="no","end at tank",IF(H8<0,"NEGATIVE",IF(H8<p_min-0.005,"low","OK"))) -> end at tank | L8: no
A9: Z3 Grit-WTP | B9: RAW_MAIN | C9: 0 | D9: 1365.94 | E9: =D9-cover -> 1364.74 | F9: ='Z3 Grit-WTP'!S18-'Z3 Grit-WTP'!P18*C9/'Z3 Grit-WTP'!G18 -> 1380.9216 | G9: ='Z3 Grit-WTP'!$B$8-E9 -> 13.26 | H9: =F9-E9 -> 16.181604 | I9: =MAX(H9,G9) -> 16.181604 | J9: =IFERROR("PN"&SMALL(PN_list,COUNTIF(PN_list,"<"&I9*bar_per_m)+1),"> max PN") -> PN10 | K9: =IF(L9="no","end at tank",IF(H9<0,"NEGATIVE",IF(H9<p_min-0.005,"low","OK"))) -> end at tank | L9: no
A10: Z3 Grit-WTP | B10: RAW_MAIN | C10: 129.83 | D10: 1365.87 | E10: =D10-cover -> 1364.67 | F10: ='Z3 Grit-WTP'!S18-'Z3 Grit-WTP'!P18*C10/'Z3 Grit-WTP'!G18 -> 1380.6903 | G10: ='Z3 Grit-WTP'!$B$8-E10 -> 13.33 | H10: =F10-E10 -> 16.020281 | I10: =MAX(H10,G10) -> 16.020281 | J10: =IFERROR("PN"&SMALL(PN_list,COUNTIF(PN_list,"<"&I10*bar_per_m)+1),"> max PN") -> PN10 | K10: =IF(L10="no","end at tank",IF(H10<0,"NEGATIVE",IF(H10<p_min-0.005,"low","OK"))) -> OK | L10: yes
A11: Z3 Grit-WTP | B11: RAW_MAIN | C11: 179.83 | D11: 1366.02 | E11: =D11-cover -> 1364.82 | F11: ='Z3 Grit-WTP'!S18-'Z3 Grit-WTP'!P18*C11/'Z3 Grit-WTP'!G18 -> 1380.6012 | G11: ='Z3 Grit-WTP'!$B$8-E11 -> 13.18 | H11: =F11-E11 -> 15.781194 | I11: =MAX(H11,G11) -> 15.781194 | J11: =IFERROR("PN"&SMALL(PN_list,COUNTIF(PN_list,"<"&I11*bar_per_m)+1),"> max PN") -> PN10 | K11: =IF(L11="no","end at tank",IF(H11<0,"NEGATIVE",IF(H11<p_min-0.005,"low","OK"))) -> OK | L11: yes
A12: Z3 Grit-WTP | B12: RAW_MAIN | C12: 229.83 | D12: 1366.08 | E12: =D12-cover -> 1364.88 | F12: ='Z3 Grit-WTP'!S18-'Z3 Grit-WTP'!P18*C12/'Z3 Grit-WTP'!G18 -> 1380.5121 | G12: ='Z3 Grit-WTP'!$B$8-E12 -> 13.12 | H12: =F12-E12 -> 15.632107 | I12: =MAX(H12,G12) -> 15.632107 | J12: =IFERROR("PN"&SMALL(PN_list,COUNTIF(PN_list,"<"&I12*bar_per_m)+1),"> max PN") -> PN10 | K12: =IF(L12="no","end at tank",IF(H12<0,"NEGATIVE",IF(H12<p_min-0.005,"low","OK"))) -> OK | L12: yes
A13: Z3 Grit-WTP | B13: RAW_MAIN | C13: 279.83 | D13: 1366.21 | E13: =D13-cover -> 1365.01 | F13: ='Z3 Grit-WTP'!S18-'Z3 Grit-WTP'!P18*C13/'Z3 Grit-WTP'!G18 -> 1380.423 | G13: ='Z3 Grit-WTP'!$B$8-E13 -> 12.99 | H13: =F13-E13 -> 15.41302 | I13: =MAX(H13,G13) -> 15.41302 | J13: =IFERROR("PN"&SMALL(PN_list,COUNTIF(PN_list,"<"&I13*bar_per_m)+1),"> max PN") -> PN10 | K13: =IF(L13="no","end at tank",IF(H13<0,"NEGATIVE",IF(H13<p_min-0.005,"low","OK"))) -> OK | L13: yes
A14: Z3 Grit-WTP | B14: RAW_MAIN | C14: 329.83 | D14: 1366.33 | E14: =D14-cover -> 1365.13 | F14: ='Z3 Grit-WTP'!S18-'Z3 Grit-WTP'!P18*C14/'Z3 Grit-WTP'!G18 -> 1380.3339 | G14: ='Z3 Grit-WTP'!$B$8-E14 -> 12.87 | H14: =F14-E14 -> 15.203933 | I14: =MAX(H14,G14) -> 15.203933 | J14: =IFERROR("PN"&SMALL(PN_list,COUNTIF(PN_list,"<"&I14*bar_per_m)+1),"> max PN") -> PN10 | K14: =IF(L14="no","end at tank",IF(H14<0,"NEGATIVE",IF(H14<p_min-0.005,"low","OK"))) -> OK | L14: yes
A15: Z3 Grit-WTP | B15: RAW_MAIN | C15: 379.84 | D15: 1367.37 | E15: =D15-cover -> 1366.17 | F15: ='Z3 Grit-WTP'!S18-'Z3 Grit-WTP'!P18*C15/'Z3 Grit-WTP'!G18 -> 1380.2448 | G15: ='Z3 Grit-WTP'!$B$8-E15 -> 11.83 | H15: =F15-E15 -> 14.074829 | I15: =MAX(H15,G15) -> 14.074829 | J15: =IFERROR("PN"&SMALL(PN_list,COUNTIF(PN_list,"<"&I15*bar_per_m)+1),"> max PN") -> PN10 | K15: =IF(L15="no","end at tank",IF(H15<0,"NEGATIVE",IF(H15<p_min-0.005,"low","OK"))) -> OK | L15: yes
A16: Z3 Grit-WTP | B16: RAW_MAIN | C16: 429.85 | D16: 1368.42 | E16: =D16-cover -> 1367.22 | F16: ='Z3 Grit-WTP'!S18-'Z3 Grit-WTP'!P18*C16/'Z3 Grit-WTP'!G18 -> 1380.1557 | G16: ='Z3 Grit-WTP'!$B$8-E16 -> 10.78 | H16: =F16-E16 -> 12.935724 | I16: =MAX(H16,G16) -> 12.935724 | J16: =IFERROR("PN"&SMALL(PN_list,COUNTIF(PN_list,"<"&I16*bar_per_m)+1),"> max PN") -> PN10 | K16: =IF(L16="no","end at tank",IF(H16<0,"NEGATIVE",IF(H16<p_min-0.005,"low","OK"))) -> OK | L16: yes
A17: Z3 Grit-WTP | B17: RAW_MAIN | C17: 479.88 | D17: 1370.17 | E17: =D17-cover -> 1368.97 | F17: ='Z3 Grit-WTP'!S18-'Z3 Grit-WTP'!P18*C17/'Z3 Grit-WTP'!G18 -> 1380.0666 | G17: ='Z3 Grit-WTP'!$B$8-E17 -> 9.03 | H17: =F17-E17 -> 11.096584 | I17: =MAX(H17,G17) -> 11.096584 | J17: =IFERROR("PN"&SMALL(PN_list,COUNTIF(PN_list,"<"&I17*bar_per_m)+1),"> max PN") -> PN10 | K17: =IF(L17="no","end at tank",IF(H17<0,"NEGATIVE",IF(H17<p_min-0.005,"low","OK"))) -> OK | L17: yes
A18: Z3 Grit-WTP | B18: RAW_MAIN | C18: 529.89 | D18: 1371.2 | E18: =D18-cover -> 1370 | F18: ='Z3 Grit-WTP'!S18-'Z3 Grit-WTP'!P18*C18/'Z3 Grit-WTP'!G18 -> 1379.9775 | G18: ='Z3 Grit-WTP'!$B$8-E18 -> 8 | H18: =F18-E18 -> 9.9774789 | I18: =MAX(H18,G18) -> 9.9774789 | J18: =IFERROR("PN"&SMALL(PN_list,COUNTIF(PN_list,"<"&I18*bar_per_m)+1),"> max PN") -> PN10 | K18: =IF(L18="no","end at tank",IF(H18<0,"NEGATIVE",IF(H18<p_min-0.005,"low","OK"))) -> OK | L18: yes
A19: Z3 Grit-WTP | B19: RAW_MAIN | C19: 578.45 | D19: 1372.47 | E19: =D19-cover -> 1371.27 | F19: ='Z3 Grit-WTP'!S18-'Z3 Grit-WTP'!P18*C19/'Z3 Grit-WTP'!G18 -> 1379.891 | G19: ='Z3 Grit-WTP'!$B$8-E19 -> 6.73 | H19: =F19-E19 -> 8.6209578 | I19: =MAX(H19,G19) -> 8.6209578 | J19: =IFERROR("PN"&SMALL(PN_list,COUNTIF(PN_list,"<"&I19*bar_per_m)+1),"> max PN") -> PN10 | K19: =IF(L19="no","end at tank",IF(H19<0,"NEGATIVE",IF(H19<p_min-0.005,"low","OK"))) -> OK | L19: yes
A20: Z3 Grit-WTP | B20: RAW_MAIN | C20: 628.45 | D20: 1371.99 | E20: =D20-cover -> 1370.79 | F20: ='Z3 Grit-WTP'!S18-'Z3 Grit-WTP'!P18*C20/'Z3 Grit-WTP'!G18 -> 1379.8019 | G20: ='Z3 Grit-WTP'!$B$8-E20 -> 7.21 | H20: =F20-E20 -> 9.0118709 | I20: =MAX(H20,G20) -> 9.0118709 | J20: =IFERROR("PN"&SMALL(PN_list,COUNTIF(PN_list,"<"&I20*bar_per_m)+1),"> max PN") -> PN10 | K20: =IF(L20="no","end at tank",IF(H20<0,"NEGATIVE",IF(H20<p_min-0.005,"low","OK"))) -> OK | L20: yes
A21: Z3 Grit-WTP | B21: RAW_MAIN | C21: 678.45 | D21: 1372.35 | E21: =D21-cover -> 1371.15 | F21: ='Z3 Grit-WTP'!S18-'Z3 Grit-WTP'!P18*C21/'Z3 Grit-WTP'!G18 -> 1379.7128 | G21: ='Z3 Grit-WTP'!$B$8-E21 -> 6.85 | H21: =F21-E21 -> 8.562784 | I21: =MAX(H21,G21) -> 8.562784 | J21: =IFERROR("PN"&SMALL(PN_list,COUNTIF(PN_list,"<"&I21*bar_per_m)+1),"> max PN") -> PN10 | K21: =IF(L21="no","end at tank",IF(H21<0,"NEGATIVE",IF(H21<p_min-0.005,"low","OK"))) -> OK | L21: yes
A22: Z3 Grit-WTP | B22: RAW_MAIN | C22: 728.45 | D22: 1372.37 | E22: =D22-cover -> 1371.17 | F22: ='Z3 Grit-WTP'!S18-'Z3 Grit-WTP'!P18*C22/'Z3 Grit-WTP'!G18 -> 1379.6237 | G22: ='Z3 Grit-WTP'!$B$8-E22 -> 6.83 | H22: =F22-E22 -> 8.4536972 | I22: =MAX(H22,G22) -> 8.4536972 | J22: =IFERROR("PN"&SMALL(PN_list,COUNTIF(PN_list,"<"&I22*bar_per_m)+1),"> max PN") -> PN10 | K22: =IF(L22="no","end at tank",IF(H22<0,"NEGATIVE",IF(H22<p_min-0.005,"low","OK"))) -> OK | L22: yes
A23: Z3 Grit-WTP | B23: RAW_MAIN | C23: 778.45 | D23: 1372.43 | E23: =D23-cover -> 1371.23 | F23: ='Z3 Grit-WTP'!S18-'Z3 Grit-WTP'!P18*C23/'Z3 Grit-WTP'!G18 -> 1379.5346 | G23: ='Z3 Grit-WTP'!$B$8-E23 -> 6.77 | H23: =F23-E23 -> 8.3046103 | I23: =MAX(H23,G23) -> 8.3046103 | J23: =IFERROR("PN"&SMALL(PN_list,COUNTIF(PN_list,"<"&I23*bar_per_m)+1),"> max PN") -> PN10 | K23: =IF(L23="no","end at tank",IF(H23<0,"NEGATIVE",IF(H23<p_min-0.005,"low","OK"))) -> OK | L23: yes
A24: Z3 Grit-WTP | B24: RAW_MAIN | C24: 828.45 | D24: 1372.18 | E24: =D24-cover -> 1370.98 | F24: ='Z3 Grit-WTP'!S18-'Z3 Grit-WTP'!P18*C24/'Z3 Grit-WTP'!G18 -> 1379.4455 | G24: ='Z3 Grit-WTP'!$B$8-E24 -> 7.02 | H24: =F24-E24 -> 8.4655234 | I24: =MAX(H24,G24) -> 8.4655234 | J24: =IFERROR("PN"&SMALL(PN_list,COUNTIF(PN_list,"<"&I24*bar_per_m)+1),"> max PN") -> PN10 | K24: =IF(L24="no","end at tank",IF(H24<0,"NEGATIVE",IF(H24<p_min-0.005,"low","OK"))) -> OK | L24: yes
A25: Z3 Grit-WTP | B25: RAW_MAIN | C25: 878.45 | D25: 1372.1 | E25: =D25-cover -> 1370.9 | F25: ='Z3 Grit-WTP'!S18-'Z3 Grit-WTP'!P18*C25/'Z3 Grit-WTP'!G18 -> 1379.3564 | G25: ='Z3 Grit-WTP'!$B$8-E25 -> 7.1 | H25: =F25-E25 -> 8.4564366 | I25: =MAX(H25,G25) -> 8.4564366 | J25: =IFERROR("PN"&SMALL(PN_list,COUNTIF(PN_list,"<"&I25*bar_per_m)+1),"> max PN") -> PN10 | K25: =IF(L25="no","end at tank",IF(H25<0,"NEGATIVE",IF(H25<p_min-0.005,"low","OK"))) -> OK | L25: yes
A26: Z3 Grit-WTP | B26: RAW_MAIN | C26: 928.46 | D26: 1371.84 | E26: =D26-cover -> 1370.64 | F26: ='Z3 Grit-WTP'!S18-'Z3 Grit-WTP'!P18*C26/'Z3 Grit-WTP'!G18 -> 1379.2673 | G26: ='Z3 Grit-WTP'!$B$8-E26 -> 7.36 | H26: =F26-E26 -> 8.6273319 | I26: =MAX(H26,G26) -> 8.6273319 | J26: =IFERROR("PN"&SMALL(PN_list,COUNTIF(PN_list,"<"&I26*bar_per_m)+1),"> max PN") -> PN10 | K26: =IF(L26="no","end at tank",IF(H26<0,"NEGATIVE",IF(H26<p_min-0.005,"low","OK"))) -> OK | L26: yes
A27: Z3 Grit-WTP | B27: RAW_MAIN | C27: 978.46 | D27: 1371.59 | E27: =D27-cover -> 1370.39 | F27: ='Z3 Grit-WTP'!S18-'Z3 Grit-WTP'!P18*C27/'Z3 Grit-WTP'!G18 -> 1379.1782 | G27: ='Z3 Grit-WTP'!$B$8-E27 -> 7.61 | H27: =F27-E27 -> 8.788245 | I27: =MAX(H27,G27) -> 8.788245 | J27: =IFERROR("PN"&SMALL(PN_list,COUNTIF(PN_list,"<"&I27*bar_per_m)+1),"> max PN") -> PN10 | K27: =IF(L27="no","end at tank",IF(H27<0,"NEGATIVE",IF(H27<p_min-0.005,"low","OK"))) -> OK | L27: yes
A28: Z3 Grit-WTP | B28: RAW_MAIN | C28: 1028.46 | D28: 1371.93 | E28: =D28-cover -> 1370.73 | F28: ='Z3 Grit-WTP'!S18-'Z3 Grit-WTP'!P18*C28/'Z3 Grit-WTP'!G18 -> 1379.0892 | G28: ='Z3 Grit-WTP'!$B$8-E28 -> 7.27 | H28: =F28-E28 -> 8.3591581 | I28: =MAX(H28,G28) -> 8.3591581 | J28: =IFERROR("PN"&SMALL(PN_list,COUNTIF(PN_list,"<"&I28*bar_per_m)+1),"> max PN") -> PN10 | K28: =IF(L28="no","end at tank",IF(H28<0,"NEGATIVE",IF(H28<p_min-0.005,"low","OK"))) -> OK | L28: yes
A29: Z3 Grit-WTP | B29: RAW_MAIN | C29: 1078.46 | D29: 1372.2 | E29: =D29-cover -> 1371 | F29: ='Z3 Grit-WTP'!S18-'Z3 Grit-WTP'!P18*C29/'Z3 Grit-WTP'!G18 -> 1379.0001 | G29: ='Z3 Grit-WTP'!$B$8-E29 -> 7 | H29: =F29-E29 -> 8.0000713 | I29: =MAX(H29,G29) -> 8.0000713 | J29: =IFERROR("PN"&SMALL(PN_list,COUNTIF(PN_list,"<"&I29*bar_per_m)+1),"> max PN") -> PN10 | K29: =IF(L29="no","end at tank",IF(H29<0,"NEGATIVE",IF(H29<p_min-0.005,"low","OK"))) -> end at tank | L29: no
A30: Z4 WTP-Ikana | B30: WTP_IKANA_RM | C30: 0 | D30: 1372.2 | E30: =D30-cover -> 1371 | F30: ='Z4 WTP-Ikana'!S18-'Z4 WTP-Ikana'!P18*C30/'Z4 WTP-Ikana'!G18 -> 1699.6324 | G30: ='Z4 WTP-Ikana'!$B$8-E30 -> 297 | H30: =F30-E30 -> 328.63242 | I30: =MAX(H30,G30) -> 328.63242 | J30: =IFERROR("PN"&SMALL(PN_list,COUNTIF(PN_list,"<"&I30*bar_per_m)+1),"> max PN") -> PN40 | K30: =IF(L30="no","end at tank",IF(H30<0,"NEGATIVE",IF(H30<p_min-0.005,"low","OK"))) -> end at tank | L30: no
A31: Z4 WTP-Ikana | B31: WTP_IKANA_RM | C31: 50.01 | D31: 1373.21 | E31: =D31-cover -> 1372.01 | F31: ='Z4 WTP-Ikana'!S18-'Z4 WTP-Ikana'!P18*C31/'Z4 WTP-Ikana'!G18 -> 1699.5545 | G31: ='Z4 WTP-Ikana'!$B$8-E31 -> 295.99 | H31: =F31-E31 -> 327.54452 | I31: =MAX(H31,G31) -> 327.54452 | J31: =IFERROR("PN"&SMALL(PN_list,COUNTIF(PN_list,"<"&I31*bar_per_m)+1),"> max PN") -> PN40 | K31: =IF(L31="no","end at tank",IF(H31<0,"NEGATIVE",IF(H31<p_min-0.005,"low","OK"))) -> OK | L31: yes
A32: Z4 WTP-Ikana | B32: WTP_IKANA_RM | C32: 100.02 | D32: 1374.1 | E32: =D32-cover -> 1372.9 | F32: ='Z4 WTP-Ikana'!S18-'Z4 WTP-Ikana'!P18*C32/'Z4 WTP-Ikana'!G18 -> 1699.4766 | G32: ='Z4 WTP-Ikana'!$B$8-E32 -> 295.1 | H32: =F32-E32 -> 326.57662 | I32: =MAX(H32,G32) -> 326.57662 | J32: =IFERROR("PN"&SMALL(PN_list,COUNTIF(PN_list,"<"&I32*bar_per_m)+1),"> max PN") -> PN40 | K32: =IF(L32="no","end at tank",IF(H32<0,"NEGATIVE",IF(H32<p_min-0.005,"low","OK"))) -> OK | L32: yes
A33: Z4 WTP-Ikana | B33: WTP_IKANA_RM | C33: 150.03 | D33: 1375.25 | E33: =D33-cover -> 1374.05 | F33: ='Z4 WTP-Ikana'!S18-'Z4 WTP-Ikana'!P18*C33/'Z4 WTP-Ikana'!G18 -> 1699.3987 | G33: ='Z4 WTP-Ikana'!$B$8-E33 -> 293.95 | H33: =F33-E33 -> 325.34872 | I33: =MAX(H33,G33) -> 325.34872 | J33: =IFERROR("PN"&SMALL(PN_list,COUNTIF(PN_list,"<"&I33*bar_per_m)+1),"> max PN") -> PN40 | K33: =IF(L33="no","end at tank",IF(H33<0,"NEGATIVE",IF(H33<p_min-0.005,"low","OK"))) -> OK | L33: yes
A34: Z4 WTP-Ikana | B34: WTP_IKANA_RM | C34: 200.04 | D34: 1376.32 | E34: =D34-cover -> 1375.12 | F34: ='Z4 WTP-Ikana'!S18-'Z4 WTP-Ikana'!P18*C34/'Z4 WTP-Ikana'!G18 -> 1699.3208 | G34: ='Z4 WTP-Ikana'!$B$8-E34 -> 292.88 | H34: =F34-E34 -> 324.20082 | I34: =MAX(H34,G34) -> 324.20082 | J34: =IFERROR("PN"&SMALL(PN_list,COUNTIF(PN_list,"<"&I34*bar_per_m)+1),"> max PN") -> PN40 | K34: =IF(L34="no","end at tank",IF(H34<0,"NEGATIVE",IF(H34<p_min-0.005,"low","OK"))) -> OK | L34: yes
A35: Z4 WTP-Ikana | B35: WTP_IKANA_RM | C35: 250.05 | D35: 1377.16 | E35: =D35-cover -> 1375.96 | F35: ='Z4 WTP-Ikana'!S18-'Z4 WTP-Ikana'!P18*C35/'Z4 WTP-Ikana'!G18 -> 1699.2429 | G35: ='Z4 WTP-Ikana'!$B$8-E35 -> 292.04 | H35: =F35-E35 -> 323.28293 | I35: =MAX(H35,G35) -> 323.28293 | J35: =IFERROR("PN"&SMALL(PN_list,COUNTIF(PN_list,"<"&I35*bar_per_m)+1),"> max PN") -> PN40 | K35: =IF(L35="no","end at tank",IF(H35<0,"NEGATIVE",IF(H35<p_min-0.005,"low","OK"))) -> OK | L35: yes
A36: Z4 WTP-Ikana | B36: WTP_IKANA_RM | C36: 300.08 | D36: 1378.79 | E36: =D36-cover -> 1377.59 | F36: ='Z4 WTP-Ikana'!S18-'Z4 WTP-Ikana'!P18*C36/'Z4 WTP-Ikana'!G18 -> 1699.165 | G36: ='Z4 WTP-Ikana'!$B$8-E36 -> 290.41 | H36: =F36-E36 -> 321.575 | I36: =MAX(H36,G36) -> 321.575 | J36: =IFERROR("PN"&SMALL(PN_list,COUNTIF(PN_list,"<"&I36*bar_per_m)+1),"> max PN") -> PN40 | K36: =IF(L36="no","end at tank",IF(H36<0,"NEGATIVE",IF(H36<p_min-0.005,"low","OK"))) -> OK | L36: yes
A37: Z4 WTP-Ikana | B37: WTP_IKANA_RM | C37: 350.09 | D37: 1379.95 | E37: =D37-cover -> 1378.75 | F37: ='Z4 WTP-Ikana'!S18-'Z4 WTP-Ikana'!P18*C37/'Z4 WTP-Ikana'!G18 -> 1699.0871 | G37: ='Z4 WTP-Ikana'!$B$8-E37 -> 289.25 | H37: =F37-E37 -> 320.3371 | I37: =MAX(H37,G37) -> 320.3371 | J37: =IFERROR("PN"&SMALL(PN_list,COUNTIF(PN_list,"<"&I37*bar_per_m)+1),"> max PN") -> PN40 | K37: =IF(L37="no","end at tank",IF(H37<0,"NEGATIVE",IF(H37<p_min-0.005,"low","OK"))) -> OK | L37: yes
A38: Z4 WTP-Ikana | B38: WTP_IKANA_RM | C38: 400.12 | D38: 1381.63 | E38: =D38-cover -> 1380.43 | F38: ='Z4 WTP-Ikana'!S18-'Z4 WTP-Ikana'!P18*C38/'Z4 WTP-Ikana'!G18 -> 1699.0092 | G38: ='Z4 WTP-Ikana'!$B$8-E38 -> 287.57 | H38: =F38-E38 -> 318.57917 | I38: =MAX(H38,G38) -> 318.57917 | J38: =IFERROR("PN"&SMALL(PN_list,COUNTIF(PN_list,"<"&I38*bar_per_m)+1),"> max PN") -> PN40 | K38: =IF(L38="no","end at tank",IF(H38<0,"NEGATIVE",IF(H38<p_min-0.005,"low","OK"))) -> OK | L38: yes
A39: Z4 WTP-Ikana | B39: WTP_IKANA_RM | C39: 450.15 | D39: 1383.37 | E39: =D39-cover -> 1382.17 | F39: ='Z4 WTP-Ikana'!S18-'Z4 WTP-Ikana'!P18*C39/'Z4 WTP-Ikana'!G18 -> 1698.9312 | G39: ='Z4 WTP-Ikana'!$B$8-E39 -> 285.83 | H39: =F39-E39 -> 316.76124 | I39: =MAX(H39,G39) -> 316.76124 | J39: =IFERROR("PN"&SMALL(PN_list,COUNTIF(PN_list,"<"&I39*bar_per_m)+1),"> max PN") -> PN40 | K39: =IF(L39="no","end at tank",IF(H39<0,"NEGATIVE",IF(H39<p_min-0.005,"low","OK"))) -> OK | L39: yes
A40: Z4 WTP-Ikana | B40: WTP_IKANA_RM | C40: 500.16 | D40: 1384.37 | E40: =D40-cover -> 1383.17 | F40: ='Z4 WTP-Ikana'!S18-'Z4 WTP-Ikana'!P18*C40/'Z4 WTP-Ikana'!G18 -> 1698.8533 | G40: ='Z4 WTP-Ikana'!$B$8-E40 -> 284.83 | H40: =F40-E40 -> 315.68334 | I40: =MAX(H40,G40) -> 315.68334 | J40: =IFERROR("PN"&SMALL(PN_list,COUNTIF(PN_list,"<"&I40*bar_per_m)+1),"> max PN") -> PN40 | K40: =IF(L40="no","end at tank",IF(H40<0,"NEGATIVE",IF(H40<p_min-0.005,"low","OK"))) -> OK | L40: yes
A41: Z4 WTP-Ikana | B41: WTP_IKANA_RM | C41: 550.19 | D41: 1386.2 | E41: =D41-cover -> 1385 | F41: ='Z4 WTP-Ikana'!S18-'Z4 WTP-Ikana'!P18*C41/'Z4 WTP-Ikana'!G18 -> 1698.7754 | G41: ='Z4 WTP-Ikana'!$B$8-E41 -> 283 | H41: =F41-E41 -> 313.77541 | I41: =MAX(H41,G41) -> 313.77541 | J41: =IFERROR("PN"&SMALL(PN_list,COUNTIF(PN_list,"<"&I41*bar_per_m)+1),"> max PN") -> PN40 | K41: =IF(L41="no","end at tank",IF(H41<0,"NEGATIVE",IF(H41<p_min-0.005,"low","OK"))) -> OK | L41: yes
A42: Z4 WTP-Ikana | B42: WTP_IKANA_RM | C42: 600.21 | D42: 1387.64 | E42: =D42-cover -> 1386.44 | F42: ='Z4 WTP-Ikana'!S18-'Z4 WTP-Ikana'!P18*C42/'Z4 WTP-Ikana'!G18 -> 1698.6975 | G42: ='Z4 WTP-Ikana'!$B$8-E42 -> 281.56 | H42: =F42-E42 -> 312.25749 | I42: =MAX(H42,G42) -> 312.25749 | J42: =IFERROR("PN"&SMALL(PN_list,COUNTIF(PN_list,"<"&I42*bar_per_m)+1),"> max PN") -> PN40 | K42: =IF(L42="no","end at tank",IF(H42<0,"NEGATIVE",IF(H42<p_min-0.005,"low","OK"))) -> OK | L42: yes
A43: Z4 WTP-Ikana | B43: WTP_IKANA_RM | C43: 650.22 | D43: 1388.72 | E43: =D43-cover -> 1387.52 | F43: ='Z4 WTP-Ikana'!S18-'Z4 WTP-Ikana'!P18*C43/'Z4 WTP-Ikana'!G18 -> 1698.6196 | G43: ='Z4 WTP-Ikana'!$B$8-E43 -> 280.48 | H43: =F43-E43 -> 311.09959 | I43: =MAX(H43,G43) -> 311.09959 | J43: =IFERROR("PN"&SMALL(PN_list,COUNTIF(PN_list,"<"&I43*bar_per_m)+1),"> max PN") -> PN40 | K43: =IF(L43="no","end at tank",IF(H43<0,"NEGATIVE",IF(H43<p_min-0.005,"low","OK"))) -> OK | L43: yes
A44: Z4 WTP-Ikana | B44: WTP_IKANA_RM | C44: 700.24 | D44: 1389.8 | E44: =D44-cover -> 1388.6 | F44: ='Z4 WTP-Ikana'!S18-'Z4 WTP-Ikana'!P18*C44/'Z4 WTP-Ikana'!G18 -> 1698.5417 | G44: ='Z4 WTP-Ikana'!$B$8-E44 -> 279.4 | H44: =F44-E44 -> 309.94168 | I44: =MAX(H44,G44) -> 309.94168 | J44: =IFERROR("PN"&SMALL(PN_list,COUNTIF(PN_list,"<"&I44*bar_per_m)+1),"> max PN") -> PN40 | K44: =IF(L44="no","end at tank",IF(H44<0,"NEGATIVE",IF(H44<p_min-0.005,"low","OK"))) -> OK | L44: yes
A45: Z4 WTP-Ikana | B45: WTP_IKANA_RM | C45: 750.24 | D45: 1390.58 | E45: =D45-cover -> 1389.38 | F45: ='Z4 WTP-Ikana'!S18-'Z4 WTP-Ikana'!P18*C45/'Z4 WTP-Ikana'!G18 -> 1698.4638 | G45: ='Z4 WTP-Ikana'!$B$8-E45 -> 278.62 | H45: =F45-E45 -> 309.0838 | I45: =MAX(H45,G45) -> 309.0838 | J45: =IFERROR("PN"&SMALL(PN_list,COUNTIF(PN_list,"<"&I45*bar_per_m)+1),"> max PN") -> PN40 | K45: =IF(L45="no","end at tank",IF(H45<0,"NEGATIVE",IF(H45<p_min-0.005,"low","OK"))) -> OK | L45: yes
A46: Z4 WTP-Ikana | B46: WTP_IKANA_RM | C46: 800.24 | D46: 1390.97 | E46: =D46-cover -> 1389.77 | F46: ='Z4 WTP-Ikana'!S18-'Z4 WTP-Ikana'!P18*C46/'Z4 WTP-Ikana'!G18 -> 1698.3859 | G46: ='Z4 WTP-Ikana'!$B$8-E46 -> 278.23 | H46: =F46-E46 -> 308.61591 | I46: =MAX(H46,G46) -> 308.61591 | J46: =IFERROR("PN"&SMALL(PN_list,COUNTIF(PN_list,"<"&I46*bar_per_m)+1),"> max PN") -> PN40 | K46: =IF(L46="no","end at tank",IF(H46<0,"NEGATIVE",IF(H46<p_min-0.005,"low","OK"))) -> OK | L46: yes
A47: Z4 WTP-Ikana | B47: WTP_IKANA_RM | C47: 850.24 | D47: 1391.04 | E47: =D47-cover -> 1389.84 | F47: ='Z4 WTP-Ikana'!S18-'Z4 WTP-Ikana'!P18*C47/'Z4 WTP-Ikana'!G18 -> 1698.308 | G47: ='Z4 WTP-Ikana'!$B$8-E47 -> 278.16 | H47: =F47-E47 -> 308.46803 | I47: =MAX(H47,G47) -> 308.46803 | J47: =IFERROR("PN"&SMALL(PN_list,COUNTIF(PN_list,"<"&I47*bar_per_m)+1),"> max PN") -> PN40 | K47: =IF(L47="no","end at tank",IF(H47<0,"NEGATIVE",IF(H47<p_min-0.005,"low","OK"))) -> OK | L47: yes
A48: Z4 WTP-Ikana | B48: WTP_IKANA_RM | C48: 900.24 | D48: 1390.7 | E48: =D48-cover -> 1389.5 | F48: ='Z4 WTP-Ikana'!S18-'Z4 WTP-Ikana'!P18*C48/'Z4 WTP-Ikana'!G18 -> 1698.2301 | G48: ='Z4 WTP-Ikana'!$B$8-E48 -> 278.5 | H48: =F48-E48 -> 308.73015 | I48: =MAX(H48,G48) -> 308.73015 | J48: =IFERROR("PN"&SMALL(PN_list,COUNTIF(PN_list,"<"&I48*bar_per_m)+1),"> max PN") -> PN40 | K48: =IF(L48="no","end at tank",IF(H48<0,"NEGATIVE",IF(H48<p_min-0.005,"low","OK"))) -> OK | L48: yes
A49: Z4 WTP-Ikana | B49: WTP_IKANA_RM | C49: 950.25 | D49: 1390.44 | E49: =D49-cover -> 1389.24 | F49: ='Z4 WTP-Ikana'!S18-'Z4 WTP-Ikana'!P18*C49/'Z4 WTP-Ikana'!G18 -> 1698.1522 | G49: ='Z4 WTP-Ikana'!$B$8-E49 -> 278.76 | H49: =F49-E49 -> 308.91225 | I49: =MAX(H49,G49) -> 308.91225 | J49: =IFERROR("PN"&SMALL(PN_list,COUNTIF(PN_list,"<"&I49*bar_per_m)+1),"> max PN") -> PN40 | K49: =IF(L49="no","end at tank",IF(H49<0,"NEGATIVE",IF(H49<p_min-0.005,"low","OK"))) -> OK | L49: yes
A50: Z4 WTP-Ikana | B50: WTP_IKANA_RM | C50: 1000.25 | D50: 1389.94 | E50: =D50-cover -> 1388.74 | F50: ='Z4 WTP-Ikana'!S18-'Z4 WTP-Ikana'!P18*C50/'Z4 WTP-Ikana'!G18 -> 1698.0744 | G50: ='Z4 WTP-Ikana'!$B$8-E50 -> 279.26 | H50: =F50-E50 -> 309.33437 | I50: =MAX(H50,G50) -> 309.33437 | J50: =IFERROR("PN"&SMALL(PN_list,COUNTIF(PN_list,"<"&I50*bar_per_m)+1),"> max PN") -> PN40 | K50: =IF(L50="no","end at tank",IF(H50<0,"NEGATIVE",IF(H50<p_min-0.005,"low","OK"))) -> OK | L50: yes
A51: Z4 WTP-Ikana | B51: WTP_IKANA_RM | C51: 1050.25 | D51: 1389.31 | E51: =D51-cover -> 1388.11 | F51: ='Z4 WTP-Ikana'!S18-'Z4 WTP-Ikana'!P18*C51/'Z4 WTP-Ikana'!G18 -> 1697.9965 | G51: ='Z4 WTP-Ikana'!$B$8-E51 -> 279.89 | H51: =F51-E51 -> 309.88648 | I51: =MAX(H51,G51) -> 309.88648 | J51: =IFERROR("PN"&SMALL(PN_list,COUNTIF(PN_list,"<"&I51*bar_per_m)+1),"> max PN") -> PN40 | K51: =IF(L51="no","end at tank",IF(H51<0,"NEGATIVE",IF(H51<p_min-0.005,"low","OK"))) -> OK | L51: yes
A52: Z4 WTP-Ikana | B52: WTP_IKANA_RM | C52: 1100.26 | D52: 1388.49 | E52: =D52-cover -> 1387.29 | F52: ='Z4 WTP-Ikana'!S18-'Z4 WTP-Ikana'!P18*C52/'Z4 WTP-Ikana'!G18 -> 1697.9186 | G52: ='Z4 WTP-Ikana'!$B$8-E52 -> 280.71 | H52: =F52-E52 -> 310.62858 | I52: =MAX(H52,G52) -> 310.62858 | J52: =IFERROR("PN"&SMALL(PN_list,COUNTIF(PN_list,"<"&I52*bar_per_m)+1),"> max PN") -> PN40 | K52: =IF(L52="no","end at tank",IF(H52<0,"NEGATIVE",IF(H52<p_min-0.005,"low","OK"))) -> OK | L52: yes
A53: Z4 WTP-Ikana | B53: WTP_IKANA_RM | C53: 1150.26 | D53: 1388.22 | E53: =D53-cover -> 1387.02 | F53: ='Z4 WTP-Ikana'!S18-'Z4 WTP-Ikana'!P18*C53/'Z4 WTP-Ikana'!G18 -> 1697.8407 | G53: ='Z4 WTP-Ikana'!$B$8-E53 -> 280.98 | H53: =F53-E53 -> 310.8207 | I53: =MAX(H53,G53) -> 310.8207 | J53: =IFERROR("PN"&SMALL(PN_list,COUNTIF(PN_list,"<"&I53*bar_per_m)+1),"> max PN") -> PN40 | K53: =IF(L53="no","end at tank",IF(H53<0,"NEGATIVE",IF(H53<p_min-0.005,"low","OK"))) -> OK | L53: yes
A54: Z4 WTP-Ikana | B54: WTP_IKANA_RM | C54: 1200.26 | D54: 1387.99 | E54: =D54-cover -> 1386.79 | F54: ='Z4 WTP-Ikana'!S18-'Z4 WTP-Ikana'!P18*C54/'Z4 WTP-Ikana'!G18 -> 1697.7628 | G54: ='Z4 WTP-Ikana'!$B$8-E54 -> 281.21 | H54: =F54-E54 -> 310.97282 | I54: =MAX(H54,G54) -> 310.97282 | J54: =IFERROR("PN"&SMALL(PN_list,COUNTIF(PN_list,"<"&I54*bar_per_m)+1),"> max PN") -> PN40 | K54: =IF(L54="no","end at tank",IF(H54<0,"NEGATIVE",IF(H54<p_min-0.005,"low","OK"))) -> OK | L54: yes
A55: Z4 WTP-Ikana | B55: WTP_IKANA_RM | C55: 1250.26 | D55: 1388.63 | E55: =D55-cover -> 1387.43 | F55: ='Z4 WTP-Ikana'!S18-'Z4 WTP-Ikana'!P18*C55/'Z4 WTP-Ikana'!G18 -> 1697.6849 | G55: ='Z4 WTP-Ikana'!$B$8-E55 -> 280.57 | H55: =F55-E55 -> 310.25493 | I55: =MAX(H55,G55) -> 310.25493 | J55: =IFERROR("PN"&SMALL(PN_list,COUNTIF(PN_list,"<"&I55*bar_per_m)+1),"> max PN") -> PN40 | K55: =IF(L55="no","end at tank",IF(H55<0,"NEGATIVE",IF(H55<p_min-0.005,"low","OK"))) -> OK | L55: yes
A56: Z4 WTP-Ikana | B56: WTP_IKANA_RM | C56: 1300.28 | D56: 1389.69 | E56: =D56-cover -> 1388.49 | F56: ='Z4 WTP-Ikana'!S18-'Z4 WTP-Ikana'!P18*C56/'Z4 WTP-Ikana'!G18 -> 1697.607 | G56: ='Z4 WTP-Ikana'!$B$8-E56 -> 279.51 | H56: =F56-E56 -> 309.11702 | I56: =MAX(H56,G56) -> 309.11702 | J56: =IFERROR("PN"&SMALL(PN_list,COUNTIF(PN_list,"<"&I56*bar_per_m)+1),"> max PN") -> PN40 | K56: =IF(L56="no","end at tank",IF(H56<0,"NEGATIVE",IF(H56<p_min-0.005,"low","OK"))) -> OK | L56: yes
A57: Z4 WTP-Ikana | B57: WTP_IKANA_RM | C57: 1350.28 | D57: 1390.51 | E57: =D57-cover -> 1389.31 | F57: ='Z4 WTP-Ikana'!S18-'Z4 WTP-Ikana'!P18*C57/'Z4 WTP-Ikana'!G18 -> 1697.5291 | G57: ='Z4 WTP-Ikana'!$B$8-E57 -> 278.69 | H57: =F57-E57 -> 308.21914 | I57: =MAX(H57,G57) -> 308.21914 | J57: =IFERROR("PN"&SMALL(PN_list,COUNTIF(PN_list,"<"&I57*bar_per_m)+1),"> max PN") -> PN40 | K57: =IF(L57="no","end at tank",IF(H57<0,"NEGATIVE",IF(H57<p_min-0.005,"low","OK"))) -> OK | L57: yes
A58: Z4 WTP-Ikana | B58: WTP_IKANA_RM | C58: 1400.3 | D58: 1391.89 | E58: =D58-cover -> 1390.69 | F58: ='Z4 WTP-Ikana'!S18-'Z4 WTP-Ikana'!P18*C58/'Z4 WTP-Ikana'!G18 -> 1697.4512 | G58: ='Z4 WTP-Ikana'!$B$8-E58 -> 277.31 | H58: =F58-E58 -> 306.76122 | I58: =MAX(H58,G58) -> 306.76122 | J58: =IFERROR("PN"&SMALL(PN_list,COUNTIF(PN_list,"<"&I58*bar_per_m)+1),"> max PN") -> PN40 | K58: =IF(L58="no","end at tank",IF(H58<0,"NEGATIVE",IF(H58<p_min-0.005,"low","OK"))) -> OK | L58: yes
A59: Z4 WTP-Ikana | B59: WTP_IKANA_RM | C59: 1450.32 | D59: 1393.24 | E59: =D59-cover -> 1392.04 | F59: ='Z4 WTP-Ikana'!S18-'Z4 WTP-Ikana'!P18*C59/'Z4 WTP-Ikana'!G18 -> 1697.3733 | G59: ='Z4 WTP-Ikana'!$B$8-E59 -> 275.96 | H59: =F59-E59 -> 305.33331 | I59: =MAX(H59,G59) -> 305.33331 | J59: =IFERROR("PN"&SMALL(PN_list,COUNTIF(PN_list,"<"&I59*bar_per_m)+1),"> max PN") -> PN30 | K59: =IF(L59="no","end at tank",IF(H59<0,"NEGATIVE",IF(H59<p_min-0.005,"low","OK"))) -> OK | L59: yes
A60: Z4 WTP-Ikana | B60: WTP_IKANA_RM | C60: 1500.35 | D60: 1394.99 | E60: =D60-cover -> 1393.79 | F60: ='Z4 WTP-Ikana'!S18-'Z4 WTP-Ikana'!P18*C60/'Z4 WTP-Ikana'!G18 -> 1697.2954 | G60: ='Z4 WTP-Ikana'!$B$8-E60 -> 274.21 | H60: =F60-E60 -> 303.50538 | I60: =MAX(H60,G60) -> 303.50538 | J60: =IFERROR("PN"&SMALL(PN_list,COUNTIF(PN_list,"<"&I60*bar_per_m)+1),"> max PN") -> PN30 | K60: =IF(L60="no","end at tank",IF(H60<0,"NEGATIVE",IF(H60<p_min-0.005,"low","OK"))) -> OK | L60: yes
A61: Z4 WTP-Ikana | B61: WTP_IKANA_RM | C61: 1550.39 | D61: 1396.88 | E61: =D61-cover -> 1395.68 | F61: ='Z4 WTP-Ikana'!S18-'Z4 WTP-Ikana'!P18*C61/'Z4 WTP-Ikana'!G18 -> 1697.2174 | G61: ='Z4 WTP-Ikana'!$B$8-E61 -> 272.32 | H61: =F61-E61 -> 301.53743 | I61: =MAX(H61,G61) -> 301.53743 | J61: =IFERROR("PN"&SMALL(PN_list,COUNTIF(PN_list,"<"&I61*bar_per_m)+1),"> max PN") -> PN30 | K61: =IF(L61="no","end at tank",IF(H61<0,"NEGATIVE",IF(H61<p_min-0.005,"low","OK"))) -> OK | L61: yes
A62: Z4 WTP-Ikana | B62: WTP_IKANA_RM | C62: 1600.4 | D62: 1398.17 | E62: =D62-cover -> 1396.97 | F62: ='Z4 WTP-Ikana'!S18-'Z4 WTP-Ikana'!P18*C62/'Z4 WTP-Ikana'!G18 -> 1697.1395 | G62: ='Z4 WTP-Ikana'!$B$8-E62 -> 271.03 | H62: =F62-E62 -> 300.16953 | I62: =MAX(H62,G62) -> 300.16953 | J62: =IFERROR("PN"&SMALL(PN_list,COUNTIF(PN_list,"<"&I62*bar_per_m)+1),"> max PN") -> PN30 | K62: =IF(L62="no","end at tank",IF(H62<0,"NEGATIVE",IF(H62<p_min-0.005,"low","OK"))) -> OK | L62: yes
A63: Z4 WTP-Ikana | B63: WTP_IKANA_RM | C63: 1650.41 | D63: 1398.98 | E63: =D63-cover -> 1397.78 | F63: ='Z4 WTP-Ikana'!S18-'Z4 WTP-Ikana'!P18*C63/'Z4 WTP-Ikana'!G18 -> 1697.0616 | G63: ='Z4 WTP-Ikana'!$B$8-E63 -> 270.22 | H63: =F63-E63 -> 299.28163 | I63: =MAX(H63,G63) -> 299.28163 | J63: =IFERROR("PN"&SMALL(PN_list,COUNTIF(PN_list,"<"&I63*bar_per_m)+1),"> max PN") -> PN30 | K63: =IF(L63="no","end at tank",IF(H63<0,"NEGATIVE",IF(H63<p_min-0.005,"low","OK"))) -> OK | L63: yes
A64: Z4 WTP-Ikana | B64: WTP_IKANA_RM | C64: 1700.42 | D64: 1399.83 | E64: =D64-cover -> 1398.63 | F64: ='Z4 WTP-Ikana'!S18-'Z4 WTP-Ikana'!P18*C64/'Z4 WTP-Ikana'!G18 -> 1696.9837 | G64: ='Z4 WTP-Ikana'!$B$8-E64 -> 269.37 | H64: =F64-E64 -> 298.35373 | I64: =MAX(H64,G64) -> 298.35373 | J64: =IFERROR("PN"&SMALL(PN_list,COUNTIF(PN_list,"<"&I64*bar_per_m)+1),"> max PN") -> PN30 | K64: =IF(L64="no","end at tank",IF(H64<0,"NEGATIVE",IF(H64<p_min-0.005,"low","OK"))) -> OK | L64: yes
A65: Z4 WTP-Ikana | B65: WTP_IKANA_RM | C65: 1750.42 | D65: 1400.71 | E65: =D65-cover -> 1399.51 | F65: ='Z4 WTP-Ikana'!S18-'Z4 WTP-Ikana'!P18*C65/'Z4 WTP-Ikana'!G18 -> 1696.9059 | G65: ='Z4 WTP-Ikana'!$B$8-E65 -> 268.49 | H65: =F65-E65 -> 297.39585 | I65: =MAX(H65,G65) -> 297.39585 | J65: =IFERROR("PN"&SMALL(PN_list,COUNTIF(PN_list,"<"&I65*bar_per_m)+1),"> max PN") -> PN30 | K65: =IF(L65="no","end at tank",IF(H65<0,"NEGATIVE",IF(H65<p_min-0.005,"low","OK"))) -> OK | L65: yes
A66: Z4 WTP-Ikana | B66: WTP_IKANA_RM | C66: 1800.43 | D66: 1401.28 | E66: =D66-cover -> 1400.08 | F66: ='Z4 WTP-Ikana'!S18-'Z4 WTP-Ikana'!P18*C66/'Z4 WTP-Ikana'!G18 -> 1696.828 | G66: ='Z4 WTP-Ikana'!$B$8-E66 -> 267.92 | H66: =F66-E66 -> 296.74795 | I66: =MAX(H66,G66) -> 296.74795 | J66: =IFERROR("PN"&SMALL(PN_list,COUNTIF(PN_list,"<"&I66*bar_per_m)+1),"> max PN") -> PN30 | K66: =IF(L66="no","end at tank",IF(H66<0,"NEGATIVE",IF(H66<p_min-0.005,"low","OK"))) -> OK | L66: yes
A67: Z4 WTP-Ikana | B67: WTP_IKANA_RM | C67: 1850.44 | D67: 1402.51 | E67: =D67-cover -> 1401.31 | F67: ='Z4 WTP-Ikana'!S18-'Z4 WTP-Ikana'!P18*C67/'Z4 WTP-Ikana'!G18 -> 1696.7501 | G67: ='Z4 WTP-Ikana'!$B$8-E67 -> 266.69 | H67: =F67-E67 -> 295.44005 | I67: =MAX(H67,G67) -> 295.44005 | J67: =IFERROR("PN"&SMALL(PN_list,COUNTIF(PN_list,"<"&I67*bar_per_m)+1),"> max PN") -> PN30 | K67: =IF(L67="no","end at tank",IF(H67<0,"NEGATIVE",IF(H67<p_min-0.005,"low","OK"))) -> OK | L67: yes
A68: Z4 WTP-Ikana | B68: WTP_IKANA_RM | C68: 1886.63 | D68: 1403.71 | E68: =D68-cover -> 1402.51 | F68: ='Z4 WTP-Ikana'!S18-'Z4 WTP-Ikana'!P18*C68/'Z4 WTP-Ikana'!G18 -> 1696.6937 | G68: ='Z4 WTP-Ikana'!$B$8-E68 -> 265.49 | H68: =F68-E68 -> 294.18368 | I68: =MAX(H68,G68) -> 294.18368 | J68: =IFERROR("PN"&SMALL(PN_list,COUNTIF(PN_list,"<"&I68*bar_per_m)+1),"> max PN") -> PN30 | K68: =IF(L68="no","end at tank",IF(H68<0,"NEGATIVE",IF(H68<p_min-0.005,"low","OK"))) -> OK | L68: yes
A69: Z4 WTP-Ikana | B69: WTP_IKANA_RM | C69: 1936.63 | D69: 1403.85 | E69: =D69-cover -> 1402.65 | F69: ='Z4 WTP-Ikana'!S18-'Z4 WTP-Ikana'!P18*C69/'Z4 WTP-Ikana'!G18 -> 1696.6158 | G69: ='Z4 WTP-Ikana'!$B$8-E69 -> 265.35 | H69: =F69-E69 -> 293.9658 | I69: =MAX(H69,G69) -> 293.9658 | J69: =IFERROR("PN"&SMALL(PN_list,COUNTIF(PN_list,"<"&I69*bar_per_m)+1),"> max PN") -> PN30 | K69: =IF(L69="no","end at tank",IF(H69<0,"NEGATIVE",IF(H69<p_min-0.005,"low","OK"))) -> OK | L69: yes
A70: Z4 WTP-Ikana | B70: WTP_IKANA_RM | C70: 1986.66 | D70: 1402.19 | E70: =D70-cover -> 1400.99 | F70: ='Z4 WTP-Ikana'!S18-'Z4 WTP-Ikana'!P18*C70/'Z4 WTP-Ikana'!G18 -> 1696.5379 | G70: ='Z4 WTP-Ikana'!$B$8-E70 -> 267.01 | H70: =F70-E70 -> 295.54787 | I70: =MAX(H70,G70) -> 295.54787 | J70: =IFERROR("PN"&SMALL(PN_list,COUNTIF(PN_list,"<"&I70*bar_per_m)+1),"> max PN") -> PN30 | K70: =IF(L70="no","end at tank",IF(H70<0,"NEGATIVE",IF(H70<p_min-0.005,"low","OK"))) -> OK | L70: yes
A71: Z4 WTP-Ikana | B71: WTP_IKANA_RM | C71: 2036.66 | D71: 1402.74 | E71: =D71-cover -> 1401.54 | F71: ='Z4 WTP-Ikana'!S18-'Z4 WTP-Ikana'!P18*C71/'Z4 WTP-Ikana'!G18 -> 1696.46 | G71: ='Z4 WTP-Ikana'!$B$8-E71 -> 266.46 | H71: =F71-E71 -> 294.91999 | I71: =MAX(H71,G71) -> 294.91999 | J71: =IFERROR("PN"&SMALL(PN_list,COUNTIF(PN_list,"<"&I71*bar_per_m)+1),"> max PN") -> PN30 | K71: =IF(L71="no","end at tank",IF(H71<0,"NEGATIVE",IF(H71<p_min-0.005,"low","OK"))) -> OK | L71: yes
A72: Z4 WTP-Ikana | B72: WTP_IKANA_RM | C72: 2086.68 | D72: 1404.09 | E72: =D72-cover -> 1402.89 | F72: ='Z4 WTP-Ikana'!S18-'Z4 WTP-Ikana'!P18*C72/'Z4 WTP-Ikana'!G18 -> 1696.3821 | G72: ='Z4 WTP-Ikana'!$B$8-E72 -> 265.11 | H72: =F72-E72 -> 293.49207 | I72: =MAX(H72,G72) -> 293.49207 | J72: =IFERROR("PN"&SMALL(PN_list,COUNTIF(PN_list,"<"&I72*bar_per_m)+1),"> max PN") -> PN30 | K72: =IF(L72="no","end at tank",IF(H72<0,"NEGATIVE",IF(H72<p_min-0.005,"low","OK"))) -> OK | L72: yes
A73: Z4 WTP-Ikana | B73: WTP_IKANA_RM | C73: 2136.7 | D73: 1405.49 | E73: =D73-cover -> 1404.29 | F73: ='Z4 WTP-Ikana'!S18-'Z4 WTP-Ikana'!P18*C73/'Z4 WTP-Ikana'!G18 -> 1696.3042 | G73: ='Z4 WTP-Ikana'!$B$8-E73 -> 263.71 | H73: =F73-E73 -> 292.01416 | I73: =MAX(H73,G73) -> 292.01416 | J73: =IFERROR("PN"&SMALL(PN_list,COUNTIF(PN_list,"<"&I73*bar_per_m)+1),"> max PN") -> PN30 | K73: =IF(L73="no","end at tank",IF(H73<0,"NEGATIVE",IF(H73<p_min-0.005,"low","OK"))) -> OK | L73: yes
A74: Z4 WTP-Ikana | B74: WTP_IKANA_RM | C74: 2186.73 | D74: 1407.13 | E74: =D74-cover -> 1405.93 | F74: ='Z4 WTP-Ikana'!S18-'Z4 WTP-Ikana'!P18*C74/'Z4 WTP-Ikana'!G18 -> 1696.2262 | G74: ='Z4 WTP-Ikana'!$B$8-E74 -> 262.07 | H74: =F74-E74 -> 290.29623 | I74: =MAX(H74,G74) -> 290.29623 | J74: =IFERROR("PN"&SMALL(PN_list,COUNTIF(PN_list,"<"&I74*bar_per_m)+1),"> max PN") -> PN30 | K74: =IF(L74="no","end at tank",IF(H74<0,"NEGATIVE",IF(H74<p_min-0.005,"low","OK"))) -> OK | L74: yes
A75: Z4 WTP-Ikana | B75: WTP_IKANA_RM | C75: 2236.7 | D75: 1406.31 | E75: =D75-cover -> 1405.11 | F75: ='Z4 WTP-Ikana'!S18-'Z4 WTP-Ikana'!P18*C75/'Z4 WTP-Ikana'!G18 -> 1696.1484 | G75: ='Z4 WTP-Ikana'!$B$8-E75 -> 262.89 | H75: =F75-E75 -> 291.03839 | I75: =MAX(H75,G75) -> 291.03839 | J75: =IFERROR("PN"&SMALL(PN_list,COUNTIF(PN_list,"<"&I75*bar_per_m)+1),"> max PN") -> PN30 | K75: =IF(L75="no","end at tank",IF(H75<0,"NEGATIVE",IF(H75<p_min-0.005,"low","OK"))) -> OK | L75: yes
A76: Z4 WTP-Ikana | B76: WTP_IKANA_RM | C76: 2339.16 | D76: 1406.47 | E76: =D76-cover -> 1405.27 | F76: ='Z4 WTP-Ikana'!S18-'Z4 WTP-Ikana'!P18*C76/'Z4 WTP-Ikana'!G18 -> 1695.9888 | G76: ='Z4 WTP-Ikana'!$B$8-E76 -> 262.73 | H76: =F76-E76 -> 290.71879 | I76: =MAX(H76,G76) -> 290.71879 | J76: =IFERROR("PN"&SMALL(PN_list,COUNTIF(PN_list,"<"&I76*bar_per_m)+1),"> max PN") -> PN30 | K76: =IF(L76="no","end at tank",IF(H76<0,"NEGATIVE",IF(H76<p_min-0.005,"low","OK"))) -> OK | L76: yes
A77: Z4 WTP-Ikana | B77: WTP_IKANA_RM | C77: 2389.16 | D77: 1406 | E77: =D77-cover -> 1404.8 | F77: ='Z4 WTP-Ikana'!S18-'Z4 WTP-Ikana'!P18*C77/'Z4 WTP-Ikana'!G18 -> 1695.9109 | G77: ='Z4 WTP-Ikana'!$B$8-E77 -> 263.2 | H77: =F77-E77 -> 291.11091 | I77: =MAX(H77,G77) -> 291.11091 | J77: =IFERROR("PN"&SMALL(PN_list,COUNTIF(PN_list,"<"&I77*bar_per_m)+1),"> max PN") -> PN30 | K77: =IF(L77="no","end at tank",IF(H77<0,"NEGATIVE",IF(H77<p_min-0.005,"low","OK"))) -> OK | L77: yes
A78: Z4 WTP-Ikana | B78: WTP_IKANA_RM | C78: 2439.25 | D78: 1403.04 | E78: =D78-cover -> 1401.84 | F78: ='Z4 WTP-Ikana'!S18-'Z4 WTP-Ikana'!P18*C78/'Z4 WTP-Ikana'!G18 -> 1695.8329 | G78: ='Z4 WTP-Ikana'!$B$8-E78 -> 266.16 | H78: =F78-E78 -> 293.99289 | I78: =MAX(H78,G78) -> 293.99289 | J78: =IFERROR("PN"&SMALL(PN_list,COUNTIF(PN_list,"<"&I78*bar_per_m)+1),"> max PN") -> PN30 | K78: =IF(L78="no","end at tank",IF(H78<0,"NEGATIVE",IF(H78<p_min-0.005,"low","OK"))) -> OK | L78: yes
A79: Z4 WTP-Ikana | B79: WTP_IKANA_RM | C79: 2489.25 | D79: 1403.22 | E79: =D79-cover -> 1402.02 | F79: ='Z4 WTP-Ikana'!S18-'Z4 WTP-Ikana'!P18*C79/'Z4 WTP-Ikana'!G18 -> 1695.755 | G79: ='Z4 WTP-Ikana'!$B$8-E79 -> 265.98 | H79: =F79-E79 -> 293.735 | I79: =MAX(H79,G79) -> 293.735 | J79: =IFERROR("PN"&SMALL(PN_list,COUNTIF(PN_list,"<"&I79*bar_per_m)+1),"> max PN") -> PN30 | K79: =IF(L79="no","end at tank",IF(H79<0,"NEGATIVE",IF(H79<p_min-0.005,"low","OK"))) -> OK | L79: yes
A80: Z4 WTP-Ikana | B80: WTP_IKANA_RM | C80: 2539.26 | D80: 1403.75 | E80: =D80-cover -> 1402.55 | F80: ='Z4 WTP-Ikana'!S18-'Z4 WTP-Ikana'!P18*C80/'Z4 WTP-Ikana'!G18 -> 1695.6771 | G80: ='Z4 WTP-Ikana'!$B$8-E80 -> 265.45 | H80: =F80-E80 -> 293.1271 | I80: =MAX(H80,G80) -> 293.1271 | J80: =IFERROR("PN"&SMALL(PN_list,COUNTIF(PN_list,"<"&I80*bar_per_m)+1),"> max PN") -> PN30 | K80: =IF(L80="no","end at tank",IF(H80<0,"NEGATIVE",IF(H80<p_min-0.005,"low","OK"))) -> OK | L80: yes
A81: Z4 WTP-Ikana | B81: WTP_IKANA_RM | C81: 2589.26 | D81: 1403.8 | E81: =D81-cover -> 1402.6 | F81: ='Z4 WTP-Ikana'!S18-'Z4 WTP-Ikana'!P18*C81/'Z4 WTP-Ikana'!G18 -> 1695.5992 | G81: ='Z4 WTP-Ikana'!$B$8-E81 -> 265.4 | H81: =F81-E81 -> 292.99922 | I81: =MAX(H81,G81) -> 292.99922 | J81: =IFERROR("PN"&SMALL(PN_list,COUNTIF(PN_list,"<"&I81*bar_per_m)+1),"> max PN") -> PN30 | K81: =IF(L81="no","end at tank",IF(H81<0,"NEGATIVE",IF(H81<p_min-0.005,"low","OK"))) -> OK | L81: yes
A82: Z4 WTP-Ikana | B82: WTP_IKANA_RM | C82: 2626.71 | D82: 1402.97 | E82: =D82-cover -> 1401.77 | F82: ='Z4 WTP-Ikana'!S18-'Z4 WTP-Ikana'!P18*C82/'Z4 WTP-Ikana'!G18 -> 1695.5409 | G82: ='Z4 WTP-Ikana'!$B$8-E82 -> 266.23 | H82: =F82-E82 -> 293.77089 | I82: =MAX(H82,G82) -> 293.77089 | J82: =IFERROR("PN"&SMALL(PN_list,COUNTIF(PN_list,"<"&I82*bar_per_m)+1),"> max PN") -> PN30 | K82: =IF(L82="no","end at tank",IF(H82<0,"NEGATIVE",IF(H82<p_min-0.005,"low","OK"))) -> OK | L82: yes
A83: Z4 WTP-Ikana | B83: WTP_IKANA_RM | C83: 2676.72 | D83: 1403.86 | E83: =D83-cover -> 1402.66 | F83: ='Z4 WTP-Ikana'!S18-'Z4 WTP-Ikana'!P18*C83/'Z4 WTP-Ikana'!G18 -> 1695.463 | G83: ='Z4 WTP-Ikana'!$B$8-E83 -> 265.34 | H83: =F83-E83 -> 292.80299 | I83: =MAX(H83,G83) -> 292.80299 | J83: =IFERROR("PN"&SMALL(PN_list,COUNTIF(PN_list,"<"&I83*bar_per_m)+1),"> max PN") -> PN30 | K83: =IF(L83="no","end at tank",IF(H83<0,"NEGATIVE",IF(H83<p_min-0.005,"low","OK"))) -> OK | L83: yes
A84: Z4 WTP-Ikana | B84: WTP_IKANA_RM | C84: 2726.72 | D84: 1404.24 | E84: =D84-cover -> 1403.04 | F84: ='Z4 WTP-Ikana'!S18-'Z4 WTP-Ikana'!P18*C84/'Z4 WTP-Ikana'!G18 -> 1695.3851 | G84: ='Z4 WTP-Ikana'!$B$8-E84 -> 264.96 | H84: =F84-E84 -> 292.3451 | I84: =MAX(H84,G84) -> 292.3451 | J84: =IFERROR("PN"&SMALL(PN_list,COUNTIF(PN_list,"<"&I84*bar_per_m)+1),"> max PN") -> PN30 | K84: =IF(L84="no","end at tank",IF(H84<0,"NEGATIVE",IF(H84<p_min-0.005,"low","OK"))) -> OK | L84: yes
A85: Z4 WTP-Ikana | B85: WTP_IKANA_RM | C85: 2776.74 | D85: 1405.35 | E85: =D85-cover -> 1404.15 | F85: ='Z4 WTP-Ikana'!S18-'Z4 WTP-Ikana'!P18*C85/'Z4 WTP-Ikana'!G18 -> 1695.3072 | G85: ='Z4 WTP-Ikana'!$B$8-E85 -> 263.85 | H85: =F85-E85 -> 291.15719 | I85: =MAX(H85,G85) -> 291.15719 | J85: =IFERROR("PN"&SMALL(PN_list,COUNTIF(PN_list,"<"&I85*bar_per_m)+1),"> max PN") -> PN30 | K85: =IF(L85="no","end at tank",IF(H85<0,"NEGATIVE",IF(H85<p_min-0.005,"low","OK"))) -> OK | L85: yes
A86: Z4 WTP-Ikana | B86: WTP_IKANA_RM | C86: 2826.74 | D86: 1405.88 | E86: =D86-cover -> 1404.68 | F86: ='Z4 WTP-Ikana'!S18-'Z4 WTP-Ikana'!P18*C86/'Z4 WTP-Ikana'!G18 -> 1695.2293 | G86: ='Z4 WTP-Ikana'!$B$8-E86 -> 263.32 | H86: =F86-E86 -> 290.54931 | I86: =MAX(H86,G86) -> 290.54931 | J86: =IFERROR("PN"&SMALL(PN_list,COUNTIF(PN_list,"<"&I86*bar_per_m)+1),"> max PN") -> PN30 | K86: =IF(L86="no","end at tank",IF(H86<0,"NEGATIVE",IF(H86<p_min-0.005,"low","OK"))) -> OK | L86: yes
A87: Z4 WTP-Ikana | B87: WTP_IKANA_RM | C87: 2876.75 | D87: 1406.79 | E87: =D87-cover -> 1405.59 | F87: ='Z4 WTP-Ikana'!S18-'Z4 WTP-Ikana'!P18*C87/'Z4 WTP-Ikana'!G18 -> 1695.1514 | G87: ='Z4 WTP-Ikana'!$B$8-E87 -> 262.41 | H87: =F87-E87 -> 289.56141 | I87: =MAX(H87,G87) -> 289.56141 | J87: =IFERROR("PN"&SMALL(PN_list,COUNTIF(PN_list,"<"&I87*bar_per_m)+1),"> max PN") -> PN30 | K87: =IF(L87="no","end at tank",IF(H87<0,"NEGATIVE",IF(H87<p_min-0.005,"low","OK"))) -> OK | L87: yes
A88: Z4 WTP-Ikana | B88: WTP_IKANA_RM | C88: 2926.75 | D88: 1406.98 | E88: =D88-cover -> 1405.78 | F88: ='Z4 WTP-Ikana'!S18-'Z4 WTP-Ikana'!P18*C88/'Z4 WTP-Ikana'!G18 -> 1695.0735 | G88: ='Z4 WTP-Ikana'!$B$8-E88 -> 262.22 | H88: =F88-E88 -> 289.29352 | I88: =MAX(H88,G88) -> 289.29352 | J88: =IFERROR("PN"&SMALL(PN_list,COUNTIF(PN_list,"<"&I88*bar_per_m)+1),"> max PN") -> PN30 | K88: =IF(L88="no","end at tank",IF(H88<0,"NEGATIVE",IF(H88<p_min-0.005,"low","OK"))) -> OK | L88: yes
A89: Z4 WTP-Ikana | B89: WTP_IKANA_RM | C89: 2976.75 | D89: 1407.6 | E89: =D89-cover -> 1406.4 | F89: ='Z4 WTP-Ikana'!S18-'Z4 WTP-Ikana'!P18*C89/'Z4 WTP-Ikana'!G18 -> 1694.9956 | G89: ='Z4 WTP-Ikana'!$B$8-E89 -> 261.6 | H89: =F89-E89 -> 288.59564 | I89: =MAX(H89,G89) -> 288.59564 | J89: =IFERROR("PN"&SMALL(PN_list,COUNTIF(PN_list,"<"&I89*bar_per_m)+1),"> max PN") -> PN30 | K89: =IF(L89="no","end at tank",IF(H89<0,"NEGATIVE",IF(H89<p_min-0.005,"low","OK"))) -> OK | L89: yes
A90: Z4 WTP-Ikana | B90: WTP_IKANA_RM | C90: 3026.75 | D90: 1407.88 | E90: =D90-cover -> 1406.68 | F90: ='Z4 WTP-Ikana'!S18-'Z4 WTP-Ikana'!P18*C90/'Z4 WTP-Ikana'!G18 -> 1694.9178 | G90: ='Z4 WTP-Ikana'!$B$8-E90 -> 261.32 | H90: =F90-E90 -> 288.23776 | I90: =MAX(H90,G90) -> 288.23776 | J90: =IFERROR("PN"&SMALL(PN_list,COUNTIF(PN_list,"<"&I90*bar_per_m)+1),"> max PN") -> PN30 | K90: =IF(L90="no","end at tank",IF(H90<0,"NEGATIVE",IF(H90<p_min-0.005,"low","OK"))) -> OK | L90: yes
A91: Z4 WTP-Ikana | B91: WTP_IKANA_RM | C91: 3076.76 | D91: 1408.59 | E91: =D91-cover -> 1407.39 | F91: ='Z4 WTP-Ikana'!S18-'Z4 WTP-Ikana'!P18*C91/'Z4 WTP-Ikana'!G18 -> 1694.8399 | G91: ='Z4 WTP-Ikana'!$B$8-E91 -> 260.61 | H91: =F91-E91 -> 287.44986 | I91: =MAX(H91,G91) -> 287.44986 | J91: =IFERROR("PN"&SMALL(PN_list,COUNTIF(PN_list,"<"&I91*bar_per_m)+1),"> max PN") -> PN30 | K91: =IF(L91="no","end at tank",IF(H91<0,"NEGATIVE",IF(H91<p_min-0.005,"low","OK"))) -> OK | L91: yes
A92: Z4 WTP-Ikana | B92: WTP_IKANA_RM | C92: 3126.76 | D92: 1409.33 | E92: =D92-cover -> 1408.13 | F92: ='Z4 WTP-Ikana'!S18-'Z4 WTP-Ikana'!P18*C92/'Z4 WTP-Ikana'!G18 -> 1694.762 | G92: ='Z4 WTP-Ikana'!$B$8-E92 -> 259.87 | H92: =F92-E92 -> 286.63197 | I92: =MAX(H92,G92) -> 286.63197 | J92: =IFERROR("PN"&SMALL(PN_list,COUNTIF(PN_list,"<"&I92*bar_per_m)+1),"> max PN") -> PN30 | K92: =IF(L92="no","end at tank",IF(H92<0,"NEGATIVE",IF(H92<p_min-0.005,"low","OK"))) -> OK | L92: yes
A93: Z4 WTP-Ikana | B93: WTP_IKANA_RM | C93: 3176.77 | D93: 1410.25 | E93: =D93-cover -> 1409.05 | F93: ='Z4 WTP-Ikana'!S18-'Z4 WTP-Ikana'!P18*C93/'Z4 WTP-Ikana'!G18 -> 1694.6841 | G93: ='Z4 WTP-Ikana'!$B$8-E93 -> 258.95 | H93: =F93-E93 -> 285.63408 | I93: =MAX(H93,G93) -> 285.63408 | J93: =IFERROR("PN"&SMALL(PN_list,COUNTIF(PN_list,"<"&I93*bar_per_m)+1),"> max PN") -> PN30 | K93: =IF(L93="no","end at tank",IF(H93<0,"NEGATIVE",IF(H93<p_min-0.005,"low","OK"))) -> OK | L93: yes
A94: Z4 WTP-Ikana | B94: WTP_IKANA_RM | C94: 3226.78 | D94: 1410.87 | E94: =D94-cover -> 1409.67 | F94: ='Z4 WTP-Ikana'!S18-'Z4 WTP-Ikana'!P18*C94/'Z4 WTP-Ikana'!G18 -> 1694.6062 | G94: ='Z4 WTP-Ikana'!$B$8-E94 -> 258.33 | H94: =F94-E94 -> 284.93618 | I94: =MAX(H94,G94) -> 284.93618 | J94: =IFERROR("PN"&SMALL(PN_list,COUNTIF(PN_list,"<"&I94*bar_per_m)+1),"> max PN") -> PN30 | K94: =IF(L94="no","end at tank",IF(H94<0,"NEGATIVE",IF(H94<p_min-0.005,"low","OK"))) -> OK | L94: yes
A95: Z4 WTP-Ikana | B95: WTP_IKANA_RM | C95: 3276.78 | D95: 1411.46 | E95: =D95-cover -> 1410.26 | F95: ='Z4 WTP-Ikana'!S18-'Z4 WTP-Ikana'!P18*C95/'Z4 WTP-Ikana'!G18 -> 1694.5283 | G95: ='Z4 WTP-Ikana'!$B$8-E95 -> 257.74 | H95: =F95-E95 -> 284.26829 | I95: =MAX(H95,G95) -> 284.26829 | J95: =IFERROR("PN"&SMALL(PN_list,COUNTIF(PN_list,"<"&I95*bar_per_m)+1),"> max PN") -> PN30 | K95: =IF(L95="no","end at tank",IF(H95<0,"NEGATIVE",IF(H95<p_min-0.005,"low","OK"))) -> OK | L95: yes
A96: Z4 WTP-Ikana | B96: WTP_IKANA_RM | C96: 3326.79 | D96: 1412.28 | E96: =D96-cover -> 1411.08 | F96: ='Z4 WTP-Ikana'!S18-'Z4 WTP-Ikana'!P18*C96/'Z4 WTP-Ikana'!G18 -> 1694.4504 | G96: ='Z4 WTP-Ikana'!$B$8-E96 -> 256.92 | H96: =F96-E96 -> 283.37039 | I96: =MAX(H96,G96) -> 283.37039 | J96: =IFERROR("PN"&SMALL(PN_list,COUNTIF(PN_list,"<"&I96*bar_per_m)+1),"> max PN") -> PN30 | K96: =IF(L96="no","end at tank",IF(H96<0,"NEGATIVE",IF(H96<p_min-0.005,"low","OK"))) -> OK | L96: yes
A97: Z4 WTP-Ikana | B97: WTP_IKANA_RM | C97: 3376.79 | D97: 1412.95 | E97: =D97-cover -> 1411.75 | F97: ='Z4 WTP-Ikana'!S18-'Z4 WTP-Ikana'!P18*C97/'Z4 WTP-Ikana'!G18 -> 1694.3725 | G97: ='Z4 WTP-Ikana'!$B$8-E97 -> 256.25 | H97: =F97-E97 -> 282.62251 | I97: =MAX(H97,G97) -> 282.62251 | J97: =IFERROR("PN"&SMALL(PN_list,COUNTIF(PN_list,"<"&I97*bar_per_m)+1),"> max PN") -> PN30 | K97: =IF(L97="no","end at tank",IF(H97<0,"NEGATIVE",IF(H97<p_min-0.005,"low","OK"))) -> OK | L97: yes
A98: Z4 WTP-Ikana | B98: WTP_IKANA_RM | C98: 3426.79 | D98: 1413.43 | E98: =D98-cover -> 1412.23 | F98: ='Z4 WTP-Ikana'!S18-'Z4 WTP-Ikana'!P18*C98/'Z4 WTP-Ikana'!G18 -> 1694.2946 | G98: ='Z4 WTP-Ikana'!$B$8-E98 -> 255.77 | H98: =F98-E98 -> 282.06463 | I98: =MAX(H98,G98) -> 282.06463 | J98: =IFERROR("PN"&SMALL(PN_list,COUNTIF(PN_list,"<"&I98*bar_per_m)+1),"> max PN") -> PN30 | K98: =IF(L98="no","end at tank",IF(H98<0,"NEGATIVE",IF(H98<p_min-0.005,"low","OK"))) -> OK | L98: yes
A99: Z4 WTP-Ikana | B99: WTP_IKANA_RM | C99: 3476.8 | D99: 1414.25 | E99: =D99-cover -> 1413.05 | F99: ='Z4 WTP-Ikana'!S18-'Z4 WTP-Ikana'!P18*C99/'Z4 WTP-Ikana'!G18 -> 1694.2167 | G99: ='Z4 WTP-Ikana'!$B$8-E99 -> 254.95 | H99: =F99-E99 -> 281.16673 | I99: =MAX(H99,G99) -> 281.16673 | J99: =IFERROR("PN"&SMALL(PN_list,COUNTIF(PN_list,"<"&I99*bar_per_m)+1),"> max PN") -> PN30 | K99: =IF(L99="no","end at tank",IF(H99<0,"NEGATIVE",IF(H99<p_min-0.005,"low","OK"))) -> OK | L99: yes
A100: Z4 WTP-Ikana | B100: WTP_IKANA_RM | C100: 3526.8 | D100: 1414.68 | E100: =D100-cover -> 1413.48 | F100: ='Z4 WTP-Ikana'!S18-'Z4 WTP-Ikana'!P18*C100/'Z4 WTP-Ikana'!G18 -> 1694.1388 | G100: ='Z4 WTP-Ikana'!$B$8-E100 -> 254.52 | H100: =F100-E100 -> 280.65885 | I100: =MAX(H100,G100) -> 280.65885 | J100: =IFERROR("PN"&SMALL(PN_list,COUNTIF(PN_list,"<"&I100*bar_per_m)+1),"> max PN") -> PN30 | K100: =IF(L100="no","end at tank",IF(H100<0,"NEGATIVE",IF(H100<p_min-0.005,"low","OK"))) -> OK | L100: yes
A101: Z4 WTP-Ikana | B101: WTP_IKANA_RM | C101: 3576.14 | D101: 1415.15 | E101: =D101-cover -> 1413.95 | F101: ='Z4 WTP-Ikana'!S18-'Z4 WTP-Ikana'!P18*C101/'Z4 WTP-Ikana'!G18 -> 1694.062 | G101: ='Z4 WTP-Ikana'!$B$8-E101 -> 254.05 | H101: =F101-E101 -> 280.11199 | I101: =MAX(H101,G101) -> 280.11199 | J101: =IFERROR("PN"&SMALL(PN_list,COUNTIF(PN_list,"<"&I101*bar_per_m)+1),"> max PN") -> PN30 | K101: =IF(L101="no","end at tank",IF(H101<0,"NEGATIVE",IF(H101<p_min-0.005,"low","OK"))) -> OK | L101: yes
...
